Workbook
Name DOLARIN: [1]ANALISIS!$H$2
Name ST: [2]Datos!$C$2:$C$7

Sheet Entregable
A1: COTIZACIÓN PLANTA METALES SIGRAMA:
A3: PROYECTO: | B3: COTIZAZION SIGRAMA 20837 - 20961 | H3: No. Cot: | I3: 005
A4: FECHA REQ.: | B4: 46077 | H4: Fecha Cot.: | I4: 46077
A5: ATENCIÓN: | B5: ING. JOSUE MESTA | H5: Piezas: | I5: =SUM(G11:G22) -> 720
A6: ELABORADO POR: | B6: ING. JESÚS A. MORALES L.
A7: PRESENTAMOS A SU AMABLE CONSIDERACIÓN:
A9: PARTIDA | B9: PARTIDA | F9: UNIDAD | G9: CANT. | H9: P.U. | I9: IMPORTE | L9: 16
A10: 1 | B10: =+'REQ. PINTADO'!B3 -> 12-6010-01 | F10: PZA | G10: =+'REQ. PINTADO'!C3 -> 48 | H10: =+ROUND(Q10,2) -> 86.88 | I10: =+H10*G10 -> 4170.24 | Q10: =+'REQ. PINTADO'!J3 -> 86.877478
A11: 2 | B11: =+'REQ. PINTADO'!B4 -> 11-D-3402-01 | F11: PZA | G11: =+'REQ. PINTADO'!C4 -> 48 | H11: =+ROUND(Q11,2) -> 134.22 | I11: =+H11*G11 -> 6442.56 | Q11: =+'REQ. PINTADO'!J4 -> 134.22
A12: 3 | B12: =+'REQ. PINTADO'!B5 -> 17-D-6043-02 | F12: PZA | G12: =+'REQ. PINTADO'!C5 -> 96 | H12: =+ROUND(Q12,2) -> 122.83 | I12: =+H12*G12 -> 11791.68 | Q12: =+'REQ. PINTADO'!J5 -> 122.83364
A13: 4 | B13: =+'REQ. PINTADO'!B6 -> 17-D-6047-01 | F13: PZA | G13: =+'REQ. PINTADO'!C6 -> 48 | H13: =+ROUND(Q13,2) -> 80.7 | I13: =+H13*G13 -> 3873.6 | Q13: =+'REQ. PINTADO'!J6 -> 80.697706
A14: 5 | B14: =+'REQ. PINTADO'!B7 -> 12-6355-03 | F14: PZA | G14: =+'REQ. PINTADO'!C7 -> 48 | H14: =+ROUND(Q14,2) -> 198.67 | I14: =+H14*G14 -> 9536.16 | Q14: =+'REQ. PINTADO'!J7 -> 198.67165
A15: 6 | B15: =+'REQ. PINTADO'!B8 -> PP21340-01 | F15: PZA | G15: =+'REQ. PINTADO'!C8 -> 48 | H15: =+ROUND(Q15,2) -> 172.35 | I15: =+H15*G15 -> 8272.8 | Q15: =+'REQ. PINTADO'!J8 -> 172.35241
A16: 7 | B16: =+'REQ. PINTADO'!B9 -> PP22121-01 | F16: PZA | G16: =+'REQ. PINTADO'!C9 -> 48 | H16: =+ROUND(Q16,2) -> 233.42 | I16: =+H16*G16 -> 11204.16 | Q16: =+'REQ. PINTADO'!J9 -> 233.41593
A17: 8 | B17: =+'REQ. PINTADO'!B10 -> 11-D-3408-01 | F17: PZA | G17: =+'REQ. PINTADO'!C10 -> 96 | H17: =+ROUND(Q17,2) -> 69.08 | I17: =+H17*G17 -> 6631.68 | Q17: =+'REQ. PINTADO'!J10 -> 69.078616
A18: 9 | B18: =+'REQ. PINTADO'!B11 -> PP21341-12 | F18: PZA | G18: =+'REQ. PINTADO'!C11 -> 48 | H18: =+ROUND(Q18,2) -> 198.9 | I18: =+H18*G18 -> 9547.2 | Q18: =+'REQ. PINTADO'!J11 -> 198.90167
A19: 10 | B19: =+'REQ. PINTADO'!B12 -> 12-6010-09 | F19: PZA | G19: =+'REQ. PINTADO'!C12 -> 48 | H19: =+ROUND(Q19,2) -> 115.32 | I19: =+H19*G19 -> 5535.36 | Q19: =+'REQ. PINTADO'!J12 -> 115.31857
A20: 11 | B20: =+'REQ. PINTADO'!B13 -> PP22124-01 | F20: PZA | G20: =+'REQ. PINTADO'!C13 -> 48 | H20: =+ROUND(Q20,2) -> 253.35 | I20: =+H20*G20 -> 12160.8 | Q20: =+'REQ. PINTADO'!J13 -> 253.34758
A21: 12 | B21: =+'REQ. PINTADO'!B14 -> 11-D-3409-02 | F21: PZA | G21: =+'REQ. PINTADO'!C14 -> 144 | H21: =+ROUND(Q21,2) -> 129.08 | I21: =+H21*G21 -> 18587.52 | Q21: =+'REQ. PINTADO'!J14 -> 129.08107
F22: SUB-TOTAL | I22: =SUM(I10:I21) -> 107753.76 | K22: =+I22*16 -> 1724060.2
H23: I.V.A. | I23: =+I22*0.16 -> 17240.602
F24: TOTAL | I24: =+I23+I22 -> 124994.36
C26: Entrega | D26: 1 | E26: 2 | F26: 3
C27: Real | D27: =+TODAY()+10 -> 46087 | E27: =+D27+10 -> 46097 | F27: =+F28 -> 46113
C28: Requerido | D28: 46076 | E28: 46094 | F28: 46113
C29: Piezas | D29: 288 | E29: 272 | F29: 208
B31: TIEMPO DE ENTREGA: | D31: AJUSTES AL PROGRAMA…!!!
B32: PRIMER PARCIALIDAD: | D32: =+D27 -> 46087
B33: ENTREGA FINAL: | D33: =+F27 -> 46113
B34: jesus.morales@sigrama.com.mx
B35: cel: 871.7954493
B36: DIR. PLANTA METALES

Sheet Analisis
B2: ANALISIS DE COSTO PROYECTO | I2: Criterios
D3: galvanizado | F3: pintuta
B4: 1 | C4: MATERIAL | D4: =+'REQ GALV'!C136 -> 2081961.4 | E4: =+D4/D8 -> 0.40954748 | F4: =+'REQ. PINTADO'!K15 -> 26248.904 | G4: =+F4/F8 -> 0.30450093 | I4: Desperdicio | J4: 0.33
B5: 2 | C5: CORTE LASER | D5: =+'REQ GALV'!D136 -> 1794654 | E5: =+D5/D8 -> 0.35303057 | F5: =+'REQ. PINTADO'!L15 -> 8930.131 | G5: =+F5/F8 -> 0.10359416 | I5: Tarifa | J5: T5.0
B6: 3 | C6: DOBLEZ | D6: =+'REQ GALV'!E136 -> 1206950 | E6: =+D6/D8 -> 0.23742195 | F6: =+'REQ. PINTADO'!M15 -> 45600 | G6: =+F6/F8 -> 0.5289837 | I6: Doblez Precio x Golpe | J6: 25
B7: 4 | C7: PINTURA | D7: 0 | E7: =+D7/D8 -> 0 | F7: =+'REQ. PINTADO'!N15 -> 5424 | G7: =+F7/F8 -> 0.062921219 | I7: Punzon Precio x Golpe | J7: 25
C8: $ Costo | D8: =SUM(D4:D7) -> 5083565.4 | E8: 1 | F8: =SUM(F4:F7) -> 86203.035 | G8: 1 | I8: Pintura | J8: 106.54762
C9: Margen de Utilidad | D9: =+D10-D8 -> 1270891.3 | E9: 0.2 | F9: =+F10-F8 -> 21550.759 | G9: =+E9 -> 0.2
C10: Precio Venta | D10: =+D8/(1-E9) -> 6354456.7 | F10: =+F8/(1-G9) -> 107753.79

Sheet REQ GALV
A1: PARTE | B1: CANTIDAD | C1: COSTO | F1: COSTO TOTAL | G1: P.V. | H1: TOTAL
C2: MAT | D2: LASER | E2: DOBLEZ
A3: 11-6284-01 | B3: 210 | C3: =+VLOOKUP(A3,'COT. GAL'!B:AC,11,FALSE) -> 17.858649 | D3: =+VLOOKUP(A3,'COT. GAL'!B:AC,20,FALSE)+VLOOKUP(A3,'COT. GAL'!B:AC,24,FALSE) -> 32.622044 | E3: =+VLOOKUP(A3,'COT. GAL'!B:AE,27,FALSE)+VLOOKUP(A3,'COT. GAL'!B:AE,30,FALSE) -> 100 | F3: =+C3+D3+E3 -> 150.48069 | G3: =+F3/(1-Analisis!$E$9) -> 188.10087 | H3: =+G3*B3 -> 39501.182
A4: 11-6285-01 | B4: 1217 | C4: =+VLOOKUP(A4,'COT. GAL'!B:AC,11,FALSE) -> 15.169093 | D4: =+VLOOKUP(A4,'COT. GAL'!B:AC,20,FALSE)+VLOOKUP(A4,'COT. GAL'!B:AC,24,FALSE) -> 34.885165 | E4: =+VLOOKUP(A4,'COT. GAL'!B:AE,27,FALSE)+VLOOKUP(A4,'COT. GAL'!B:AE,30,FALSE) -> 100 | F4: =+C4+D4+E4 -> 150.05426 | G4: =+F4/(1-Analisis!$E$9) -> 187.56782 | H4: =+G4*B4 -> 228270.04
A5: 11-6355-01 | B5: 180 | C5: =+VLOOKUP(A5,'COT. GAL'!B:AC,11,FALSE) -> 12.3424 | D5: =+VLOOKUP(A5,'COT. GAL'!B:AC,20,FALSE)+VLOOKUP(A5,'COT. GAL'!B:AC,24,FALSE) -> 33.668639 | E5: =+VLOOKUP(A5,'COT. GAL'!B:AE,27,FALSE)+VLOOKUP(A5,'COT. GAL'!B:AE,30,FALSE) -> 100 | F5: =+C5+D5+E5 -> 146.01104 | G5: =+F5/(1-Analisis!$E$9) -> 182.5138 | H5: =+G5*B5 -> 32852.484
A6: 11-6474-01 | B6: 120 | C6: =+VLOOKUP(A6,'COT. GAL'!B:AC,11,FALSE) -> 29.250358 | D6: =+VLOOKUP(A6,'COT. GAL'!B:AC,20,FALSE)+VLOOKUP(A6,'COT. GAL'!B:AC,24,FALSE) -> 41.593287 | E6: =+VLOOKUP(A6,'COT. GAL'!B:AE,27,FALSE)+VLOOKUP(A6,'COT. GAL'!B:AE,30,FALSE) -> 100 | F6: =+C6+D6+E6 -> 170.84364 | G6: =+F6/(1-Analisis!$E$9) -> 213.55456 | H6: =+G6*B6 -> 25626.547
A7: 11-A-6030-05 | B7: 30 | C7: =+VLOOKUP(A7,'COT. GAL'!B:AC,11,FALSE) -> 5.0983333 | D7: =+VLOOKUP(A7,'COT. GAL'!B:AC,20,FALSE)+VLOOKUP(A7,'COT. GAL'!B:AC,24,FALSE) -> 20.106499 | E7: =+VLOOKUP(A7,'COT. GAL'!B:AE,27,FALSE)+VLOOKUP(A7,'COT. GAL'!B:AE,30,FALSE) -> 0 | F7: =+C7+D7+E7 -> 25.204832 | G7: =+F7/(1-Analisis!$E$9) -> 31.50604 | H7: =+G7*B7 -> 945.1812
A8: 11-A-6068-01 | B8: 150 | C8: =+VLOOKUP(A8,'COT. GAL'!B:AC,11,FALSE) -> 5.1932344 | D8: =+VLOOKUP(A8,'COT. GAL'!B:AC,20,FALSE)+VLOOKUP(A8,'COT. GAL'!B:AC,24,FALSE) -> 18.346364 | E8: =+VLOOKUP(A8,'COT. GAL'!B:AE,27,FALSE)+VLOOKUP(A8,'COT. GAL'!B:AE,30,FALSE) -> 0 | F8: =+C8+D8+E8 -> 23.539598 | G8: =+F8/(1-Analisis!$E$9) -> 29.424498 | H8: =+G8*B8 -> 4413.6747
A9: 11-A-6160-01 | B9: 120 | C9: =+VLOOKUP(A9,'COT. GAL'!B:AC,11,FALSE) -> 4.0454167 | D9: =+VLOOKUP(A9,'COT. GAL'!B:AC,20,FALSE)+VLOOKUP(A9,'COT. GAL'!B:AC,24,FALSE) -> 34.048484 | E9: =+VLOOKUP(A9,'COT. GAL'!B:AE,27,FALSE)+VLOOKUP(A9,'COT. GAL'!B:AE,30,FALSE) -> 25 | F9: =+C9+D9+E9 -> 63.093901 | G9: =+F9/(1-Analisis!$E$9) -> 78.867376 | H9: =+G9*B9 -> 9464.0851
A10: 11-A-6201-01 | B10: 4800 | C10: =+VLOOKUP(A10,'COT. GAL'!B:AC,11,FALSE) -> 24.460667 | D10: =+VLOOKUP(A10,'COT. GAL'!B:AC,20,FALSE)+VLOOKUP(A10,'COT. GAL'!B:AC,24,FALSE) -> 47.417937 | E10: =+VLOOKUP(A10,'COT. GAL'!B:AE,27,FALSE)+VLOOKUP(A10,'COT. GAL'!B:AE,30,FALSE) -> 0 | F10: =+C10+D10+E10 -> 71.878604 | G10: =+F10/(1-Analisis!$E$9) -> 89.848256 | H10: =+G10*B10 -> 431271.63
A11: 11-A-6271-01 | B11: 510 | C11: =+VLOOKUP(A11,'COT. GAL'!B:AC,11,FALSE) -> 15.79375 | D11: =+VLOOKUP(A11,'COT. GAL'!B:AC,20,FALSE)+VLOOKUP(A11,'COT. GAL'!B:AC,24,FALSE) -> 27.984357 | E11: =+VLOOKUP(A11,'COT. GAL'!B:AE,27,FALSE)+VLOOKUP(A11,'COT. GAL'!B:AE,30,FALSE) -> 0 | F11: =+C11+D11+E11 -> 43.778107 | G11: =+F11/(1-Analisis!$E$9) -> 54.722633 | H11: =+G11*B11 -> 27908.543
A12: 11-A-6340-01 | B12: 2400 | C12: =+VLOOKUP(A12,'COT. GAL'!B:AC,11,FALSE) -> 32.022521 | D12: =+VLOOKUP(A12,'COT. GAL'!B:AC,20,FALSE)+VLOOKUP(A12,'COT. GAL'!B:AC,24,FALSE) -> 48.459003 | E12: =+VLOOKUP(A12,'COT. GAL'!B:AE,27,FALSE)+VLOOKUP(A12,'COT. GAL'!B:AE,30,FALSE) -> 0 | F12: =+C12+D12+E12 -> 80.481524 | G12: =+F12/(1-Analisis!$E$9) -> 100.6019 | H12: =+G12*B12 -> 241444.57
A13: 11-D-6195-03 | B13: 450 | C13: =+VLOOKUP(A13,'COT. GAL'!B:AC,11,FALSE) -> 7.2928333 | D13: =+VLOOKUP(A13,'COT. GAL'!B:AC,20,FALSE)+VLOOKUP(A13,'COT. GAL'!B:AC,24,FALSE) -> 30.113917 | E13: =+VLOOKUP(A13,'COT. GAL'!B:AE,27,FALSE)+VLOOKUP(A13,'COT. GAL'!B:AE,30,FALSE) -> 0 | F13: =+C13+D13+E13 -> 37.40675 | G13: =+F13/(1-Analisis!$E$9) -> 46.758437 | H13: =+G13*B13 -> 21041.297
A14: 11-D-6218-01 | B14: 45 | C14: =+VLOOKUP(A14,'COT. GAL'!B:AC,11,FALSE) -> 68.83282 | D14: =+VLOOKUP(A14,'COT. GAL'!B:AC,20,FALSE)+VLOOKUP(A14,'COT. GAL'!B:AC,24,FALSE) -> 56.858352 | E14: =+VLOOKUP(A14,'COT. GAL'!B:AE,27,FALSE)+VLOOKUP(A14,'COT. GAL'!B:AE,30,FALSE) -> 25 | F14: =+C14+D14+E14 -> 150.69117 | G14: =+F14/(1-Analisis!$E$9) -> 188.36397 | H14: =+G14*B14 -> 8476.3784
... A135: PP7722-13 | B135: 30 | C135: =+VLOOKUP(A135,'COT. GAL'!B:AC,11,FALSE) -> 129.5323 | D135: =+VLOOKUP(A135,'COT. GAL'!B:AC,20,FALSE)+VLOOKUP(A135,'COT. GAL'!B:AC,24,FALSE) -> 91.475225 | E135: =+VLOOKUP(A135,'COT. GAL'!B:AE,27,FALSE)+VLOOKUP(A135,'COT. GAL'!B:AE,30,FALSE) -> 100 | F135: =+C135+D135+E135 -> 321.00752 | G135: =+F135/(1-Analisis!$E$9) -> 401.2594 | H135: =+G135*B135 -> 12037.782
C136: =+SUMPRODUCT(C3:C135,B3:B135) -> 2081961.4 | D136: =+SUMPRODUCT(D3:D135,B3:B135) -> 1794654 | E136: =+SUMPRODUCT(E3:E135,B3:B135) -> 1206950 | F136: =SUM(C136:E136) -> 5083565.4 | H136: =SUM(H3:H135) -> 6354456.7

Sheet COT. GAL
A1: No. | B1: Numero Parte | C1: Cantidad | D1: P.F. | E1: Material | F1: Acabado | G1: Ancho (in) | H1: Longitud (in) | I1: Espesor (in) | J1: Peso (lb) | K1: $ / Kg | L1: $ Material | M1: TARIFA | N1: $/Hr | O1: Material | P1: Cal. Corte | Q1: Velocidad | R1: Tarifa $/mm | S1: Tiempo corte laser | T1: Long corte (mm) | U1: $ Corte | V1: Objetos | W1: Tiempo por Objeto | X1: Total Tiempo x Objeto | Y1: $ Objetos | Z1: Golpes | AA1: Tiempo (min) | AB1: $ Golpes | AC1: Punzonado | AD1: Tiempo (min) | AE1: $ Punz. | AF1: COSTO | AG1: P.V. | AH1: TOTAL | AI1: MATERIAL
A2: 1 | B2: P12365-272 | C2: =IFERROR(VLOOKUP(B2,'REQ GALV'!A:B,2,0),0) -> 0 | D2: =+AG2 -> 1205.3542 | E2: 12GA | F2: DECAPADO | G2: 23.325 | H2: 41.02 | I2: 0.105 | J2: 28.408 | K2: =+L2*2.2/J2 -> 54.749287 | L2: =+VLOOKUP(E2,Material!$H$2:$M$17,6,FALSE)*G2*H2*(1+Material!$K$14) -> 706.96261 | M2: =+Analisis!$J$5 -> T5.0 | N2: =+VLOOKUP(M2,Material!$A$3:$B$58,2,FALSE) -> 5000 | O2: ACERO A36 | P2: Cal 12 | Q2: =+IF(O2="ACERO A36",VLOOKUP(P2,'Velocidades Std 1500 w'!$B$2:$F$15,5,FALSE),IF(O2="INOXIDABLE",VLOOKUP(P2,'Velocidades Std 1500 w'!$B$17:$F$28,5,FALSE),IF(O2="ALUMINIO",VLOOKUP(P2,'Velocidades Std 1500 w'!$B$30:$F$38,5,FALSE)))) -> 4.3859649e-06 | R2: =+Q2*N2 -> 0.021929825 | S2: =+Q2*T2*3600 -> 62.150926 | T2: =(+H2*2+G2*2+V2*1.05)*25.4*1.05 -> 3936.2253 | U2: =+T2*R2 -> 86.32073 | V2: 18 | W2: =+IF(O2="ACERO A36",VLOOKUP(P2,'Tiempo Objeto'!$B$2:$C$12,2,FALSE),IF(O2="INOXIDABLE",VLOOKUP(P2,'Tiempo Objeto'!$B$14:$C$22,2,FALSE),IF(O2="ALUMINIO",VLOOKUP(P2,'Tiempo Objeto'!$B$24:$C$32,2,FALSE)))) -> 1.84 | X2: =+W2*V2 -> 33.12 | Y2: =+X2*N2/3600 -> 46 | Z2: 5 | AA2: =30*Z2+Z2*$C2*1.5 -> 150 | AB2: =+Z2*Analisis!$J$6 -> 125 | AC2: 0 | AD2: =30*AC2+AC2*$C2*1.5 -> 0 | AE2: =+AD2*Analisis!$J$7 -> 0 | AF2: =+L2+U2+Y2+AB2+AE2 -> 964.28334 | AG2: =+AF2/(1-Analisis!$E$9) -> 1205.3542 | AH2: =+AG2*C2 -> 0
A3: 2 | B3: P12365-311 | C3: =IFERROR(VLOOKUP(B3,'REQ GALV'!A:B,2,0),0) -> 0 | D3: =+AG3 -> 2182.523 | E3: 12GA | F3: DECAPADO | G3: 19.04 | H3: 39.39 | I3: 0.105 | J3: 28.24 | K3: =+L3*2.2/J3 -> 43.170795 | L3: =+VLOOKUP(E3,Material!$H$2:$M$17,6,FALSE)*G3*H3*(1+Material!$K$14) -> 554.15603 | M3: =+Analisis!$J$5 -> T5.0 | N3: =+VLOOKUP(M3,Material!$A$3:$B$58,2,FALSE) -> 5000 | O3: ACERO A36 | P3: Cal 12 | Q3: =+IF(O3="ACERO A36",VLOOKUP(P3,'Velocidades Std 1500 w'!$B$2:$F$15,5,FALSE),IF(O3="INOXIDABLE",VLOOKUP(P3,'Velocidades Std 1500 w'!$B$17:$F$28,5,FALSE),IF(O3="ALUMINIO",VLOOKUP(P3,'Velocidades Std 1500 w'!$B$30:$F$38,5,FALSE)))) -> 4.3859649e-06 | R3: =+Q3*N3 -> 0.021929825 | S3: =+Q3*T3*3600 -> 251.34089 | T3: =(+H3*2+G3*2+V3*1.5)*25.4*1.05 -> 15918.256 | U3: =+T3*R3 -> 349.08457 | V3: 320 | W3: =+IF(O3="ACERO A36",VLOOKUP(P3,'Tiempo Objeto'!$B$2:$C$12,2,FALSE),IF(O3="INOXIDABLE",VLOOKUP(P3,'Tiempo Objeto'!$B$14:$C$22,2,FALSE),IF(O3="ALUMINIO",VLOOKUP(P3,'Tiempo Objeto'!$B$24:$C$32,2,FALSE)))) -> 1.84 | X3: =+W3*V3 -> 588.8 | Y3: =+X3*N3/3600 -> 817.77778 | Z3: 1 | AA3: =30*Z3+Z3*$C3*1.5 -> 30 | AB3: =+Z3*Analisis!$J$6 -> 25 | AC3: 0 | AD3: =30*AC3+AC3*$C3*1.5 -> 0 | AE3: =+AD3*Analisis!$J$7 -> 0 | AF3: =+L3+U3+Y3+AB3+AE3 -> 1746.0184 | AG3: =+AF3/(1-Analisis!$E$9) -> 2182.523 | AH3: =+AG3*C3 -> 0
A4: 2 | B4: 11-D-9570-01 | C4: =IFERROR(VLOOKUP(B4,'REQ GALV'!A:B,2,0),0) -> 0 | D4: =+AG4 -> 220.64871 | E4: 12GA | F4: DECAPADO | G4: 5 | H4: 11 | I4: 0.105 | J4: 28.24 | K4: =+L4*2.2/J4 -> 3.1659191 | L4: =+VLOOKUP(E4,Material!$H$2:$M$17,6,FALSE)*G4*H4*(1+Material!$K$14) -> 40.638889 | M4: =+Analisis!$J$5 -> T5.0 | N4: =+VLOOKUP(M4,Material!$A$3:$B$58,2,FALSE) -> 5000 | O4: ACERO A36 | P4: Cal 12 | Q4: =+IF(O4="ACERO A36",VLOOKUP(P4,'Velocidades Std 1500 w'!$B$2:$F$15,5,FALSE),IF(O4="INOXIDABLE",VLOOKUP(P4,'Velocidades Std 1500 w'!$B$17:$F$28,5,FALSE),IF(O4="ALUMINIO",VLOOKUP(P4,'Velocidades Std 1500 w'!$B$30:$F$38,5,FALSE)))) -> 4.3859649e-06 | R4: =+Q4*N4 -> 0.021929825 | S4: =+Q4*T4*3600 -> 16.633658 | T4: =(+H4*2+G4*2+V4*1.5)*25.4*1.05 -> 1053.465 | U4: =+T4*R4 -> 23.102303 | V4: 5 | W4: =+IF(O4="ACERO A36",VLOOKUP(P4,'Tiempo Objeto'!$B$2:$C$12,2,FALSE),IF(O4="INOXIDABLE",VLOOKUP(P4,'Tiempo Objeto'!$B$14:$C$22,2,FALSE),IF(O4="ALUMINIO",VLOOKUP(P4,'Tiempo Objeto'!$B$24:$C$32,2,FALSE)))) -> 1.84 | X4: =+W4*V4 -> 9.2 | Y4: =+X4*N4/3600 -> 12.777778 | Z4: 4 | AA4: =30*Z4+Z4*$C4*1.5 -> 120 | AB4: =+Z4*Analisis!$J$6 -> 100 | AC4: 0 | AD4: =30*AC4+AC4*$C4*1.5 -> 0 | AE4: =+AD4*Analisis!$J$7 -> 0 | AF4: =+L4+U4+Y4+AB4+AE4 -> 176.51897 | AG4: =+AF4/(1-Analisis!$E$9) -> 220.64871 | AH4: =+AG4*C4 -> 0
A5: 2 | B5: PP14252-17-MO | C5: =IFERROR(VLOOKUP(B5,'REQ GALV'!A:B,2,0),0) -> 0 | D5: =+AG5 -> 556.43267 | E5: 188al | F5: DECAPADO | G5: 5.048 | H5: 40 | I5: 0.105 | J5: 28.24 | K5: =+L5*2.2/J5 -> 17.434429 | L5: =+VLOOKUP(E5,Material!$H$2:$M$17,6,FALSE)*G5*H5*(1+Material!$K$14) -> 223.79467 | M5: =+Analisis!$J$5 -> T5.0 | N5: =+VLOOKUP(M5,Material!$A$3:$B$58,2,FALSE) -> 5000 | O5: ACERO A36 | P5: Cal 12 | Q5: =+IF(O5="ACERO A36",VLOOKUP(P5,'Velocidades Std 1500 w'!$B$2:$F$15,5,FALSE),IF(O5="INOXIDABLE",VLOOKUP(P5,'Velocidades Std 1500 w'!$B$17:$F$28,5,FALSE),IF(O5="ALUMINIO",VLOOKUP(P5,'Velocidades Std 1500 w'!$B$30:$F$38,5,FALSE)))) -> 4.3859649e-06 | R5: =+Q5*N5 -> 0.021929825 | S5: =+Q5*T5*3600 -> 50.573058 | T5: =(+H5*2+G5*2+V5*1.5)*25.4*1.05 -> 3202.9603 | U5: =+T5*R5 -> 70.240358 | V5: 20 | W5: =+IF(O5="ACERO A36",VLOOKUP(P5,'Tiempo Objeto'!$B$2:$C$12,2,FALSE),IF(O5="INOXIDABLE",VLOOKUP(P5,'Tiempo Objeto'!$B$14:$C$22,2,FALSE),IF(O5="ALUMINIO",VLOOKUP(P5,'Tiempo Objeto'!$B$24:$C$32,2,FALSE)))) -> 1.84 | X5: =+W5*V5 -> 36.8 | Y5: =+X5*N5/3600 -> 51.111111 | Z5: 4 | AA5: =30*Z5+Z5*$C5*1.5 -> 120 | AB5: =+Z5*Analisis!$J$6 -> 100 | AC5: 0 | AD5: =30*AC5+AC5*$C5*1.5 -> 0 | AE5: =+AD5*Analisis!$J$7 -> 0 | AF5: =+L5+U5+Y5+AB5+AE5 -> 445.14614 | AG5: =+AF5/(1-Analisis!$E$9) -> 556.43267 | AH5: =+AG5*C5 -> 0
A6: 1 | B6: 11-B-9087-01 | C6: =IFERROR(VLOOKUP(B6,'REQ GALV'!A:B,2,0),0) -> 0 | D6: =+AG6 -> 284.81814 | E6: 12GA | F6: DECAPADO | G6: 6.91 | H6: 22.13 | I6: 0.105 | J6: 28.24 | K6: =+L6*2.2/J6 -> 8.8023085 | L6: =+VLOOKUP(E6,Material!$H$2:$M$17,6,FALSE)*G6*H6*(1+Material!$K$14) -> 112.98963 | M6: =+Analisis!$J$5 -> T5.0 | N6: =+VLOOKUP(M6,Material!$A$3:$B$58,2,FALSE) -> 5000 | O6: ACERO A36 | P6: Cal 12 | Q6: =+IF(O6="ACERO A36",VLOOKUP(P6,'Velocidades Std 1500 w'!$B$2:$F$15,5,FALSE),IF(O6="INOXIDABLE",VLOOKUP(P6,'Velocidades Std 1500 w'!$B$17:$F$28,5,FALSE),IF(O6="ALUMINIO",VLOOKUP(P6,'Velocidades Std 1500 w'!$B$30:$F$38,5,FALSE)))) -> 4.3859649e-06 | R6: =+Q6*N6 -> 0.021929825 | S6: =+Q6*T6*3600 -> 30.142715 | T6: =(+H6*2+G6*2+V6*1.5)*25.4*1.05 -> 1909.0386 | U6: =+T6*R6 -> 41.864882 | V6: 9 | W6: =+IF(O6="ACERO A36",VLOOKUP(P6,'Tiempo Objeto'!$B$2:$C$12,2,FALSE),IF(O6="INOXIDABLE",VLOOKUP(P6,'Tiempo Objeto'!$B$14:$C$22,2,FALSE),IF(O6="ALUMINIO",VLOOKUP(P6,'Tiempo Objeto'!$B$24:$C$32,2,FALSE)))) -> 1.84 | X6: =+W6*V6 -> 16.56 | Y6: =+X6*N6/3600 -> 23 | Z6: 2 | AA6: =30*Z6+Z6*$C6*1.5 -> 60 | AB6: =+Z6*Analisis!$J$6 -> 50 | AC6: 0 | AD6: =30*AC6+AC6*$C6*1.5 -> 0 | AE6: =+AD6*Analisis!$J$7 -> 0 | AF6: =+L6+U6+Y6+AB6+AE6 -> 227.85451 | AG6: =+AF6/(1-Analisis!$E$9) -> 284.81814 | AH6: =+AG6*C6 -> 0
A7: 2 | B7: 11-D-9401-01 | C7: =IFERROR(VLOOKUP(B7,'REQ GALV'!A:B,2,0),0) -> 0 | D7: =+AG7 -> 990.2411 | E7: 12GA | F7: DECAPADO | G7: 41.94 | H7: 13.03 | I7: 0.105 | J7: 28.24 | K7: =+L7*2.2/J7 -> 31.456469 | L7: =+VLOOKUP(E7,Material!$H$2:$M$17,6,FALSE)*G7*H7*(1+Material!$K$14) -> 403.78667 | M7: =+Analisis!$J$5 -> T5.0 | N7: =+VLOOKUP(M7,Material!$A$3:$B$58,2,FALSE) -> 5000 | O7: ACERO A36 | P7: Cal 12 | Q7: =+IF(O7="ACERO A36",VLOOKUP(P7,'Velocidades Std 1500 w'!$B$2:$F$15,5,FALSE),IF(O7="INOXIDABLE",VLOOKUP(P7,'Velocidades Std 1500 w'!$B$17:$F$28,5,FALSE),IF(O7="ALUMINIO",VLOOKUP(P7,'Velocidades Std 1500 w'!$B$30:$F$38,5,FALSE)))) -> 4.3859649e-06 | R7: =+Q7*N7 -> 0.021929825 | S7: =+Q7*T7*3600 -> 82.932471 | T7: =(+H7*2+G7*2+V7*1.5)*25.4*1.05 -> 5252.3898 | U7: =+T7*R7 -> 115.18399 | V7: 58 | W7: =+IF(O7="ACERO A36",VLOOKUP(P7,'Tiempo Objeto'!$B$2:$C$12,2,FALSE),IF(O7="INOXIDABLE",VLOOKUP(P7,'Tiempo Objeto'!$B$14:$C$22,2,FALSE),IF(O7="ALUMINIO",VLOOKUP(P7,'Tiempo Objeto'!$B$24:$C$32,2,FALSE)))) -> 1.84 | X7: =+W7*V7 -> 106.72 | Y7: =+X7*N7/3600 -> 148.22222 | Z7: 5 | AA7: =30*Z7+Z7*$C7*1.5 -> 150 | AB7: =+Z7*Analisis!$J$6 -> 125 | AC7: 0 | AD7: =30*AC7+AC7*$C7*1.5 -> 0 | AE7: =+AD7*Analisis!$J$7 -> 0 | AF7: =+L7+U7+Y7+AB7+AE7 -> 792.19288 | AG7: =+AF7/(1-Analisis!$E$9) -> 990.2411 | AH7: =+AG7*C7 -> 0
A8: 2 | B8: 11-D-9401-02 | C8: =IFERROR(VLOOKUP(B8,'REQ GALV'!A:B,2,0),0) -> 0 | D8: =+AG8 -> 936.2538 | E8: 12GA | F8: DECAPADO | G8: 37.94 | H8: 13.03 | I8: 0.105 | J8: 28.24 | K8: =+L8*2.2/J8 -> 28.456329 | L8: =+VLOOKUP(E8,Material!$H$2:$M$17,6,FALSE)*G8*H8*(1+Material!$K$14) -> 365.27578 | M8: =+Analisis!$J$5 -> T5.0 | N8: =+VLOOKUP(M8,Material!$A$3:$B$58,2,FALSE) -> 5000 | O8: ACERO A36 | P8: Cal 12 | Q8: =+IF(O8="ACERO A36",VLOOKUP(P8,'Velocidades Std 1500 w'!$B$2:$F$15,5,FALSE),IF(O8="INOXIDABLE",VLOOKUP(P8,'Velocidades Std 1500 w'!$B$17:$F$28,5,FALSE),IF(O8="ALUMINIO",VLOOKUP(P8,'Velocidades Std 1500 w'!$B$30:$F$38,5,FALSE)))) -> 4.3859649e-06 | R8: =+Q8*N8 -> 0.021929825 | S8: =+Q8*T8*3600 -> 79.563628 | T8: =(+H8*2+G8*2+V8*1.5)*25.4*1.05 -> 5039.0298 | U8: =+T8*R8 -> 110.50504 | V8: 58 | W8: =+IF(O8="ACERO A36",VLOOKUP(P8,'Tiempo Objeto'!$B$2:$C$12,2,FALSE),IF(O8="INOXIDABLE",VLOOKUP(P8,'Tiempo Objeto'!$B$14:$C$22,2,FALSE),IF(O8="ALUMINIO",VLOOKUP(P8,'Tiempo Objeto'!$B$24:$C$32,2,FALSE)))) -> 1.84 | X8: =+W8*V8 -> 106.72 | Y8: =+X8*N8/3600 -> 148.22222 | Z8: 5 | AA8: =30*Z8+Z8*$C8*1.5 -> 150 | AB8: =+Z8*Analisis!$J$6 -> 125 | AC8: 0 | AD8: =30*AC8+AC8*$C8*1.5 -> 0 | AE8: =+AD8*Analisis!$J$7 -> 0 | AF8: =+L8+U8+Y8+AB8+AE8 -> 749.00304 | AG8: =+AF8/(1-Analisis!$E$9) -> 936.2538 | AH8: =+AG8*C8 -> 0
A9: 2 | B9: 11-D-9401-03 | C9: =IFERROR(VLOOKUP(B9,'REQ GALV'!A:B,2,0),0) -> 0 | D9: =+AG9 -> 963.24745 | E9: 12GA | F9: DECAPADO | G9: 39.94 | H9: 13.03 | I9: 0.105 | J9: 28.24 | K9: =+L9*2.2/J9 -> 29.956399 | L9: =+VLOOKUP(E9,Material!$H$2:$M$17,6,FALSE)*G9*H9*(1+Material!$K$14) -> 384.53123 | M9: =+Analisis!$J$5 -> T5.0 | N9: =+VLOOKUP(M9,Material!$A$3:$B$58,2,FALSE) -> 5000 | O9: ACERO A36 | P9: Cal 12 | Q9: =+IF(O9="ACERO A36",VLOOKUP(P9,'Velocidades Std 1500 w'!$B$2:$F$15,5,FALSE),IF(O9="INOXIDABLE",VLOOKUP(P9,'Velocidades Std 1500 w'!$B$17:$F$28,5,FALSE),IF(O9="ALUMINIO",VLOOKUP(P9,'Velocidades Std 1500 w'!$B$30:$F$38,5,FALSE)))) -> 4.3859649e-06 | R9: =+Q9*N9 -> 0.021929825 | S9: =+Q9*T9*3600 -> 81.248049 | T9: =(+H9*2+G9*2+V9*1.5)*25.4*1.05 -> 5145.7098 | U9: =+T9*R9 -> 112.84451 | V9: 58 | W9: =+IF(O9="ACERO A36",VLOOKUP(P9,'Tiempo Objeto'!$B$2:$C$12,2,FALSE),IF(O9="INOXIDABLE",VLOOKUP(P9,'Tiempo Objeto'!$B$14:$C$22,2,FALSE),IF(O9="ALUMINIO",VLOOKUP(P9,'Tiempo Objeto'!$B$24:$C$32,2,FALSE)))) -> 1.84 | X9: =+W9*V9 -> 106.72 | Y9: =+X9*N9/3600 -> 148.22222 | Z9: 5 | AA9: =30*Z9+Z9*$C9*1.5 -> 150 | AB9: =+Z9*Analisis!$J$6 -> 125 | AC9: 0 | AD9: =30*AC9+AC9*$C9*1.5 -> 0 | AE9: =+AD9*Analisis!$J$7 -> 0 | AF9: =+L9+U9+Y9+AB9+AE9 -> 770.59796 | AG9: =+AF9/(1-Analisis!$E$9) -> 963.24745 | AH9: =+AG9*C9 -> 0
A10: 2 | B10: 11-D-9401-04 | C10: =IFERROR(VLOOKUP(B10,'REQ GALV'!A:B,2,0),0) -> 0 | D10: =+AG10 -> 1044.2284 | E10: 12GA | F10: DECAPADO | G10: 45.94 | H10: 13.03 | I10: 0.105 | J10: 28.24 | K10: =+L10*2.2/J10 -> 34.456609 | L10: =+VLOOKUP(E10,Material!$H$2:$M$17,6,FALSE)*G10*H10*(1+Material!$K$14) -> 442.29756 | M10: =+Analisis!$J$5 -> T5.0 | N10: =+VLOOKUP(M10,Material!$A$3:$B$58,2,FALSE) -> 5000 | O10: ACERO A36 | P10: Cal 12 | Q10: =+IF(O10="ACERO A36",VLOOKUP(P10,'Velocidades Std 1500 w'!$B$2:$F$15,5,FALSE),IF(O10="INOXIDABLE",VLOOKUP(P10,'Velocidades Std 1500 w'!$B$17:$F$28,5,FALSE),IF(O10="ALUMINIO",VLOOKUP(P10,'Velocidades Std 1500 w'!$B$30:$F$38,5,FALSE)))) -> 4.3859649e-06 | R10: =+Q10*N10 -> 0.021929825 | S10: =+Q10*T10*3600 -> 86.301313 | T10: =(+H10*2+G10*2+V10*1.5)*25.4*1.05 -> 5465.7498 | U10: =+T10*R10 -> 119.86293 | V10: 58 | W10: =+IF(O10="ACERO A36",VLOOKUP(P10,'Tiempo Objeto'!$B$2:$C$12,2,FALSE),IF(O10="INOXIDABLE",VLOOKUP(P10,'Tiempo Objeto'!$B$14:$C$22,2,FALSE),IF(O10="ALUMINIO",VLOOKUP(P10,'Tiempo Objeto'!$B$24:$C$32,2,FALSE)))) -> 1.84 | X10: =+W10*V10 -> 106.72 | Y10: =+X10*N10/3600 -> 148.22222 | Z10: 5 | AA10: =30*Z10+Z10*$C10*1.5 -> 150 | AB10: =+Z10*Analisis!$J$6 -> 125 | AC10: 0 | AD10: =30*AC10+AC10*$C10*1.5 -> 0 | AE10: =+AD10*Analisis!$J$7 -> 0 | AF10: =+L10+U10+Y10+AB10+AE10 -> 835.38272 | AG10: =+AF10/(1-Analisis!$E$9) -> 1044.2284 | AH10: =+AG10*C10 -> 0
A11: 3 | B11: 11-A-9813-01 | C11: =IFERROR(VLOOKUP(B11,'REQ GALV'!A:B,2,0),0) -> 0 | D11: =+AG11 -> 260.30033 | E11: 12GA | F11: DECAPADO | G11: 2.69 | H11: 21.94 | I11: 0.105 | J11: 28.24 | K11: =+L11*2.2/J11 -> 3.3972384 | L11: =+VLOOKUP(E11,Material!$H$2:$M$17,6,FALSE)*G11*H11*(1+Material!$K$14) -> 43.608188 | M11: =+Analisis!$J$5 -> T5.0 | N11: =+VLOOKUP(M11,Material!$A$3:$B$58,2,FALSE) -> 5000 | O11: ACERO A36 | P11: Cal 12 | Q11: =+IF(O11="ACERO A36",VLOOKUP(P11,'Velocidades Std 1500 w'!$B$2:$F$15,5,FALSE),IF(O11="INOXIDABLE",VLOOKUP(P11,'Velocidades Std 1500 w'!$B$17:$F$28,5,FALSE),IF(O11="ALUMINIO",VLOOKUP(P11,'Velocidades Std 1500 w'!$B$30:$F$38,5,FALSE)))) -> 4.3859649e-06 | R11: =+Q11*N11 -> 0.021929825 | S11: =+Q11*T11*3600 -> 36.535093 | T11: =(+H11*2+G11*2+V11*1.5)*25.4*1.05 -> 2313.8892 | U11: =+T11*R11 -> 50.743184 | V11: 25 | W11: =+IF(O11="ACERO A36",VLOOKUP(P11,'Tiempo Objeto'!$B$2:$C$12,2,FALSE),IF(O11="INOXIDABLE",VLOOKUP(P11,'Tiempo Objeto'!$B$14:$C$22,2,FALSE),IF(O11="ALUMINIO",VLOOKUP(P11,'Tiempo Objeto'!$B$24:$C$32,2,FALSE)))) -> 1.84 | X11: =+W11*V11 -> 46 | Y11: =+X11*N11/3600 -> 63.888889 | Z11: 2 | AA11: =30*Z11+Z11*$C11*1.5 -> 60 | AB11: =+Z11*Analisis!$J$6 -> 50 | AC11: 0 | AD11: =30*AC11+AC11*$C11*1.5 -> 0 | AE11: =+AD11*Analisis!$J$7 -> 0 | AF11: =+L11+U11+Y11+AB11+AE11 -> 208.24026 | AG11: =+AF11/(1-Analisis!$E$9) -> 260.30033 | AH11: =+AG11*C11 -> 0
A12: 3 | B12: 11-A-9813-02 | C12: =IFERROR(VLOOKUP(B12,'REQ GALV'!A:B,2,0),0) -> 0 | D12: =+AG12 -> 299.76718 | E12: 12GA | F12: DECAPADO | G12: 2.69 | H12: 31.94 | I12: 0.105 | J12: 28.24 | K12: =+L12*2.2/J12 -> 4.9456607 | L12: =+VLOOKUP(E12,Material!$H$2:$M$17,6,FALSE)*G12*H12*(1+Material!$K$14) -> 63.484299 | M12: =+Analisis!$J$5 -> T5.0 | N12: =+VLOOKUP(M12,Material!$A$3:$B$58,2,FALSE) -> 5000 | O12: ACERO A36 | P12: Cal 12 | Q12: =+IF(O12="ACERO A36",VLOOKUP(P12,'Velocidades Std 1500 w'!$B$2:$F$15,5,FALSE),IF(O12="INOXIDABLE",VLOOKUP(P12,'Velocidades Std 1500 w'!$B$17:$F$28,5,FALSE),IF(O12="ALUMINIO",VLOOKUP(P12,'Velocidades Std 1500 w'!$B$30:$F$38,5,FALSE)))) -> 4.3859649e-06 | R12: =+Q12*N12 -> 0.021929825 | S12: =+Q12*T12*3600 -> 44.957198 | T12: =(+H12*2+G12*2+V12*1.5)*25.4*1.05 -> 2847.2892 | U12: =+T12*R12 -> 62.440553 | V12: 25 | W12: =+IF(O12="ACERO A36",VLOOKUP(P12,'Tiempo Objeto'!$B$2:$C$12,2,FALSE),IF(O12="INOXIDABLE",VLOOKUP(P12,'Tiempo Objeto'!$B$14:$C$22,2,FALSE),IF(O12="ALUMINIO",VLOOKUP(P12,'Tiempo Objeto'!$B$24:$C$32,2,FALSE)))) -> 1.84 | X12: =+W12*V12 -> 46 | Y12: =+X12*N12/3600 -> 63.888889 | Z12: 2 | AA12: =30*Z12+Z12*$C12*1.5 -> 60 | AB12: =+Z12*Analisis!$J$6 -> 50 | AC12: 0 | AD12: =30*AC12+AC12*$C12*1.5 -> 0 | AE12: =+AD12*Analisis!$J$7 -> 0 | AF12: =+L12+U12+Y12+AB12+AE12 -> 239.81374 | AG12: =+AF12/(1-Analisis!$E$9) -> 299.76718 | AH12: =+AG12*C12 -> 0
A13: 3 | B13: 11-A-9813-03 | C13: =IFERROR(VLOOKUP(B13,'REQ GALV'!A:B,2,0),0) -> 0 | D13: =+AG13 -> 339.23402 | E13: 12GA | F13: DECAPADO | G13: 2.69 | H13: 41.94 | I13: 0.105 | J13: 28.24 | K13: =+L13*2.2/J13 -> 6.4940829 | L13: =+VLOOKUP(E13,Material!$H$2:$M$17,6,FALSE)*G13*H13*(1+Material!$K$14) -> 83.36041 | M13: =+Analisis!$J$5 -> T5.0 | N13: =+VLOOKUP(M13,Material!$A$3:$B$58,2,FALSE) -> 5000 | O13: ACERO A36 | P13: Cal 12 | Q13: =+IF(O13="ACERO A36",VLOOKUP(P13,'Velocidades Std 1500 w'!$B$2:$F$15,5,FALSE),IF(O13="INOXIDABLE",VLOOKUP(P13,'Velocidades Std 1500 w'!$B$17:$F$28,5,FALSE),IF(O13="ALUMINIO",VLOOKUP(P13,'Velocidades Std 1500 w'!$B$30:$F$38,5,FALSE)))) -> 4.3859649e-06 | R13: =+Q13*N13 -> 0.021929825 | S13: =+Q13*T13*3600 -> 53.379303 | T13: =(+H13*2+G13*2+V13*1.5)*25.4*1.05 -> 3380.6892 | U13: =+T13*R13 -> 74.137921 | V13: 25 | W13: =+IF(O13="ACERO A36",VLOOKUP(P13,'Tiempo Objeto'!$B$2:$C$12,2,FALSE),IF(O13="INOXIDABLE",VLOOKUP(P13,'Tiempo Objeto'!$B$14:$C$22,2,FALSE),IF(O13="ALUMINIO",VLOOKUP(P13,'Tiempo Objeto'!$B$24:$C$32,2,FALSE)))) -> 1.84 | X13: =+W13*V13 -> 46 | Y13: =+X13*N13/3600 -> 63.888889 | Z13: 2 | AA13: =30*Z13+Z13*$C13*1.5 -> 60 | AB13: =+Z13*Analisis!$J$6 -> 50 | AC13: 0 | AD13: =30*AC13+AC13*$C13*1.5 -> 0 | AE13: =+AD13*Analisis!$J$7 -> 0 | AF13: =+L13+U13+Y13+AB13+AE13 -> 271.38722 | AG13: =+AF13/(1-Analisis!$E$9) -> 339.23402 | AH13: =+AG13*C13 -> 0
A14: 3 | B14: 11-A-9813-04 | C14: =IFERROR(VLOOKUP(B14,'REQ GALV'!A:B,2,0),0) -> 0 | D14: =+AG14 -> 323.44729 | E14: 12GA | F14: DECAPADO | G14: 2.69 | H14: 37.94 | I14: 0.105 | J14: 28.24 | K14: =+L14*2.2/J14 -> 5.874714 | L14: =+VLOOKUP(E14,Material!$H$2:$M$17,6,FALSE)*G14*H14*(1+Material!$K$14) -> 75.409966 | M14: =+Analisis!$J$5 -> T5.0 | N14: =+VLOOKUP(M14,Material!$A$3:$B$58,2,FALSE) -> 5000 | O14: ACERO A36 | P14: Cal 12 | Q14: =+IF(O14="ACERO A36",VLOOKUP(P14,'Velocidades Std 1500 w'!$B$2:$F$15,5,FALSE),IF(O14="INOXIDABLE",VLOOKUP(P14,'Velocidades Std 1500 w'!$B$17:$F$28,5,FALSE),IF(O14="ALUMINIO",VLOOKUP(P14,'Velocidades Std 1500 w'!$B$30:$F$38,5,FALSE)))) -> 4.3859649e-06 | R14: =+Q14*N14 -> 0.021929825 | S14: =+Q14*T14*3600 -> 50.010461 | T14: =(+H14*2+G14*2+V14*1.5)*25.4*1.05 -> 3167.3292 | U14: =+T14*R14 -> 69.458974 | V14: 25 | W14: =+IF(O14="ACERO A36",VLOOKUP(P14,'Tiempo Objeto'!$B$2:$C$12,2,FALSE),IF(O14="INOXIDABLE",VLOOKUP(P14,'Tiempo Objeto'!$B$14:$C$22,2,FALSE),IF(O14="ALUMINIO",VLOOKUP(P14,'Tiempo Objeto'!$B$24:$C$32,2,FALSE)))) -> 1.84 | X14: =+W14*V14 -> 46 | Y14: =+X14*N14/3600 -> 63.888889 | Z14: 2 | AA14: =30*Z14+Z14*$C14*1.5 -> 60 | AB14: =+Z14*Analisis!$J$6 -> 50 | AC14: 0 | AD14: =30*AC14+AC14*$C14*1.5 -> 0 | AE14: =+AD14*Analisis!$J$7 -> 0 | AF14: =+L14+U14+Y14+AB14+AE14 -> 258.75783 | AG14: =+AF14/(1-Analisis!$E$9) -> 323.44729 | AH14: =+AG14*C14 -> 0
... A36: 23 | B36: P11649-242 | C36: =IFERROR(VLOOKUP(B36,'REQ GALV'!A:B,2,0),0) -> 0 | D36: =+AG36 -> 142.11121 | E36: 12GA | F36: DECAPADO | G36: 3.237 | H36: 12 | I36: 0.105 | J36: 28.24 | K36: =+L36*2.2/J36 -> 2.2359448 | L36: =+VLOOKUP(E36,Material!$H$2:$M$17,6,FALSE)*G36*H36*(1+Material!$K$14) -> 28.7014 | M36: =+Analisis!$J$5 -> T5.0 | N36: =+VLOOKUP(M36,Material!$A$3:$B$58,2,FALSE) -> 5000 | O36: ACERO A36 | P36: Cal 12 | Q36: =+IF(O36="ACERO A36",VLOOKUP(P36,'Velocidades Std 1500 w'!$B$2:$F$15,5,FALSE),IF(O36="INOXIDABLE",VLOOKUP(P36,'Velocidades Std 1500 w'!$B$17:$F$28,5,FALSE),IF(O36="ALUMINIO",VLOOKUP(P36,'Velocidades Std 1500 w'!$B$30:$F$38,5,FALSE)))) -> 4.3859649e-06 | R36: =+Q36*N36 -> 0.021929825 | S36: =+Q36*T36*3600 -> 15.991051 | T36: =(+H36*2+G36*2+V36*1.5)*25.4*1.05 -> 1012.7666 | U36: =+T36*R36 -> 22.209793 | V36: 5 | W36: =+IF(O36="ACERO A36",VLOOKUP(P36,'Tiempo Objeto'!$B$2:$C$12,2,FALSE),IF(O36="INOXIDABLE",VLOOKUP(P36,'Tiempo Objeto'!$B$14:$C$22,2,FALSE),IF(O36="ALUMINIO",VLOOKUP(P36,'Tiempo Objeto'!$B$24:$C$32,2,FALSE)))) -> 1.84 | X36: =+W36*V36 -> 9.2 | Y36: =+X36*N36/3600 -> 12.777778 | Z36: 2 | AA36: =30*Z36+Z36*$C36*1.5 -> 60 | AB36: =+Z36*Analisis!$J$6 -> 50 | AC36: 0 | AD36: =30*AC36+AC36*$C36*1.5 -> 0 | AE36: =+AD36*Analisis!$J$7 -> 0 | AF36: =+L36+U36+Y36+AB36+AE36 -> 113.68897 | AG36: =+AF36/(1-Analisis!$E$9) -> 142.11121 | AH36: =+AG36*C36 -> 0
A37: a | B37: PP5309-79 | C37: =IFERROR(VLOOKUP(B37,'REQ GALV'!A:B,2,0),0) -> 0 | D37: =+AG37 -> 94.966953 | E37: 12GA | F37: DECAPADO | G37: 17.5 | H37: 0.946 | I37: 0.105 | J37: 28.24 | K37: =+L37*2.2/J37 -> 0.95294165 | L37: =+VLOOKUP(E37,Material!$H$2:$M$17,6,FALSE)*G37*H37*(1+Material!$K$14) -> 12.232306 | M37: =+Analisis!$J$5 -> T5.0 | N37: =+VLOOKUP(M37,Material!$A$3:$B$58,2,FALSE) -> 5000 | O37: ACERO A36 | P37: Cal 12 | Q37: =+IF(O37="ACERO A36",VLOOKUP(P37,'Velocidades Std 1500 w'!$B$2:$F$15,5,FALSE),IF(O37="INOXIDABLE",VLOOKUP(P37,'Velocidades Std 1500 w'!$B$17:$F$28,5,FALSE),IF(O37="ALUMINIO",VLOOKUP(P37,'Velocidades Std 1500 w'!$B$30:$F$38,5,FALSE)))) -> 4.3859649e-06 | R37: =+Q37*N37 -> 0.021929825 | S37: =+Q37*T37*3600 -> 18.693705 | T37: =(+H37*2+G37*2+V37*1.5)*25.4*1.05 -> 1183.9346 | U37: =+T37*R37 -> 25.963479 | V37: 5 | W37: =+IF(O37="ACERO A36",VLOOKUP(P37,'Tiempo Objeto'!$B$2:$C$12,2,FALSE),IF(O37="INOXIDABLE",VLOOKUP(P37,'Tiempo Objeto'!$B$14:$C$22,2,FALSE),IF(O37="ALUMINIO",VLOOKUP(P37,'Tiempo Objeto'!$B$24:$C$32,2,FALSE)))) -> 1.84 | X37: =+W37*V37 -> 9.2 | Y37: =+X37*N37/3600 -> 12.777778 | Z37: 1 | AA37: =30*Z37+Z37*$C37*1.5 -> 30 | AB37: =+Z37*Analisis!$J$6 -> 25 | AC37: 0 | AD37: =30*AC37+AC37*$C37*1.5 -> 0 | AE37: =+AD37*Analisis!$J$7 -> 0 | AF37: =+L37+U37+Y37+AB37+AE37 -> 75.973562 | AG37: =+AF37/(1-Analisis!$E$9) -> 94.966953 | AH37: =+AG37*C37 -> 0
A38: b | B38: PP7515-161 | C38: =IFERROR(VLOOKUP(B38,'REQ GALV'!A:B,2,0),0) -> 0 | D38: =+AG38 -> 182.92749 | E38: 12GA | F38: DECAPADO | G38: 3.56 | H38: 28.38 | I38: 0.105 | J38: 28.24 | K38: =+L38*2.2/J38 -> 5.8156668 | L38: =+VLOOKUP(E38,Material!$H$2:$M$17,6,FALSE)*G38*H38*(1+Material!$K$14) -> 74.652013 | M38: =+Analisis!$J$5 -> T5.0 | N38: =+VLOOKUP(M38,Material!$A$3:$B$58,2,FALSE) -> 5000 | O38: ACERO A36 | P38: Cal 12 | Q38: =+IF(O38="ACERO A36",VLOOKUP(P38,'Velocidades Std 1500 w'!$B$2:$F$15,5,FALSE),IF(O38="INOXIDABLE",VLOOKUP(P38,'Velocidades Std 1500 w'!$B$17:$F$28,5,FALSE),IF(O38="ALUMINIO",VLOOKUP(P38,'Velocidades Std 1500 w'!$B$30:$F$38,5,FALSE)))) -> 4.3859649e-06 | R38: =+Q38*N38 -> 0.021929825 | S38: =+Q38*T38*3600 -> 33.216783 | T38: =(+H38*2+G38*2+V38*1.5)*25.4*1.05 -> 2103.7296 | U38: =+T38*R38 -> 46.134421 | V38: 10 | W38: =+IF(O38="ACERO A36",VLOOKUP(P38,'Tiempo Objeto'!$B$2:$C$12,2,FALSE),IF(O38="INOXIDABLE",VLOOKUP(P38,'Tiempo Objeto'!$B$14:$C$22,2,FALSE),IF(O38="ALUMINIO",VLOOKUP(P38,'Tiempo Objeto'!$B$24:$C$32,2,FALSE)))) -> 1.84 | X38: =+W38*V38 -> 18.4 | Y38: =+X38*N38/3600 -> 25.555556 | Z38: 0 | AA38: =30*Z38+Z38*$C38*1.5 -> 0 | AB38: =+Z38*Analisis!$J$6 -> 0 | AC38: 0 | AD38: =30*AC38+AC38*$C38*1.5 -> 0 | AE38: =+AD38*Analisis!$J$7 -> 0 | AF38: =+L38+U38+Y38+AB38+AE38 -> 146.34199 | AG38: =+AF38/(1-Analisis!$E$9) -> 182.92749 | AH38: =+AG38*C38 -> 0
B39: PP5309-74 MNT | C39: =IFERROR(VLOOKUP(B39,'REQ GALV'!A:B,2,0),0) -> 0 | D39: =+AG39 -> 94.966953 | E39: 12GA | F39: DECAPADO | G39: 17.5 | H39: 0.946 | I39: 0.105 | J39: 28.24 | K39: =+L39*2.2/J39 -> 0.95294165 | L39: =+VLOOKUP(E39,Material!$H$2:$M$17,6,FALSE)*G39*H39*(1+Material!$K$14) -> 12.232306 | M39: =+Analisis!$J$5 -> T5.0 | N39: =+VLOOKUP(M39,Material!$A$3:$B$58,2,FALSE) -> 5000 | O39: ACERO A36 | P39: Cal 12 | Q39: =+IF(O39="ACERO A36",VLOOKUP(P39,'Velocidades Std 1500 w'!$B$2:$F$15,5,FALSE),IF(O39="INOXIDABLE",VLOOKUP(P39,'Velocidades Std 1500 w'!$B$17:$F$28,5,FALSE),IF(O39="ALUMINIO",VLOOKUP(P39,'Velocidades Std 1500 w'!$B$30:$F$38,5,FALSE)))) -> 4.3859649e-06 | R39: =+Q39*N39 -> 0.021929825 | S39: =+Q39*T39*3600 -> 18.693705 | T39: =(+H39*2+G39*2+V39*1.5)*25.4*1.05 -> 1183.9346 | U39: =+T39*R39 -> 25.963479 | V39: 5 | W39: =+IF(O39="ACERO A36",VLOOKUP(P39,'Tiempo Objeto'!$B$2:$C$12,2,FALSE),IF(O39="INOXIDABLE",VLOOKUP(P39,'Tiempo Objeto'!$B$14:$C$22,2,FALSE),IF(O39="ALUMINIO",VLOOKUP(P39,'Tiempo Objeto'!$B$24:$C$32,2,FALSE)))) -> 1.84 | X39: =+W39*V39 -> 9.2 | Y39: =+X39*N39/3600 -> 12.777778 | Z39: 1 | AA39: =30*Z39+Z39*$C39*1.5 -> 30 | AB39: =+Z39*Analisis!$J$6 -> 25 | AC39: 0 | AD39: =30*AC39+AC39*$C39*1.5 -> 0 | AE39: =+AD39*Analisis!$J$7 -> 0 | AF39: =+L39+U39+Y39+AB39+AE39 -> 75.973562 | AG39: =+AF39/(1-Analisis!$E$9) -> 94.966953 | AH39: =+AG39*C39 -> 0
B40: 11-B-9366-01 MNT | C40: =IFERROR(VLOOKUP(B40,'REQ GALV'!A:B,2,0),0) -> 0 | D40: =+AG40 -> 1302.8949 | E40: 12GA | F40: DECAPADO | G40: 10.39 | H40: 91.56 | I40: 0.105 | J40: 28.24 | K40: =+L40*2.2/J40 -> 54.759372 | L40: =+VLOOKUP(E40,Material!$H$2:$M$17,6,FALSE)*G40*H40*(1+Material!$K$14) -> 702.91121 | M40: =+Analisis!$J$5 -> T5.0 | N40: =+VLOOKUP(M40,Material!$A$3:$B$58,2,FALSE) -> 5000 | O40: ACERO A36 | P40: Cal 12 | Q40: =+IF(O40="ACERO A36",VLOOKUP(P40,'Velocidades Std 1500 w'!$B$2:$F$15,5,FALSE),IF(O40="INOXIDABLE",VLOOKUP(P40,'Velocidades Std 1500 w'!$B$17:$F$28,5,FALSE),IF(O40="ALUMINIO",VLOOKUP(P40,'Velocidades Std 1500 w'!$B$30:$F$38,5,FALSE)))) -> 4.3859649e-06 | R40: =+Q40*N40 -> 0.021929825 | S40: =+Q40*T40*3600 -> 107.97139 | T40: =(+H40*2+G40*2+V40*1.5)*25.4*1.05 -> 6838.188 | U40: =+T40*R40 -> 149.96026 | V40: 35 | W40: =+IF(O40="ACERO A36",VLOOKUP(P40,'Tiempo Objeto'!$B$2:$C$12,2,FALSE),IF(O40="INOXIDABLE",VLOOKUP(P40,'Tiempo Objeto'!$B$14:$C$22,2,FALSE),IF(O40="ALUMINIO",VLOOKUP(P40,'Tiempo Objeto'!$B$24:$C$32,2,FALSE)))) -> 1.84 | X40: =+W40*V40 -> 64.4 | Y40: =+X40*N40/3600 -> 89.444444 | Z40: 4 | AA40: =30*Z40+Z40*$C40*1.5 -> 120 | AB40: =+Z40*Analisis!$J$6 -> 100 | AC40: 0 | AD40: =30*AC40+AC40*$C40*1.5 -> 0 | AE40: =+AD40*Analisis!$J$7 -> 0 | AF40: =+L40+U40+Y40+AB40+AE40 -> 1042.3159 | AG40: =+AF40/(1-Analisis!$E$9) -> 1302.8949 | AH40: =+AG40*C40 -> 0
B41: PP8886-46 MNT | C41: =IFERROR(VLOOKUP(B41,'REQ GALV'!A:B,2,0),0) -> 0 | D41: =+AG41 -> 87.146208 | E41: 12GA | F41: DECAPADO | G41: 3 | H41: 7.1 | I41: 0.105 | J41: 28.24 | K41: =+L41*2.2/J41 -> 1.2260741 | L41: =+VLOOKUP(E41,Material!$H$2:$M$17,6,FALSE)*G41*H41*(1+Material!$K$14) -> 15.738333 | M41: =+Analisis!$J$5 -> T5.0 | N41: =+VLOOKUP(M41,Material!$A$3:$B$58,2,FALSE) -> 5000 | O41: ACERO A36 | P41: Cal 12 | Q41: =+IF(O41="ACERO A36",VLOOKUP(P41,'Velocidades Std 1500 w'!$B$2:$F$15,5,FALSE),IF(O41="INOXIDABLE",VLOOKUP(P41,'Velocidades Std 1500 w'!$B$17:$F$28,5,FALSE),IF(O41="ALUMINIO",VLOOKUP(P41,'Velocidades Std 1500 w'!$B$30:$F$38,5,FALSE)))) -> 4.3859649e-06 | R41: =+Q41*N41 -> 0.021929825 | S41: =+Q41*T41*3600 -> 11.664616 | T41: =(+H41*2+G41*2+V41*1.5)*25.4*1.05 -> 738.759 | U41: =+T41*R41 -> 16.200855 | V41: 5 | W41: =+IF(O41="ACERO A36",VLOOKUP(P41,'Tiempo Objeto'!$B$2:$C$12,2,FALSE),IF(O41="INOXIDABLE",VLOOKUP(P41,'Tiempo Objeto'!$B$14:$C$22,2,FALSE),IF(O41="ALUMINIO",VLOOKUP(P41,'Tiempo Objeto'!$B$24:$C$32,2,FALSE)))) -> 1.84 | X41: =+W41*V41 -> 9.2 | Y41: =+X41*N41/3600 -> 12.777778 | Z41: 1 | AA41: =30*Z41+Z41*$C41*1.5 -> 30 | AB41: =+Z41*Analisis!$J$6 -> 25 | AC41: 0 | AD41: =30*AC41+AC41*$C41*1.5 -> 0 | AE41: =+AD41*Analisis!$J$7 -> 0 | AF41: =+L41+U41+Y41+AB41+AE41 -> 69.716966 | AG41: =+AF41/(1-Analisis!$E$9) -> 87.146208 | AH41: =+AG41*C41 -> 0
B42: PP9616-783 MNT1 | C42: =IFERROR(VLOOKUP(B42,'REQ GALV'!A:B,2,0),0) -> 0 | D42: =+AG42 -> 709.38619 | E42: 12GA | F42: DECAPADO | G42: 15.525 | H42: 27.4 | I42: 0.105 | J42: 28.24 | K42: =+L42*2.2/J42 -> 24.486082 | L42: =+VLOOKUP(E42,Material!$H$2:$M$17,6,FALSE)*G42*H42*(1+Material!$K$14) -> 314.31225 | M42: =+Analisis!$J$5 -> T5.0 | N42: =+VLOOKUP(M42,Material!$A$3:$B$58,2,FALSE) -> 5000 | O42: ACERO A36 | P42: Cal 12 | Q42: =+IF(O42="ACERO A36",VLOOKUP(P42,'Velocidades Std 1500 w'!$B$2:$F$15,5,FALSE),IF(O42="INOXIDABLE",VLOOKUP(P42,'Velocidades Std 1500 w'!$B$17:$F$28,5,FALSE),IF(O42="ALUMINIO",VLOOKUP(P42,'Velocidades Std 1500 w'!$B$30:$F$38,5,FALSE)))) -> 4.3859649e-06 | R42: =+Q42*N42 -> 0.021929825 | S42: =+Q42*T42*3600 -> 55.101624 | T42: =(+H42*2+G42*2+V42*1.5)*25.4*1.05 -> 3489.7695 | U42: =+T42*R42 -> 76.530033 | V42: 30 | W42: =+IF(O42="ACERO A36",VLOOKUP(P42,'Tiempo Objeto'!$B$2:$C$12,2,FALSE),IF(O42="INOXIDABLE",VLOOKUP(P42,'Tiempo Objeto'!$B$14:$C$22,2,FALSE),IF(O42="ALUMINIO",VLOOKUP(P42,'Tiempo Objeto'!$B$24:$C$32,2,FALSE)))) -> 1.84 | X42: =+W42*V42 -> 55.2 | Y42: =+X42*N42/3600 -> 76.666667 | Z42: 4 | AA42: =30*Z42+Z42*$C42*1.5 -> 120 | AB42: =+Z42*Analisis!$J$6 -> 100 | AC42: 0 | AD42: =30*AC42+AC42*$C42*1.5 -> 0 | AE42: =+AD42*Analisis!$J$7 -> 0 | AF42: =+L42+U42+Y42+AB42+AE42 -> 567.50895 | AG42: =+AF42/(1-Analisis!$E$9) -> 709.38619 | AH42: =+AG42*C42 -> 0
B43: PP9616-801 | C43: =IFERROR(VLOOKUP(B43,'REQ GALV'!A:B,2,0),0) -> 0 | D43: =+AG43 -> 191.51965 | E43: 12GA | F43: DECAPADO | G43: 4.39 | H43: 7.005 | I43: 0.105 | J43: 28.24 | K43: =+L43*2.2/J43 -> 1.7701488 | L43: =+VLOOKUP(E43,Material!$H$2:$M$17,6,FALSE)*G43*H43*(1+Material!$K$14) -> 22.722274 | M43: =+Analisis!$J$5 -> T5.0 | N43: =+VLOOKUP(M43,Material!$A$3:$B$58,2,FALSE) -> 5000 | O43: ACERO A36 | P43: Cal 12 | Q43: =+IF(O43="ACERO A36",VLOOKUP(P43,'Velocidades Std 1500 w'!$B$2:$F$15,5,FALSE),IF(O43="INOXIDABLE",VLOOKUP(P43,'Velocidades Std 1500 w'!$B$17:$F$28,5,FALSE),IF(O43="ALUMINIO",VLOOKUP(P43,'Velocidades Std 1500 w'!$B$30:$F$38,5,FALSE)))) -> 4.3859649e-06 | R43: =+Q43*N43 -> 0.021929825 | S43: =+Q43*T43*3600 -> 12.755278 | T43: =(+H43*2+G43*2+V43*1.5)*25.4*1.05 -> 807.8343 | U43: =+T43*R43 -> 17.715664 | V43: 5 | W43: =+IF(O43="ACERO A36",VLOOKUP(P43,'Tiempo Objeto'!$B$2:$C$12,2,FALSE),IF(O43="INOXIDABLE",VLOOKUP(P43,'Tiempo Objeto'!$B$14:$C$22,2,FALSE),IF(O43="ALUMINIO",VLOOKUP(P43,'Tiempo Objeto'!$B$24:$C$32,2,FALSE)))) -> 1.84 | X43: =+W43*V43 -> 9.2 | Y43: =+X43*N43/3600 -> 12.777778 | Z43: 4 | AA43: =30*Z43+Z43*$C43*1.5 -> 120 | AB43: =+Z43*Analisis!$J$6 -> 100 | AC43: 0 | AD43: =30*AC43+AC43*$C43*1.5 -> 0 | AE43: =+AD43*Analisis!$J$7 -> 0 | AF43: =+L43+U43+Y43+AB43+AE43 -> 153.21572 | AG43: =+AF43/(1-Analisis!$E$9) -> 191.51965 | AH43: =+AG43*C43 -> 0
B44: P8533-59 | C44: =IFERROR(VLOOKUP(B44,'REQ GALV'!A:B,2,0),0) -> 0 | D44: =+AG44 -> 56.569786 | E44: 12GA | F44: DECAPADO | G44: 1.75 | H44: 1.818 | I44: 0.105 | J44: 28.24 | K44: =+L44*2.2/J44 -> 0.18313403 | L44: =+VLOOKUP(E44,Material!$H$2:$M$17,6,FALSE)*G44*H44*(1+Material!$K$14) -> 2.350775 | M44: =+Analisis!$J$5 -> T5.0 | N44: =+VLOOKUP(M44,Material!$A$3:$B$58,2,FALSE) -> 5000 | O44: ACERO A36 | P44: Cal 12 | Q44: =+IF(O44="ACERO A36",VLOOKUP(P44,'Velocidades Std 1500 w'!$B$2:$F$15,5,FALSE),IF(O44="INOXIDABLE",VLOOKUP(P44,'Velocidades Std 1500 w'!$B$17:$F$28,5,FALSE),IF(O44="ALUMINIO",VLOOKUP(P44,'Velocidades Std 1500 w'!$B$30:$F$38,5,FALSE)))) -> 4.3859649e-06 | R44: =+Q44*N44 -> 0.021929825 | S44: =+Q44*T44*3600 -> 5.5316387 | T44: =(+H44*2+G44*2+V44*1.5)*25.4*1.05 -> 350.33712 | U44: =+T44*R44 -> 7.6828316 | V44: 4 | W44: =+IF(O44="ACERO A36",VLOOKUP(P44,'Tiempo Objeto'!$B$2:$C$12,2,FALSE),IF(O44="INOXIDABLE",VLOOKUP(P44,'Tiempo Objeto'!$B$14:$C$22,2,FALSE),IF(O44="ALUMINIO",VLOOKUP(P44,'Tiempo Objeto'!$B$24:$C$32,2,FALSE)))) -> 1.84 | X44: =+W44*V44 -> 7.36 | Y44: =+X44*N44/3600 -> 10.222222 | Z44: 1 | AA44: =30*Z44+Z44*$C44*1.5 -> 30 | AB44: =+Z44*Analisis!$J$6 -> 25 | AC44: 0 | AD44: =30*AC44+AC44*$C44*1.5 -> 0 | AE44: =+AD44*Analisis!$J$7 -> 0 | AF44: =+L44+U44+Y44+AB44+AE44 -> 45.255829 | AG44: =+AF44/(1-Analisis!$E$9) -> 56.569786 | AH44: =+AG44*C44 -> 0
B45: DS-A-22000 | C45: =IFERROR(VLOOKUP(B45,'REQ GALV'!A:B,2,0),0) -> 0 | D45: =+AG45 -> 747.56517 | E45: 12GA | F45: DECAPADO | G45: 22.12 | H45: 25 | I45: 0.105 | J45: 28.24 | K45: =+L45*2.2/J45 -> 31.831878 | L45: =+VLOOKUP(E45,Material!$H$2:$M$17,6,FALSE)*G45*H45*(1+Material!$K$14) -> 408.60556 | M45: =+Analisis!$J$5 -> T5.0 | N45: =+VLOOKUP(M45,Material!$A$3:$B$58,2,FALSE) -> 5000 | O45: ACERO A36 | P45: Cal 12 | Q45: =+IF(O45="ACERO A36",VLOOKUP(P45,'Velocidades Std 1500 w'!$B$2:$F$15,5,FALSE),IF(O45="INOXIDABLE",VLOOKUP(P45,'Velocidades Std 1500 w'!$B$17:$F$28,5,FALSE),IF(O45="ALUMINIO",VLOOKUP(P45,'Velocidades Std 1500 w'!$B$30:$F$38,5,FALSE)))) -> 4.3859649e-06 | R45: =+Q45*N45 -> 0.021929825 | S45: =+Q45*T45*3600 -> 46.001539 | T45: =(+H45*2+G45*2+V45*1.5)*25.4*1.05 -> 2913.4308 | U45: =+T45*R45 -> 63.891026 | V45: 10 | W45: =+IF(O45="ACERO A36",VLOOKUP(P45,'Tiempo Objeto'!$B$2:$C$12,2,FALSE),IF(O45="INOXIDABLE",VLOOKUP(P45,'Tiempo Objeto'!$B$14:$C$22,2,FALSE),IF(O45="ALUMINIO",VLOOKUP(P45,'Tiempo Objeto'!$B$24:$C$32,2,FALSE)))) -> 1.84 | X45: =+W45*V45 -> 18.4 | Y45: =+X45*N45/3600 -> 25.555556 | Z45: 4 | AA45: =30*Z45+Z45*$C45*1.5 -> 120 | AB45: =+Z45*Analisis!$J$6 -> 100 | AC45: 0 | AD45: =30*AC45+AC45*$C45*1.5 -> 0 | AE45: =+AD45*Analisis!$J$7 -> 0 | AF45: =+L45+U45+Y45+AB45+AE45 -> 598.05214 | AG45: =+AF45/(1-Analisis!$E$9) -> 747.56517 | AH45: =+AG45*C45 -> 0
B46: PP8886-46 MNT1 | C46: =IFERROR(VLOOKUP(B46,'REQ GALV'!A:B,2,0),0) -> 0 | D46: =+AG46 -> 90.109311 | E46: 12GA | F46: DECAPADO | G46: 3 | H46: 7.8 | I46: 0.105 | J46: 28.24 | K46: =+L46*2.2/J46 -> 1.3469547 | L46: =+VLOOKUP(E46,Material!$H$2:$M$17,6,FALSE)*G46*H46*(1+Material!$K$14) -> 17.29 | M46: =+Analisis!$J$5 -> T5.0 | N46: =+VLOOKUP(M46,Material!$A$3:$B$58,2,FALSE) -> 5000 | O46: ACERO A36 | P46: Cal 12 | Q46: =+IF(O46="ACERO A36",VLOOKUP(P46,'Velocidades Std 1500 w'!$B$2:$F$15,5,FALSE),IF(O46="INOXIDABLE",VLOOKUP(P46,'Velocidades Std 1500 w'!$B$17:$F$28,5,FALSE),IF(O46="ALUMINIO",VLOOKUP(P46,'Velocidades Std 1500 w'!$B$30:$F$38,5,FALSE)))) -> 4.3859649e-06 | R46: =+Q46*N46 -> 0.021929825 | S46: =+Q46*T46*3600 -> 12.254163 | T46: =(+H46*2+G46*2+V46*1.5)*25.4*1.05 -> 776.097 | U46: =+T46*R46 -> 17.019671 | V46: 5 | W46: =+IF(O46="ACERO A36",VLOOKUP(P46,'Tiempo Objeto'!$B$2:$C$12,2,FALSE),IF(O46="INOXIDABLE",VLOOKUP(P46,'Tiempo Objeto'!$B$14:$C$22,2,FALSE),IF(O46="ALUMINIO",VLOOKUP(P46,'Tiempo Objeto'!$B$24:$C$32,2,FALSE)))) -> 1.84 | X46: =+W46*V46 -> 9.2 | Y46: =+X46*N46/3600 -> 12.777778 | Z46: 1 | AA46: =30*Z46+Z46*$C46*1.5 -> 30 | AB46: =+Z46*Analisis!$J$6 -> 25 | AC46: 0 | AD46: =30*AC46+AC46*$C46*1.5 -> 0 | AE46: =+AD46*Analisis!$J$7 -> 0 | AF46: =+L46+U46+Y46+AB46+AE46 -> 72.087449 | AG46: =+AF46/(1-Analisis!$E$9) -> 90.109311 | AH46: =+AG46*C46 -> 0
B47: PP9616-783 MNT2 | C47: =IFERROR(VLOOKUP(B47,'REQ GALV'!A:B,2,0),0) -> 0 | D47: =+AG47 -> 641.79417 | E47: 12GA | F47: DECAPADO | G47: 13 | H47: 27.4 | I47: 0.105 | J47: 28.24 | K47: =+L47*2.2/J47 -> 20.503643 | L47: =+VLOOKUP(E47,Material!$H$2:$M$17,6,FALSE)*G47*H47*(1+Material!$K$14) -> 263.19222 | M47: =+Analisis!$J$5 -> T5.0 | N47: =+VLOOKUP(M47,Material!$A$3:$B$58,2,FALSE) -> 5000 | O47: ACERO A36 | P47: Cal 12 | Q47: =+IF(O47="ACERO A36",VLOOKUP(P47,'Velocidades Std 1500 w'!$B$2:$F$15,5,FALSE),IF(O47="INOXIDABLE",VLOOKUP(P47,'Velocidades Std 1500 w'!$B$17:$F$28,5,FALSE),IF(O47="ALUMINIO",VLOOKUP(P47,'Velocidades Std 1500 w'!$B$30:$F$38,5,FALSE)))) -> 4.3859649e-06 | R47: =+Q47*N47 -> 0.021929825 | S47: =+Q47*T47*3600 -> 52.975042 | T47: =(+H47*2+G47*2+V47*1.5)*25.4*1.05 -> 3355.086 | U47: =+T47*R47 -> 73.576447 | V47: 30 | W47: =+IF(O47="ACERO A36",VLOOKUP(P47,'Tiempo Objeto'!$B$2:$C$12,2,FALSE),IF(O47="INOXIDABLE",VLOOKUP(P47,'Tiempo Objeto'!$B$14:$C$22,2,FALSE),IF(O47="ALUMINIO",VLOOKUP(P47,'Tiempo Objeto'!$B$24:$C$32,2,FALSE)))) -> 1.84 | X47: =+W47*V47 -> 55.2 | Y47: =+X47*N47/3600 -> 76.666667 | Z47: 4 | AA47: =30*Z47+Z47*$C47*1.5 -> 120 | AB47: =+Z47*Analisis!$J$6 -> 100 | AC47: 0 | AD47: =30*AC47+AC47*$C47*1.5 -> 0 | AE47: =+AD47*Analisis!$J$7 -> 0 | AF47: =+L47+U47+Y47+AB47+AE47 -> 513.43534 | AG47: =+AF47/(1-Analisis!$E$9) -> 641.79417 | AH47: =+AG47*C47 -> 0
B48: 11-C-9662-01 | C48: =IFERROR(VLOOKUP(B48,'REQ GALV'!A:B,2,0),0) -> 0 | D48: =+AG48 -> 228.94505 | E48: 12GA | F48: DECAPADO | G48: 8.57 | H48: 17 | I48: 0.105 | J48: 28.24 | K48: =+L48*2.2/J48 -> 8.3862319 | L48: =+VLOOKUP(E48,Material!$H$2:$M$17,6,FALSE)*G48*H48*(1+Material!$K$14) -> 107.64872 | M48: =+Analisis!$J$5 -> T5.0 | N48: =+VLOOKUP(M48,Material!$A$3:$B$58,2,FALSE) -> 5000 | O48: ACERO A36 | P48: Cal 12 | Q48: =+IF(O48="ACERO A36",VLOOKUP(P48,'Velocidades Std 1500 w'!$B$2:$F$15,5,FALSE),IF(O48="INOXIDABLE",VLOOKUP(P48,'Velocidades Std 1500 w'!$B$17:$F$28,5,FALSE),IF(O48="ALUMINIO",VLOOKUP(P48,'Velocidades Std 1500 w'!$B$30:$F$38,5,FALSE)))) -> 4.3859649e-06 | R48: =+Q48*N48 -> 0.021929825 | S48: =+Q48*T48*3600 -> 25.325271 | T48: =(+H48*2+G48*2+V48*1.5)*25.4*1.05 -> 1603.9338 | U48: =+T48*R48 -> 35.173987 | V48: 6 | W48: =+IF(O48="ACERO A36",VLOOKUP(P48,'Tiempo Objeto'!$B$2:$C$12,2,FALSE),IF(O48="INOXIDABLE",VLOOKUP(P48,'Tiempo Objeto'!$B$14:$C$22,2,FALSE),IF(O48="ALUMINIO",VLOOKUP(P48,'Tiempo Objeto'!$B$24:$C$32,2,FALSE)))) -> 1.84 | X48: =+W48*V48 -> 11.04 | Y48: =+X48*N48/3600 -> 15.333333 | Z48: 1 | AA48: =30*Z48+Z48*$C48*1.5 -> 30 | AB48: =+Z48*Analisis!$J$6 -> 25 | AC48: 0 | AD48: =30*AC48+AC48*$C48*1.5 -> 0 | AE48: =+AD48*Analisis!$J$7 -> 0 | AF48: =+L48+U48+Y48+AB48+AE48 -> 183.15604 | AG48: =+AF48/(1-Analisis!$E$9) -> 228.94505 | AH48: =+AG48*C48 -> 0
B49: 11-C-9662-02 | C49: =IFERROR(VLOOKUP(B49,'REQ GALV'!A:B,2,0),0) -> 0 | D49: =+AG49 -> 322.72024 | E49: 12GA | F49: DECAPADO | G49: 8.57 | H49: 27 | I49: 0.105 | J49: 28.24 | K49: =+L49*2.2/J49 -> 13.319309 | L49: =+VLOOKUP(E49,Material!$H$2:$M$17,6,FALSE)*G49*H49*(1+Material!$K$14) -> 170.9715 | M49: =+Analisis!$J$5 -> T5.0 | N49: =+VLOOKUP(M49,Material!$A$3:$B$58,2,FALSE) -> 5000 | O49: ACERO A36 | P49: Cal 12 | Q49: =+IF(O49="ACERO A36",VLOOKUP(P49,'Velocidades Std 1500 w'!$B$2:$F$15,5,FALSE),IF(O49="INOXIDABLE",VLOOKUP(P49,'Velocidades Std 1500 w'!$B$17:$F$28,5,FALSE),IF(O49="ALUMINIO",VLOOKUP(P49,'Velocidades Std 1500 w'!$B$30:$F$38,5,FALSE)))) -> 4.3859649e-06 | R49: =+Q49*N49 -> 0.021929825 | S49: =+Q49*T49*3600 -> 33.747376 | T49: =(+H49*2+G49*2+V49*1.5)*25.4*1.05 -> 2137.3338 | U49: =+T49*R49 -> 46.871355 | V49: 6 | W49: =+IF(O49="ACERO A36",VLOOKUP(P49,'Tiempo Objeto'!$B$2:$C$12,2,FALSE),IF(O49="INOXIDABLE",VLOOKUP(P49,'Tiempo Objeto'!$B$14:$C$22,2,FALSE),IF(O49="ALUMINIO",VLOOKUP(P49,'Tiempo Objeto'!$B$24:$C$32,2,FALSE)))) -> 1.84 | X49: =+W49*V49 -> 11.04 | Y49: =+X49*N49/3600 -> 15.333333 | Z49: 1 | AA49: =30*Z49+Z49*$C49*1.5 -> 30 | AB49: =+Z49*Analisis!$J$6 -> 25 | AC49: 0 | AD49: =30*AC49+AC49*$C49*1.5 -> 0 | AE49: =+AD49*Analisis!$J$7 -> 0 | AF49: =+L49+U49+Y49+AB49+AE49 -> 258.17619 | AG49: =+AF49/(1-Analisis!$E$9) -> 322.72024 | AH49: =+AG49*C49 -> 0
B50: 11-C-9662-03 | C50: =IFERROR(VLOOKUP(B50,'REQ GALV'!A:B,2,0),0) -> 0 | D50: =+AG50 -> 416.49542 | E50: 12GA | F50: DECAPADO | G50: 8.57 | H50: 37 | I50: 0.105 | J50: 28.24 | K50: =+L50*2.2/J50 -> 18.252387 | L50: =+VLOOKUP(E50,Material!$H$2:$M$17,6,FALSE)*G50*H50*(1+Material!$K$14) -> 234.29428 | M50: =+Analisis!$J$5 -> T5.0 | N50: =+VLOOKUP(M50,Material!$A$3:$B$58,2,FALSE) -> 5000 | O50: ACERO A36 | P50: Cal 12 | Q50: =+IF(O50="ACERO A36",VLOOKUP(P50,'Velocidades Std 1500 w'!$B$2:$F$15,5,FALSE),IF(O50="INOXIDABLE",VLOOKUP(P50,'Velocidades Std 1500 w'!$B$17:$F$28,5,FALSE),IF(O50="ALUMINIO",VLOOKUP(P50,'Velocidades Std 1500 w'!$B$30:$F$38,5,FALSE)))) -> 4.3859649e-06 | R50: =+Q50*N50 -> 0.021929825 | S50: =+Q50*T50*3600 -> 42.169481 | T50: =(+H50*2+G50*2+V50*1.5)*25.4*1.05 -> 2670.7338 | U50: =+T50*R50 -> 58.568724 | V50: 6 | W50: =+IF(O50="ACERO A36",VLOOKUP(P50,'Tiempo Objeto'!$B$2:$C$12,2,FALSE),IF(O50="INOXIDABLE",VLOOKUP(P50,'Tiempo Objeto'!$B$14:$C$22,2,FALSE),IF(O50="ALUMINIO",VLOOKUP(P50,'Tiempo Objeto'!$B$24:$C$32,2,FALSE)))) -> 1.84 | X50: =+W50*V50 -> 11.04 | Y50: =+X50*N50/3600 -> 15.333333 | Z50: 1 | AA50: =30*Z50+Z50*$C50*1.5 -> 30 | AB50: =+Z50*Analisis!$J$6 -> 25 | AC50: 0 | AD50: =30*AC50+AC50*$C50*1.5 -> 0 | AE50: =+AD50*Analisis!$J$7 -> 0 | AF50: =+L50+U50+Y50+AB50+AE50 -> 333.19633 | AG50: =+AF50/(1-Analisis!$E$9) -> 416.49542 | AH50: =+AG50*C50 -> 0
... B146: PP14252-17 | C146: =IFERROR(VLOOKUP(B146,'REQ GALV'!A:B,2,0),0) -> 0 | D146: =+AG146 -> 530.00977 | E146: 188al | F146: DECAPADO | G146: 5.048 | H146: 39.92 | I146: 0.105 | J146: 28.24 | K146: =+L146*2.2/J146 -> 17.39956 | L146: =+VLOOKUP(E146,Material!$H$2:$M$17,6,FALSE)*G146*H146*(1+Material!$K$14) -> 223.34708 | M146: =+Analisis!$J$5 -> T5.0 | N146: =+VLOOKUP(M146,Material!$A$3:$B$58,2,FALSE) -> 5000 | O146: ACERO A36 | P146: Cal 12 | Q146: =+IF(O146="ACERO A36",VLOOKUP(P146,'Velocidades Std 1500 w'!$B$2:$F$15,5,FALSE),IF(O146="INOXIDABLE",VLOOKUP(P146,'Velocidades Std 1500 w'!$B$17:$F$28,5,FALSE),IF(O146="ALUMINIO",VLOOKUP(P146,'Velocidades Std 1500 w'!$B$30:$F$38,5,FALSE)))) -> 4.3859649e-06 | R146: =+Q146*N146 -> 0.021929825 | S146: =+Q146*T146*3600 -> 46.715733 | T146: =(+H146*2+G146*2+V146*1.5)*25.4*1.05 -> 2958.6631 | U146: =+T146*R146 -> 64.882963 | V146: 14 | W146: =+IF(O146="ACERO A36",VLOOKUP(P146,'Tiempo Objeto'!$B$2:$C$12,2,FALSE),IF(O146="INOXIDABLE",VLOOKUP(P146,'Tiempo Objeto'!$B$14:$C$22,2,FALSE),IF(O146="ALUMINIO",VLOOKUP(P146,'Tiempo Objeto'!$B$24:$C$32,2,FALSE)))) -> 1.84 | X146: =+W146*V146 -> 25.76 | Y146: =+X146*N146/3600 -> 35.777778 | Z146: 4 | AA146: =30*Z146+Z146*$C146*1.5 -> 120 | AB146: =+Z146*Analisis!$J$6 -> 100 | AC146: 0 | AD146: =30*AC146+AC146*$C146*1.5 -> 0 | AE146: =+AD146*Analisis!$J$7 -> 0 | AF146: =+L146+U146+Y146+AB146+AE146 -> 424.00782 | AG146: =+AF146/(1-Analisis!$E$9) -> 530.00977 | AH146: =+AG146*C146 -> 0
B147: 11-6284-01 | C147: =IFERROR(VLOOKUP(B147,'REQ GALV'!A:B,2,0),0) -> 210 | D147: =+AG147 -> 188.10087 | E147: 12ga | F147: DECAPADO | G147: 6.64 | H147: 3.64 | I147: 0.105 | J147: 28.24 | K147: =+L147*2.2/J147 -> 1.3912545 | L147: =+VLOOKUP(E147,Material!$H$2:$M$17,6,FALSE)*G147*H147*(1+Material!$K$14) -> 17.858649 | M147: =+Analisis!$J$5 -> T5.0 | N147: =+VLOOKUP(M147,Material!$A$3:$B$58,2,FALSE) -> 5000 | O147: ACERO A36 | P147: Cal 12 | Q147: =+IF(O147="ACERO A36",VLOOKUP(P147,'Velocidades Std 1500 w'!$B$2:$F$15,5,FALSE),IF(O147="INOXIDABLE",VLOOKUP(P147,'Velocidades Std 1500 w'!$B$17:$F$28,5,FALSE),IF(O147="ALUMINIO",VLOOKUP(P147,'Velocidades Std 1500 w'!$B$30:$F$38,5,FALSE)))) -> 4.3859649e-06 | R147: =+Q147*N147 -> 0.021929825 | S147: =+Q147*T147*3600 -> 12.447872 | T147: =(+H147*2+G147*2+V147*1.5)*25.4*1.05 -> 788.3652 | U147: =+T147*R147 -> 17.288711 | V147: 6 | W147: =+IF(O147="ACERO A36",VLOOKUP(P147,'Tiempo Objeto'!$B$2:$C$12,2,FALSE),IF(O147="INOXIDABLE",VLOOKUP(P147,'Tiempo Objeto'!$B$14:$C$22,2,FALSE),IF(O147="ALUMINIO",VLOOKUP(P147,'Tiempo Objeto'!$B$24:$C$32,2,FALSE)))) -> 1.84 | X147: =+W147*V147 -> 11.04 | Y147: =+X147*N147/3600 -> 15.333333 | Z147: 4 | AA147: =30*Z147+Z147*$C147*1.5 -> 1380 | AB147: =+Z147*Analisis!$J$6 -> 100 | AC147: 0 | AD147: =30*AC147+AC147*$C147*1.5 -> 0 | AE147: =+AD147*Analisis!$J$7 -> 0 | AF147: =+L147+U147+Y147+AB147+AE147 -> 150.48069 | AG147: =+AF147/(1-Analisis!$E$9) -> 188.10087 | AH147: =+AG147*C147 -> 39501.182 | AI147: =+L147*C147 -> 3750.3163
B148: 11-8233-01 | C148: =IFERROR(VLOOKUP(B148,'REQ GALV'!A:B,2,0),0) -> 0 | D148: =+AG148 -> 125.55262 | E148: 12ga | F148: DECAPADO | G148: 3.64 | H148: 6.63 | I148: 0.105 | J148: 28.24 | K148: =+L148*2.2/J148 -> 1.3891593 | L148: =+VLOOKUP(E148,Material!$H$2:$M$17,6,FALSE)*G148*H148*(1+Material!$K$14) -> 17.831753 | M148: =+Analisis!$J$5 -> T5.0 | N148: =+VLOOKUP(M148,Material!$A$3:$B$58,2,FALSE) -> 5000 | O148: ACERO A36 | P148: Cal 12 | Q148: =+IF(O148="ACERO A36",VLOOKUP(P148,'Velocidades Std 1500 w'!$B$2:$F$15,5,FALSE),IF(O148="INOXIDABLE",VLOOKUP(P148,'Velocidades Std 1500 w'!$B$17:$F$28,5,FALSE),IF(O148="ALUMINIO",VLOOKUP(P148,'Velocidades Std 1500 w'!$B$30:$F$38,5,FALSE)))) -> 4.3859649e-06 | R148: =+Q148*N148 -> 0.021929825 | S148: =+Q148*T148*3600 -> 12.439449 | T148: =(+H148*2+G148*2+V148*1.5)*25.4*1.05 -> 787.8318 | U148: =+T148*R148 -> 17.277013 | V148: 6 | W148: =+IF(O148="ACERO A36",VLOOKUP(P148,'Tiempo Objeto'!$B$2:$C$12,2,FALSE),IF(O148="INOXIDABLE",VLOOKUP(P148,'Tiempo Objeto'!$B$14:$C$22,2,FALSE),IF(O148="ALUMINIO",VLOOKUP(P148,'Tiempo Objeto'!$B$24:$C$32,2,FALSE)))) -> 1.84 | X148: =+W148*V148 -> 11.04 | Y148: =+X148*N148/3600 -> 15.333333 | Z148: 2 | AA148: =30*Z148+Z148*$C148*1.5 -> 60 | AB148: =+Z148*Analisis!$J$6 -> 50 | AC148: 0 | AD148: =30*AC148+AC148*$C148*1.5 -> 0 | AE148: =+AD148*Analisis!$J$7 -> 0 | AF148: =+L148+U148+Y148+AB148+AE148 -> 100.4421 | AG148: =+AF148/(1-Analisis!$E$9) -> 125.55262 | AH148: =+AG148*C148 -> 0
B149: 11-A-6030-01 | C149: =IFERROR(VLOOKUP(B149,'REQ GALV'!A:B,2,0),0) -> 0 | D149: =+AG149 -> 29.818249 | E149: 12ga | F149: DECAPADO | G149: 2 | H149: 2.94 | I149: 0.105 | J149: 28.24 | K149: =+L149*2.2/J149 -> 0.33846553 | L149: =+VLOOKUP(E149,Material!$H$2:$M$17,6,FALSE)*G149*H149*(1+Material!$K$14) -> 4.3446667 | M149: =+Analisis!$J$5 -> T5.0 | N149: =+VLOOKUP(M149,Material!$A$3:$B$58,2,FALSE) -> 5000 | O149: ACERO A36 | P149: Cal 12 | Q149: =+IF(O149="ACERO A36",VLOOKUP(P149,'Velocidades Std 1500 w'!$B$2:$F$15,5,FALSE),IF(O149="INOXIDABLE",VLOOKUP(P149,'Velocidades Std 1500 w'!$B$17:$F$28,5,FALSE),IF(O149="ALUMINIO",VLOOKUP(P149,'Velocidades Std 1500 w'!$B$30:$F$38,5,FALSE)))) -> 4.3859649e-06 | R149: =+Q149*N149 -> 0.021929825 | S149: =+Q149*T149*3600 -> 6.6871516 | T149: =(+H149*2+G149*2+V149*1.5)*25.4*1.05 -> 423.5196 | U149: =+T149*R149 -> 9.2877105 | V149: 4 | W149: =+IF(O149="ACERO A36",VLOOKUP(P149,'Tiempo Objeto'!$B$2:$C$12,2,FALSE),IF(O149="INOXIDABLE",VLOOKUP(P149,'Tiempo Objeto'!$B$14:$C$22,2,FALSE),IF(O149="ALUMINIO",VLOOKUP(P149,'Tiempo Objeto'!$B$24:$C$32,2,FALSE)))) -> 1.84 | X149: =+W149*V149 -> 7.36 | Y149: =+X149*N149/3600 -> 10.222222 | Z149: 0 | AA149: =30*Z149+Z149*$C149*1.5 -> 0 | AB149: =+Z149*Analisis!$J$6 -> 0 | AC149: 0 | AD149: =30*AC149+AC149*$C149*1.5 -> 0 | AE149: =+AD149*Analisis!$J$7 -> 0 | AF149: =+L149+U149+Y149+AB149+AE149 -> 23.854599 | AG149: =+AF149/(1-Analisis!$E$9) -> 29.818249 | AH149: =+AG149*C149 -> 0
B150: 11-A-6030-02 | C150: =IFERROR(VLOOKUP(B150,'REQ GALV'!A:B,2,0),0) -> 0 | D150: =+AG150 -> 27.534768 | E150: 12ga | F150: DECAPADO | G150: 2 | H150: 2.25 | I150: 0.105 | J150: 28.24 | K150: =+L150*2.2/J150 -> 0.25902975 | L150: =+VLOOKUP(E150,Material!$H$2:$M$17,6,FALSE)*G150*H150*(1+Material!$K$14) -> 3.325 | M150: =+Analisis!$J$5 -> T5.0 | N150: =+VLOOKUP(M150,Material!$A$3:$B$58,2,FALSE) -> 5000 | O150: ACERO A36 | P150: Cal 12 | Q150: =+IF(O150="ACERO A36",VLOOKUP(P150,'Velocidades Std 1500 w'!$B$2:$F$15,5,FALSE),IF(O150="INOXIDABLE",VLOOKUP(P150,'Velocidades Std 1500 w'!$B$17:$F$28,5,FALSE),IF(O150="ALUMINIO",VLOOKUP(P150,'Velocidades Std 1500 w'!$B$30:$F$38,5,FALSE)))) -> 4.3859649e-06 | R150: =+Q150*N150 -> 0.021929825 | S150: =+Q150*T150*3600 -> 6.1060263 | T150: =(+H150*2+G150*2+V150*1.5)*25.4*1.05 -> 386.715 | U150: =+T150*R150 -> 8.4805921 | V150: 4 | W150: =+IF(O150="ACERO A36",VLOOKUP(P150,'Tiempo Objeto'!$B$2:$C$12,2,FALSE),IF(O150="INOXIDABLE",VLOOKUP(P150,'Tiempo Objeto'!$B$14:$C$22,2,FALSE),IF(O150="ALUMINIO",VLOOKUP(P150,'Tiempo Objeto'!$B$24:$C$32,2,FALSE)))) -> 1.84 | X150: =+W150*V150 -> 7.36 | Y150: =+X150*N150/3600 -> 10.222222 | Z150: 0 | AA150: =30*Z150+Z150*$C150*1.5 -> 0 | AB150: =+Z150*Analisis!$J$6 -> 0 | AC150: 0 | AD150: =30*AC150+AC150*$C150*1.5 -> 0 | AE150: =+AD150*Analisis!$J$7 -> 0 | AF150: =+L150+U150+Y150+AB150+AE150 -> 22.027814 | AG150: =+AF150/(1-Analisis!$E$9) -> 27.534768 | AH150: =+AG150*C150 -> 0
B151: 11-A-6030-03 | C151: =IFERROR(VLOOKUP(B151,'REQ GALV'!A:B,2,0),0) -> 0 | D151: =+AG151 -> 34.782339 | E151: 12ga | F151: DECAPADO | G151: 2 | H151: 4.44 | I151: 0.105 | J151: 28.24 | K151: =+L151*2.2/J151 -> 0.51115203 | L151: =+VLOOKUP(E151,Material!$H$2:$M$17,6,FALSE)*G151*H151*(1+Material!$K$14) -> 6.5613333 | M151: =+Analisis!$J$5 -> T5.0 | N151: =+VLOOKUP(M151,Material!$A$3:$B$58,2,FALSE) -> 5000 | O151: ACERO A36 | P151: Cal 12 | Q151: =+IF(O151="ACERO A36",VLOOKUP(P151,'Velocidades Std 1500 w'!$B$2:$F$15,5,FALSE),IF(O151="INOXIDABLE",VLOOKUP(P151,'Velocidades Std 1500 w'!$B$17:$F$28,5,FALSE),IF(O151="ALUMINIO",VLOOKUP(P151,'Velocidades Std 1500 w'!$B$30:$F$38,5,FALSE)))) -> 4.3859649e-06 | R151: =+Q151*N151 -> 0.021929825 | S151: =+Q151*T151*3600 -> 7.9504674 | T151: =(+H151*2+G151*2+V151*1.5)*25.4*1.05 -> 503.5296 | U151: =+T151*R151 -> 11.042316 | V151: 4 | W151: =+IF(O151="ACERO A36",VLOOKUP(P151,'Tiempo Objeto'!$B$2:$C$12,2,FALSE),IF(O151="INOXIDABLE",VLOOKUP(P151,'Tiempo Objeto'!$B$14:$C$22,2,FALSE),IF(O151="ALUMINIO",VLOOKUP(P151,'Tiempo Objeto'!$B$24:$C$32,2,FALSE)))) -> 1.84 | X151: =+W151*V151 -> 7.36 | Y151: =+X151*N151/3600 -> 10.222222 | Z151: 0 | AA151: =30*Z151+Z151*$C151*1.5 -> 0 | AB151: =+Z151*Analisis!$J$6 -> 0 | AC151: 0 | AD151: =30*AC151+AC151*$C151*1.5 -> 0 | AE151: =+AD151*Analisis!$J$7 -> 0 | AF151: =+L151+U151+Y151+AB151+AE151 -> 27.825871 | AG151: =+AF151/(1-Analisis!$E$9) -> 34.782339 | AH151: =+AG151*C151 -> 0
B152: 11-A-6030-04 | C152: =IFERROR(VLOOKUP(B152,'REQ GALV'!A:B,2,0),0) -> 0 | D152: =+AG152 -> 28.362116 | E152: 12ga | F152: DECAPADO | G152: 2 | H152: 2.5 | I152: 0.105 | J152: 28.24 | K152: =+L152*2.2/J152 -> 0.28781083 | L152: =+VLOOKUP(E152,Material!$H$2:$M$17,6,FALSE)*G152*H152*(1+Material!$K$14) -> 3.6944444 | M152: =+Analisis!$J$5 -> T5.0 | N152: =+VLOOKUP(M152,Material!$A$3:$B$58,2,FALSE) -> 5000 | O152: ACERO A36 | P152: Cal 12 | Q152: =+IF(O152="ACERO A36",VLOOKUP(P152,'Velocidades Std 1500 w'!$B$2:$F$15,5,FALSE),IF(O152="INOXIDABLE",VLOOKUP(P152,'Velocidades Std 1500 w'!$B$17:$F$28,5,FALSE),IF(O152="ALUMINIO",VLOOKUP(P152,'Velocidades Std 1500 w'!$B$30:$F$38,5,FALSE)))) -> 4.3859649e-06 | R152: =+Q152*N152 -> 0.021929825 | S152: =+Q152*T152*3600 -> 6.3165789 | T152: =(+H152*2+G152*2+V152*1.5)*25.4*1.05 -> 400.05 | U152: =+T152*R152 -> 8.7730263 | V152: 4 | W152: =+IF(O152="ACERO A36",VLOOKUP(P152,'Tiempo Objeto'!$B$2:$C$12,2,FALSE),IF(O152="INOXIDABLE",VLOOKUP(P152,'Tiempo Objeto'!$B$14:$C$22,2,FALSE),IF(O152="ALUMINIO",VLOOKUP(P152,'Tiempo Objeto'!$B$24:$C$32,2,FALSE)))) -> 1.84 | X152: =+W152*V152 -> 7.36 | Y152: =+X152*N152/3600 -> 10.222222 | Z152: 0 | AA152: =30*Z152+Z152*$C152*1.5 -> 0 | AB152: =+Z152*Analisis!$J$6 -> 0 | AC152: 0 | AD152: =30*AC152+AC152*$C152*1.5 -> 0 | AE152: =+AD152*Analisis!$J$7 -> 0 | AF152: =+L152+U152+Y152+AB152+AE152 -> 22.689693 | AG152: =+AF152/(1-Analisis!$E$9) -> 28.362116 | AH152: =+AG152*C152 -> 0
B153: 11-A-6030-05 | C153: =IFERROR(VLOOKUP(B153,'REQ GALV'!A:B,2,0),0) -> 30 | D153: =+AG153 -> 31.50604 | E153: 12ga | F153: DECAPADO | G153: 2 | H153: 3.45 | I153: 0.105 | J153: 28.24 | K153: =+L153*2.2/J153 -> 0.39717894 | L153: =+VLOOKUP(E153,Material!$H$2:$M$17,6,FALSE)*G153*H153*(1+Material!$K$14) -> 5.0983333 | M153: =+Analisis!$J$5 -> T5.0 | N153: =+VLOOKUP(M153,Material!$A$3:$B$58,2,FALSE) -> 5000 | O153: ACERO A36 | P153: Cal 12 | Q153: =+IF(O153="ACERO A36",VLOOKUP(P153,'Velocidades Std 1500 w'!$B$2:$F$15,5,FALSE),IF(O153="INOXIDABLE",VLOOKUP(P153,'Velocidades Std 1500 w'!$B$17:$F$28,5,FALSE),IF(O153="ALUMINIO",VLOOKUP(P153,'Velocidades Std 1500 w'!$B$30:$F$38,5,FALSE)))) -> 4.3859649e-06 | R153: =+Q153*N153 -> 0.021929825 | S153: =+Q153*T153*3600 -> 7.1166789 | T153: =(+H153*2+G153*2+V153*1.5)*25.4*1.05 -> 450.723 | U153: =+T153*R153 -> 9.8842763 | V153: 4 | W153: =+IF(O153="ACERO A36",VLOOKUP(P153,'Tiempo Objeto'!$B$2:$C$12,2,FALSE),IF(O153="INOXIDABLE",VLOOKUP(P153,'Tiempo Objeto'!$B$14:$C$22,2,FALSE),IF(O153="ALUMINIO",VLOOKUP(P153,'Tiempo Objeto'!$B$24:$C$32,2,FALSE)))) -> 1.84 | X153: =+W153*V153 -> 7.36 | Y153: =+X153*N153/3600 -> 10.222222 | Z153: 0 | AA153: =30*Z153+Z153*$C153*1.5 -> 0 | AB153: =+Z153*Analisis!$J$6 -> 0 | AC153: 0 | AD153: =30*AC153+AC153*$C153*1.5 -> 0 | AE153: =+AD153*Analisis!$J$7 -> 0 | AF153: =+L153+U153+Y153+AB153+AE153 -> 25.204832 | AG153: =+AF153/(1-Analisis!$E$9) -> 31.50604 | AH153: =+AG153*C153 -> 945.1812 | AI153: =+L153*C153 -> 152.95
B154: 11-A-6030-06 | C154: =IFERROR(VLOOKUP(B154,'REQ GALV'!A:B,2,0),0) -> 0 | D154: =+AG154 -> 30.645598 | E154: 12ga | F154: DECAPADO | G154: 2 | H154: 3.19 | I154: 0.105 | J154: 28.24 | K154: =+L154*2.2/J154 -> 0.36724662 | L154: =+VLOOKUP(E154,Material!$H$2:$M$17,6,FALSE)*G154*H154*(1+Material!$K$14) -> 4.7141111 | M154: =+Analisis!$J$5 -> T5.0 | N154: =+VLOOKUP(M154,Material!$A$3:$B$58,2,FALSE) -> 5000 | O154: ACERO A36 | P154: Cal 12 | Q154: =+IF(O154="ACERO A36",VLOOKUP(P154,'Velocidades Std 1500 w'!$B$2:$F$15,5,FALSE),IF(O154="INOXIDABLE",VLOOKUP(P154,'Velocidades Std 1500 w'!$B$17:$F$28,5,FALSE),IF(O154="ALUMINIO",VLOOKUP(P154,'Velocidades Std 1500 w'!$B$30:$F$38,5,FALSE)))) -> 4.3859649e-06 | R154: =+Q154*N154 -> 0.021929825 | S154: =+Q154*T154*3600 -> 6.8977042 | T154: =(+H154*2+G154*2+V154*1.5)*25.4*1.05 -> 436.8546 | U154: =+T154*R154 -> 9.5801447 | V154: 4 | W154: =+IF(O154="ACERO A36",VLOOKUP(P154,'Tiempo Objeto'!$B$2:$C$12,2,FALSE),IF(O154="INOXIDABLE",VLOOKUP(P154,'Tiempo Objeto'!$B$14:$C$22,2,FALSE),IF(O154="ALUMINIO",VLOOKUP(P154,'Tiempo Objeto'!$B$24:$C$32,2,FALSE)))) -> 1.84 | X154: =+W154*V154 -> 7.36 | Y154: =+X154*N154/3600 -> 10.222222 | Z154: 0 | AA154: =30*Z154+Z154*$C154*1.5 -> 0 | AB154: =+Z154*Analisis!$J$6 -> 0 | AC154: 0 | AD154: =30*AC154+AC154*$C154*1.5 -> 0 | AE154: =+AD154*Analisis!$J$7 -> 0 | AF154: =+L154+U154+Y154+AB154+AE154 -> 24.516478 | AG154: =+AF154/(1-Analisis!$E$9) -> 30.645598 | AH154: =+AG154*C154 -> 0
B155: 11-A-6030-07 | C155: =IFERROR(VLOOKUP(B155,'REQ GALV'!A:B,2,0),0) -> 0 | D155: =+AG155 -> 41.368032 | E155: 12ga | F155: DECAPADO | G155: 2 | H155: 6.43 | I155: 0.105 | J155: 28.24 | K155: =+L155*2.2/J155 -> 0.74024945 | L155: =+VLOOKUP(E155,Material!$H$2:$M$17,6,FALSE)*G155*H155*(1+Material!$K$14) -> 9.5021111 | M155: =+Analisis!$J$5 -> T5.0 | N155: =+VLOOKUP(M155,Material!$A$3:$B$58,2,FALSE) -> 5000 | O155: ACERO A36 | P155: Cal 12 | Q155: =+IF(O155="ACERO A36",VLOOKUP(P155,'Velocidades Std 1500 w'!$B$2:$F$15,5,FALSE),IF(O155="INOXIDABLE",VLOOKUP(P155,'Velocidades Std 1500 w'!$B$17:$F$28,5,FALSE),IF(O155="ALUMINIO",VLOOKUP(P155,'Velocidades Std 1500 w'!$B$30:$F$38,5,FALSE)))) -> 4.3859649e-06 | R155: =+Q155*N155 -> 0.021929825 | S155: =+Q155*T155*3600 -> 9.6264663 | T155: =(+H155*2+G155*2+V155*1.5)*25.4*1.05 -> 609.6762 | U155: =+T155*R155 -> 13.370092 | V155: 4 | W155: =+IF(O155="ACERO A36",VLOOKUP(P155,'Tiempo Objeto'!$B$2:$C$12,2,FALSE),IF(O155="INOXIDABLE",VLOOKUP(P155,'Tiempo Objeto'!$B$14:$C$22,2,FALSE),IF(O155="ALUMINIO",VLOOKUP(P155,'Tiempo Objeto'!$B$24:$C$32,2,FALSE)))) -> 1.84 | X155: =+W155*V155 -> 7.36 | Y155: =+X155*N155/3600 -> 10.222222 | Z155: 0 | AA155: =30*Z155+Z155*$C155*1.5 -> 0 | AB155: =+Z155*Analisis!$J$6 -> 0 | AC155: 0 | AD155: =30*AC155+AC155*$C155*1.5 -> 0 | AE155: =+AD155*Analisis!$J$7 -> 0 | AF155: =+L155+U155+Y155+AB155+AE155 -> 33.094425 | AG155: =+AF155/(1-Analisis!$E$9) -> 41.368032 | AH155: =+AG155*C155 -> 0
B156: 11-A-6030-08 | C156: =IFERROR(VLOOKUP(B156,'REQ GALV'!A:B,2,0),0) -> 0 | D156: =+AG156 -> 26.939077 | E156: 12ga | F156: DECAPADO | G156: 2 | H156: 2.07 | I156: 0.105 | J156: 28.24 | K156: =+L156*2.2/J156 -> 0.23830737 | L156: =+VLOOKUP(E156,Material!$H$2:$M$17,6,FALSE)*G156*H156*(1+Material!$K$14) -> 3.059 | M156: =+Analisis!$J$5 -> T5.0 | N156: =+VLOOKUP(M156,Material!$A$3:$B$58,2,FALSE) -> 5000 | O156: ACERO A36 | P156: Cal 12 | Q156: =+IF(O156="ACERO A36",VLOOKUP(P156,'Velocidades Std 1500 w'!$B$2:$F$15,5,FALSE),IF(O156="INOXIDABLE",VLOOKUP(P156,'Velocidades Std 1500 w'!$B$17:$F$28,5,FALSE),IF(O156="ALUMINIO",VLOOKUP(P156,'Velocidades Std 1500 w'!$B$30:$F$38,5,FALSE)))) -> 4.3859649e-06 | R156: =+Q156*N156 -> 0.021929825 | S156: =+Q156*T156*3600 -> 5.9544284 | T156: =(+H156*2+G156*2+V156*1.5)*25.4*1.05 -> 377.1138 | U156: =+T156*R156 -> 8.2700395 | V156: 4 | W156: =+IF(O156="ACERO A36",VLOOKUP(P156,'Tiempo Objeto'!$B$2:$C$12,2,FALSE),IF(O156="INOXIDABLE",VLOOKUP(P156,'Tiempo Objeto'!$B$14:$C$22,2,FALSE),IF(O156="ALUMINIO",VLOOKUP(P156,'Tiempo Objeto'!$B$24:$C$32,2,FALSE)))) -> 1.84 | X156: =+W156*V156 -> 7.36 | Y156: =+X156*N156/3600 -> 10.222222 | Z156: 0 | AA156: =30*Z156+Z156*$C156*1.5 -> 0 | AB156: =+Z156*Analisis!$J$6 -> 0 | AC156: 0 | AD156: =30*AC156+AC156*$C156*1.5 -> 0 | AE156: =+AD156*Analisis!$J$7 -> 0 | AF156: =+L156+U156+Y156+AB156+AE156 -> 21.551262 | AG156: =+AF156/(1-Analisis!$E$9) -> 26.939077 | AH156: =+AG156*C156 -> 0
B157: 11-A-6068-01 | C157: =IFERROR(VLOOKUP(B157,'REQ GALV'!A:B,2,0),0) -> 150 | D157: =+AG157 -> 29.424498 | E157: 16ga | F157: DECAPADO | G157: 2.38 | H157: 4.5 | I157: 0.105 | J157: 28.24 | K157: =+L157*2.2/J157 -> 0.40457208 | L157: =+VLOOKUP(E157,Material!$H$2:$M$17,6,FALSE)*G157*H157*(1+Material!$K$14) -> 5.1932344 | M157: =+Analisis!$J$5 -> T5.0 | N157: =+VLOOKUP(M157,Material!$A$3:$B$58,2,FALSE) -> 5000 | O157: ACERO A36 | P157: Cal 12 | Q157: =+IF(O157="ACERO A36",VLOOKUP(P157,'Velocidades Std 1500 w'!$B$2:$F$15,5,FALSE),IF(O157="INOXIDABLE",VLOOKUP(P157,'Velocidades Std 1500 w'!$B$17:$F$28,5,FALSE),IF(O157="ALUMINIO",VLOOKUP(P157,'Velocidades Std 1500 w'!$B$30:$F$38,5,FALSE)))) -> 4.3859649e-06 | R157: =+Q157*N157 -> 0.021929825 | S157: =+Q157*T157*3600 -> 7.6893821 | T157: =(+H157*2+G157*2+V157*1.5)*25.4*1.05 -> 486.9942 | U157: =+T157*R157 -> 10.679697 | V157: 3 | W157: =+IF(O157="ACERO A36",VLOOKUP(P157,'Tiempo Objeto'!$B$2:$C$12,2,FALSE),IF(O157="INOXIDABLE",VLOOKUP(P157,'Tiempo Objeto'!$B$14:$C$22,2,FALSE),IF(O157="ALUMINIO",VLOOKUP(P157,'Tiempo Objeto'!$B$24:$C$32,2,FALSE)))) -> 1.84 | X157: =+W157*V157 -> 5.52 | Y157: =+X157*N157/3600 -> 7.6666667 | Z157: 0 | AA157: =30*Z157+Z157*$C157*1.5 -> 0 | AB157: =+Z157*Analisis!$J$6 -> 0 | AC157: 0 | AD157: =30*AC157+AC157*$C157*1.5 -> 0 | AE157: =+AD157*Analisis!$J$7 -> 0 | AF157: =+L157+U157+Y157+AB157+AE157 -> 23.539598 | AG157: =+AF157/(1-Analisis!$E$9) -> 29.424498 | AH157: =+AG157*C157 -> 4413.6747 | AI157: =+L157*C157 -> 778.98516
B158: 11-A-6201-01 | C158: =IFERROR(VLOOKUP(B158,'REQ GALV'!A:B,2,0),0) -> 4800 | D158: =+AG158 -> 89.848256 | E158: 10ga | F158: DECAPADO | G158: 7.63 | H158: 3.56 | I158: 0.105 | J158: 28.24 | K158: =+L158*2.2/J158 -> 1.9055761 | L158: =+VLOOKUP(E158,Material!$H$2:$M$17,6,FALSE)*G158*H158*(1+Material!$K$14) -> 24.460667 | M158: =+Analisis!$J$5 -> T5.0 | N158: =+VLOOKUP(M158,Material!$A$3:$B$58,2,FALSE) -> 5000 | O158: ACERO A36 | P158: Cal 12 | Q158: =+IF(O158="ACERO A36",VLOOKUP(P158,'Velocidades Std 1500 w'!$B$2:$F$15,5,FALSE),IF(O158="INOXIDABLE",VLOOKUP(P158,'Velocidades Std 1500 w'!$B$17:$F$28,5,FALSE),IF(O158="ALUMINIO",VLOOKUP(P158,'Velocidades Std 1500 w'!$B$30:$F$38,5,FALSE)))) -> 4.3859649e-06 | R158: =+Q158*N158 -> 0.021929825 | S158: =+Q158*T158*3600 -> 15.740915 | T158: =(+H158*2+G158*2+V158*1.5)*25.4*1.05 -> 996.9246 | U158: =+T158*R158 -> 21.862382 | V158: 10 | W158: =+IF(O158="ACERO A36",VLOOKUP(P158,'Tiempo Objeto'!$B$2:$C$12,2,FALSE),IF(O158="INOXIDABLE",VLOOKUP(P158,'Tiempo Objeto'!$B$14:$C$22,2,FALSE),IF(O158="ALUMINIO",VLOOKUP(P158,'Tiempo Objeto'!$B$24:$C$32,2,FALSE)))) -> 1.84 | X158: =+W158*V158 -> 18.4 | Y158: =+X158*N158/3600 -> 25.555556 | Z158: 0 | AA158: =30*Z158+Z158*$C158*1.5 -> 0 | AB158: =+Z158*Analisis!$J$6 -> 0 | AC158: 0 | AD158: =30*AC158+AC158*$C158*1.5 -> 0 | AE158: =+AD158*Analisis!$J$7 -> 0 | AF158: =+L158+U158+Y158+AB158+AE158 -> 71.878604 | AG158: =+AF158/(1-Analisis!$E$9) -> 89.848256 | AH158: =+AG158*C158 -> 431271.63 | AI158: =+L158*C158 -> 117411.2
B159: 11-A-6271-01 | C159: =IFERROR(VLOOKUP(B159,'REQ GALV'!A:B,2,0),0) -> 510 | D159: =+AG159 -> 54.722633 | E159: 12ga | F159: DECAPADO | G159: 4.5 | H159: 4.75 | I159: 0.105 | J159: 28.24 | K159: =+L159*2.2/J159 -> 1.2303913 | L159: =+VLOOKUP(E159,Material!$H$2:$M$17,6,FALSE)*G159*H159*(1+Material!$K$14) -> 15.79375 | M159: =+Analisis!$J$5 -> T5.0 | N159: =+VLOOKUP(M159,Material!$A$3:$B$58,2,FALSE) -> 5000 | O159: ACERO A36 | P159: Cal 12 | Q159: =+IF(O159="ACERO A36",VLOOKUP(P159,'Velocidades Std 1500 w'!$B$2:$F$15,5,FALSE),IF(O159="INOXIDABLE",VLOOKUP(P159,'Velocidades Std 1500 w'!$B$17:$F$28,5,FALSE),IF(O159="ALUMINIO",VLOOKUP(P159,'Velocidades Std 1500 w'!$B$30:$F$38,5,FALSE)))) -> 4.3859649e-06 | R159: =+Q159*N159 -> 0.021929825 | S159: =+Q159*T159*3600 -> 10.948737 | T159: =(+H159*2+G159*2+V159*1.5)*25.4*1.05 -> 693.42 | U159: =+T159*R159 -> 15.206579 | V159: 5 | W159: =+IF(O159="ACERO A36",VLOOKUP(P159,'Tiempo Objeto'!$B$2:$C$12,2,FALSE),IF(O159="INOXIDABLE",VLOOKUP(P159,'Tiempo Objeto'!$B$14:$C$22,2,FALSE),IF(O159="ALUMINIO",VLOOKUP(P159,'Tiempo Objeto'!$B$24:$C$32,2,FALSE)))) -> 1.84 | X159: =+W159*V159 -> 9.2 | Y159: =+X159*N159/3600 -> 12.777778 | Z159: 0 | AA159: =30*Z159+Z159*$C159*1.5 -> 0 | AB159: =+Z159*Analisis!$J$6 -> 0 | AC159: 0 | AD159: =30*AC159+AC159*$C159*1.5 -> 0 | AE159: =+AD159*Analisis!$J$7 -> 0 | AF159: =+L159+U159+Y159+AB159+AE159 -> 43.778107 | AG159: =+AF159/(1-Analisis!$E$9) -> 54.722633 | AH159: =+AG159*C159 -> 27908.543 | AI159: =+L159*C159 -> 8054.8125
B160: 11-A-6271-01 | C160: =IFERROR(VLOOKUP(B160,'REQ GALV'!A:B,2,0),0) -> 510 | D160: =+AG160 -> 61.153807 | E160: 12ga | F160: DECAPADO | G160: 4.62 | H160: 5.75 | I160: 0.105 | J160: 28.24 | K160: =+L160*2.2/J160 -> 1.5291389 | L160: =+VLOOKUP(E160,Material!$H$2:$M$17,6,FALSE)*G160*H160*(1+Material!$K$14) -> 19.628583 | M160: =+Analisis!$J$5 -> T5.0 | N160: =+VLOOKUP(M160,Material!$A$3:$B$58,2,FALSE) -> 5000 | O160: ACERO A36 | P160: Cal 12 | Q160: =+IF(O160="ACERO A36",VLOOKUP(P160,'Velocidades Std 1500 w'!$B$2:$F$15,5,FALSE),IF(O160="INOXIDABLE",VLOOKUP(P160,'Velocidades Std 1500 w'!$B$17:$F$28,5,FALSE),IF(O160="ALUMINIO",VLOOKUP(P160,'Velocidades Std 1500 w'!$B$30:$F$38,5,FALSE)))) -> 4.3859649e-06 | R160: =+Q160*N160 -> 0.021929825 | S160: =+Q160*T160*3600 -> 11.892013 | T160: =(+H160*2+G160*2+V160*1.5)*25.4*1.05 -> 753.1608 | U160: =+T160*R160 -> 16.516684 | V160: 5 | W160: =+IF(O160="ACERO A36",VLOOKUP(P160,'Tiempo Objeto'!$B$2:$C$12,2,FALSE),IF(O160="INOXIDABLE",VLOOKUP(P160,'Tiempo Objeto'!$B$14:$C$22,2,FALSE),IF(O160="ALUMINIO",VLOOKUP(P160,'Tiempo Objeto'!$B$24:$C$32,2,FALSE)))) -> 1.84 | X160: =+W160*V160 -> 9.2 | Y160: =+X160*N160/3600 -> 12.777778 | Z160: 0 | AA160: =30*Z160+Z160*$C160*1.5 -> 0 | AB160: =+Z160*Analisis!$J$6 -> 0 | AC160: 0 | AD160: =30*AC160+AC160*$C160*1.5 -> 0 | AE160: =+AD160*Analisis!$J$7 -> 0 | AF160: =+L160+U160+Y160+AB160+AE160 -> 48.923045 | AG160: =+AF160/(1-Analisis!$E$9) -> 61.153807 | AH160: =+AG160*C160 -> 31188.441 | AI160: =+L160*C160 -> 10010.578
B161: 11-A-6340-01 | C161: =IFERROR(VLOOKUP(B161,'REQ GALV'!A:B,2,0),0) -> 2400 | D161: =+AG161 -> 100.6019 | E161: 10ga | F161: DECAPADO | G161: 7 | H161: 5.08 | I161: 0.105 | J161: 28.24 | K161: =+L161*2.2/J161 -> 2.4946723 | L161: =+VLOOKUP(E161,Material!$H$2:$M$17,6,FALSE)*G161*H161*(1+Material!$K$14) -> 32.022521 | M161: =+Analisis!$J$5 -> T5.0 | N161: =+VLOOKUP(M161,Material!$A$3:$B$58,2,FALSE) -> 5000 | O161: ACERO A36 | P161: Cal 12 | Q161: =+IF(O161="ACERO A36",VLOOKUP(P161,'Velocidades Std 1500 w'!$B$2:$F$15,5,FALSE),IF(O161="INOXIDABLE",VLOOKUP(P161,'Velocidades Std 1500 w'!$B$17:$F$28,5,FALSE),IF(O161="ALUMINIO",VLOOKUP(P161,'Velocidades Std 1500 w'!$B$30:$F$38,5,FALSE)))) -> 4.3859649e-06 | R161: =+Q161*N161 -> 0.021929825 | S161: =+Q161*T161*3600 -> 16.490482 | T161: =(+H161*2+G161*2+V161*1.5)*25.4*1.05 -> 1044.3972 | U161: =+T161*R161 -> 22.903447 | V161: 10 | W161: =+IF(O161="ACERO A36",VLOOKUP(P161,'Tiempo Objeto'!$B$2:$C$12,2,FALSE),IF(O161="INOXIDABLE",VLOOKUP(P161,'Tiempo Objeto'!$B$14:$C$22,2,FALSE),IF(O161="ALUMINIO",VLOOKUP(P161,'Tiempo Objeto'!$B$24:$C$32,2,FALSE)))) -> 1.84 | X161: =+W161*V161 -> 18.4 | Y161: =+X161*N161/3600 -> 25.555556 | Z161: 0 | AA161: =30*Z161+Z161*$C161*1.5 -> 0 | AB161: =+Z161*Analisis!$J$6 -> 0 | AC161: 0 | AD161: =30*AC161+AC161*$C161*1.5 -> 0 | AE161: =+AD161*Analisis!$J$7 -> 0 | AF161: =+L161+U161+Y161+AB161+AE161 -> 80.481524 | AG161: =+AF161/(1-Analisis!$E$9) -> 100.6019 | AH161: =+AG161*C161 -> 241444.57 | AI161: =+L161*C161 -> 76854.05
B162: 11-C-6085-01 | C162: =IFERROR(VLOOKUP(B162,'REQ GALV'!A:B,2,0),0) -> 0 | D162: =+AG162 -> 48.646105 | E162: 12ga | F162: DECAPADO | G162: 0.75 | H162: 1.59 | I162: 0.105 | J162: 28.24 | K162: =+L162*2.2/J162 -> 0.068642882 | L162: =+VLOOKUP(E162,Material!$H$2:$M$17,6,FALSE)*G162*H162*(1+Material!$K$14) -> 0.881125 | M162: =+Analisis!$J$5 -> T5.0 | N162: =+VLOOKUP(M162,Material!$A$3:$B$58,2,FALSE) -> 5000 | O162: ACERO A36 | P162: Cal 12 | Q162: =+IF(O162="ACERO A36",VLOOKUP(P162,'Velocidades Std 1500 w'!$B$2:$F$15,5,FALSE),IF(O162="INOXIDABLE",VLOOKUP(P162,'Velocidades Std 1500 w'!$B$17:$F$28,5,FALSE),IF(O162="ALUMINIO",VLOOKUP(P162,'Velocidades Std 1500 w'!$B$30:$F$38,5,FALSE)))) -> 4.3859649e-06 | R162: =+Q162*N162 -> 0.021929825 | S162: =+Q162*T162*3600 -> 3.8657463 | T162: =(+H162*2+G162*2+V162*1.5)*25.4*1.05 -> 244.8306 | U162: =+T162*R162 -> 5.3690921 | V162: 3 | W162: =+IF(O162="ACERO A36",VLOOKUP(P162,'Tiempo Objeto'!$B$2:$C$12,2,FALSE),IF(O162="INOXIDABLE",VLOOKUP(P162,'Tiempo Objeto'!$B$14:$C$22,2,FALSE),IF(O162="ALUMINIO",VLOOKUP(P162,'Tiempo Objeto'!$B$24:$C$32,2,FALSE)))) -> 1.84 | X162: =+W162*V162 -> 5.52 | Y162: =+X162*N162/3600 -> 7.6666667 | Z162: 1 | AA162: =30*Z162+Z162*$C162*1.5 -> 30 | AB162: =+Z162*Analisis!$J$6 -> 25 | AC162: 0 | AD162: =30*AC162+AC162*$C162*1.5 -> 0 | AE162: =+AD162*Analisis!$J$7 -> 0 | AF162: =+L162+U162+Y162+AB162+AE162 -> 38.916884 | AG162: =+AF162/(1-Analisis!$E$9) -> 48.646105 | AH162: =+AG162*C162 -> 0
B163: 11-C-6085-02 | C163: =IFERROR(VLOOKUP(B163,'REQ GALV'!A:B,2,0),0) -> 0 | D163: =+AG163 -> 48.883141 | E163: 12ga | F163: DECAPADO | G163: 0.75 | H163: 1.7 | I163: 0.105 | J163: 28.24 | K163: =+L163*2.2/J163 -> 0.073391761 | L163: =+VLOOKUP(E163,Material!$H$2:$M$17,6,FALSE)*G163*H163*(1+Material!$K$14) -> 0.94208333 | M163: =+Analisis!$J$5 -> T5.0 | N163: =+VLOOKUP(M163,Material!$A$3:$B$58,2,FALSE) -> 5000 | O163: ACERO A36 | P163: Cal 12 | Q163: =+IF(O163="ACERO A36",VLOOKUP(P163,'Velocidades Std 1500 w'!$B$2:$F$15,5,FALSE),IF(O163="INOXIDABLE",VLOOKUP(P163,'Velocidades Std 1500 w'!$B$17:$F$28,5,FALSE),IF(O163="ALUMINIO",VLOOKUP(P163,'Velocidades Std 1500 w'!$B$30:$F$38,5,FALSE)))) -> 4.3859649e-06 | R163: =+Q163*N163 -> 0.021929825 | S163: =+Q163*T163*3600 -> 3.9583895 | T163: =(+H163*2+G163*2+V163*1.5)*25.4*1.05 -> 250.698 | U163: =+T163*R163 -> 5.4977632 | V163: 3 | W163: =+IF(O163="ACERO A36",VLOOKUP(P163,'Tiempo Objeto'!$B$2:$C$12,2,FALSE),IF(O163="INOXIDABLE",VLOOKUP(P163,'Tiempo Objeto'!$B$14:$C$22,2,FALSE),IF(O163="ALUMINIO",VLOOKUP(P163,'Tiempo Objeto'!$B$24:$C$32,2,FALSE)))) -> 1.84 | X163: =+W163*V163 -> 5.52 | Y163: =+X163*N163/3600 -> 7.6666667 | Z163: 1 | AA163: =30*Z163+Z163*$C163*1.5 -> 30 | AB163: =+Z163*Analisis!$J$6 -> 25 | AC163: 0 | AD163: =30*AC163+AC163*$C163*1.5 -> 0 | AE163: =+AD163*Analisis!$J$7 -> 0 | AF163: =+L163+U163+Y163+AB163+AE163 -> 39.106513 | AG163: =+AF163/(1-Analisis!$E$9) -> 48.883141 | AH163: =+AG163*C163 -> 0
B164: 11-D-6150-01 | C164: =IFERROR(VLOOKUP(B164,'REQ GALV'!A:B,2,0),0) -> 0 | D164: =+AG164 -> 103.17112 | E164: 12ga | F164: DECAPADO | G164: 3.64 | H164: 2.88 | I164: 0.105 | J164: 28.24 | K164: =+L164*2.2/J164 -> 0.60343569 | L164: =+VLOOKUP(E164,Material!$H$2:$M$17,6,FALSE)*G164*H164*(1+Material!$K$14) -> 7.74592 | M164: =+Analisis!$J$5 -> T5.0 | N164: =+VLOOKUP(M164,Material!$A$3:$B$58,2,FALSE) -> 5000 | O164: ACERO A36 | P164: Cal 12 | Q164: =+IF(O164="ACERO A36",VLOOKUP(P164,'Velocidades Std 1500 w'!$B$2:$F$15,5,FALSE),IF(O164="INOXIDABLE",VLOOKUP(P164,'Velocidades Std 1500 w'!$B$17:$F$28,5,FALSE),IF(O164="ALUMINIO",VLOOKUP(P164,'Velocidades Std 1500 w'!$B$30:$F$38,5,FALSE)))) -> 4.3859649e-06 | R164: =+Q164*N164 -> 0.021929825 | S164: =+Q164*T164*3600 -> 8.6495021 | T164: =(+H164*2+G164*2+V164*1.5)*25.4*1.05 -> 547.8018 | U164: =+T164*R164 -> 12.013197 | V164: 5 | W164: =+IF(O164="ACERO A36",VLOOKUP(P164,'Tiempo Objeto'!$B$2:$C$12,2,FALSE),IF(O164="INOXIDABLE",VLOOKUP(P164,'Tiempo Objeto'!$B$14:$C$22,2,FALSE),IF(O164="ALUMINIO",VLOOKUP(P164,'Tiempo Objeto'!$B$24:$C$32,2,FALSE)))) -> 1.84 | X164: =+W164*V164 -> 9.2 | Y164: =+X164*N164/3600 -> 12.777778 | Z164: 2 | AA164: =30*Z164+Z164*$C164*1.5 -> 60 | AB164: =+Z164*Analisis!$J$6 -> 50 | AC164: 0 | AD164: =30*AC164+AC164*$C164*1.5 -> 0 | AE164: =+AD164*Analisis!$J$7 -> 0 | AF164: =+L164+U164+Y164+AB164+AE164 -> 82.536895 | AG164: =+AF164/(1-Analisis!$E$9) -> 103.17112 | AH164: =+AG164*C164 -> 0
B165: 11-D-6163-01 | C165: =IFERROR(VLOOKUP(B165,'REQ GALV'!A:B,2,0),0) -> 0 | D165: =+AG165 -> 310.9705 | E165: 14ga | F165: DECAPADO | G165: 13.75 | H165: 10.71 | I165: 0.105 | J165: 28.24 | K165: =+L165*2.2/J165 -> 5.9602137 | L165: =+VLOOKUP(E165,Material!$H$2:$M$17,6,FALSE)*G165*H165*(1+Material!$K$14) -> 76.507471 | M165: =+Analisis!$J$5 -> T5.0 | N165: =+VLOOKUP(M165,Material!$A$3:$B$58,2,FALSE) -> 5000 | O165: ACERO A36 | P165: Cal 12 | Q165: =+IF(O165="ACERO A36",VLOOKUP(P165,'Velocidades Std 1500 w'!$B$2:$F$15,5,FALSE),IF(O165="INOXIDABLE",VLOOKUP(P165,'Velocidades Std 1500 w'!$B$17:$F$28,5,FALSE),IF(O165="ALUMINIO",VLOOKUP(P165,'Velocidades Std 1500 w'!$B$30:$F$38,5,FALSE)))) -> 4.3859649e-06 | R165: =+Q165*N165 -> 0.021929825 | S165: =+Q165*T165*3600 -> 33.233627 | T165: =(+H165*2+G165*2+V165*1.5)*25.4*1.05 -> 2104.7964 | U165: =+T165*R165 -> 46.157816 | V165: 20 | W165: =+IF(O165="ACERO A36",VLOOKUP(P165,'Tiempo Objeto'!$B$2:$C$12,2,FALSE),IF(O165="INOXIDABLE",VLOOKUP(P165,'Tiempo Objeto'!$B$14:$C$22,2,FALSE),IF(O165="ALUMINIO",VLOOKUP(P165,'Tiempo Objeto'!$B$24:$C$32,2,FALSE)))) -> 1.84 | X165: =+W165*V165 -> 36.8 | Y165: =+X165*N165/3600 -> 51.111111 | Z165: 3 | AA165: =30*Z165+Z165*$C165*1.5 -> 90 | AB165: =+Z165*Analisis!$J$6 -> 75 | AC165: 0 | AD165: =30*AC165+AC165*$C165*1.5 -> 0 | AE165: =+AD165*Analisis!$J$7 -> 0 | AF165: =+L165+U165+Y165+AB165+AE165 -> 248.7764 | AG165: =+AF165/(1-Analisis!$E$9) -> 310.9705 | AH165: =+AG165*C165 -> 0
B166: 11-D-6164-01 | C166: =IFERROR(VLOOKUP(B166,'REQ GALV'!A:B,2,0),0) -> 0 | D166: =+AG166 -> 653.63108 | E166: 14ga | F166: DECAPADO | G166: 16.26 | H166: 11.5 | I166: 0.105 | J166: 28.24 | K166: =+L166*2.2/J166 -> 7.5681206 | L166: =+VLOOKUP(E166,Material!$H$2:$M$17,6,FALSE)*G166*H166*(1+Material!$K$14) -> 97.147148 | M166: =+Analisis!$J$5 -> T5.0 | N166: =+VLOOKUP(M166,Material!$A$3:$B$58,2,FALSE) -> 5000 | O166: ACERO A36 | P166: Cal 12 | Q166: =+IF(O166="ACERO A36",VLOOKUP(P166,'Velocidades Std 1500 w'!$B$2:$F$15,5,FALSE),IF(O166="INOXIDABLE",VLOOKUP(P166,'Velocidades Std 1500 w'!$B$17:$F$28,5,FALSE),IF(O166="ALUMINIO",VLOOKUP(P166,'Velocidades Std 1500 w'!$B$30:$F$38,5,FALSE)))) -> 4.3859649e-06 | R166: =+Q166*N166 -> 0.021929825 | S166: =+Q166*T166*3600 -> 86.545554 | T166: =(+H166*2+G166*2+V166*1.5)*25.4*1.05 -> 5481.2184 | U166: =+T166*R166 -> 120.20216 | V166: 100 | W166: =+IF(O166="ACERO A36",VLOOKUP(P166,'Tiempo Objeto'!$B$2:$C$12,2,FALSE),IF(O166="INOXIDABLE",VLOOKUP(P166,'Tiempo Objeto'!$B$14:$C$22,2,FALSE),IF(O166="ALUMINIO",VLOOKUP(P166,'Tiempo Objeto'!$B$24:$C$32,2,FALSE)))) -> 1.84 | X166: =+W166*V166 -> 184 | Y166: =+X166*N166/3600 -> 255.55556 | Z166: 2 | AA166: =30*Z166+Z166*$C166*1.5 -> 60 | AB166: =+Z166*Analisis!$J$6 -> 50 | AC166: 0 | AD166: =30*AC166+AC166*$C166*1.5 -> 0 | AE166: =+AD166*Analisis!$J$7 -> 0 | AF166: =+L166+U166+Y166+AB166+AE166 -> 522.90486 | AG166: =+AF166/(1-Analisis!$E$9) -> 653.63108 | AH166: =+AG166*C166 -> 0
B167: 11-D-6195-01 | C167: =IFERROR(VLOOKUP(B167,'REQ GALV'!A:B,2,0),0) -> 0 | D167: =+AG167 -> 30.503048 | E167: 16ga | F167: DECAPADO | G167: 0.94 | H167: 8 | I167: 0.105 | J167: 28.24 | K167: =+L167*2.2/J167 -> 0.28406929 | L167: =+VLOOKUP(E167,Material!$H$2:$M$17,6,FALSE)*G167*H167*(1+Material!$K$14) -> 3.6464167 | M167: =+Analisis!$J$5 -> T5.0 | N167: =+VLOOKUP(M167,Material!$A$3:$B$58,2,FALSE) -> 5000 | O167: ACERO A36 | P167: Cal 12 | Q167: =+IF(O167="ACERO A36",VLOOKUP(P167,'Velocidades Std 1500 w'!$B$2:$F$15,5,FALSE),IF(O167="INOXIDABLE",VLOOKUP(P167,'Velocidades Std 1500 w'!$B$17:$F$28,5,FALSE),IF(O167="ALUMINIO",VLOOKUP(P167,'Velocidades Std 1500 w'!$B$30:$F$38,5,FALSE)))) -> 4.3859649e-06 | R167: =+Q167*N167 -> 0.021929825 | S167: =+Q167*T167*3600 -> 9.4243358 | T167: =(+H167*2+G167*2+V167*1.5)*25.4*1.05 -> 596.8746 | U167: =+T167*R167 -> 13.089355 | V167: 3 | W167: =+IF(O167="ACERO A36",VLOOKUP(P167,'Tiempo Objeto'!$B$2:$C$12,2,FALSE),IF(O167="INOXIDABLE",VLOOKUP(P167,'Tiempo Objeto'!$B$14:$C$22,2,FALSE),IF(O167="ALUMINIO",VLOOKUP(P167,'Tiempo Objeto'!$B$24:$C$32,2,FALSE)))) -> 1.84 | X167: =+W167*V167 -> 5.52 | Y167: =+X167*N167/3600 -> 7.6666667 | Z167: 0 | AA167: =30*Z167+Z167*$C167*1.5 -> 0 | AB167: =+Z167*Analisis!$J$6 -> 0 | AC167: 0 | AD167: =30*AC167+AC167*$C167*1.5 -> 0 | AE167: =+AD167*Analisis!$J$7 -> 0 | AF167: =+L167+U167+Y167+AB167+AE167 -> 24.402439 | AG167: =+AF167/(1-Analisis!$E$9) -> 30.503048 | AH167: =+AG167*C167 -> 0
B168: 11-D-6195-02 | C168: =IFERROR(VLOOKUP(B168,'REQ GALV'!A:B,2,0),0) -> 0 | D168: =+AG168 -> 38.630743 | E168: 16ga | F168: DECAPADO | G168: 0.94 | H168: 12 | I168: 0.105 | J168: 28.24 | K168: =+L168*2.2/J168 -> 0.42610393 | L168: =+VLOOKUP(E168,Material!$H$2:$M$17,6,FALSE)*G168*H168*(1+Material!$K$14) -> 5.469625 | M168: =+Analisis!$J$5 -> T5.0 | N168: =+VLOOKUP(M168,Material!$A$3:$B$58,2,FALSE) -> 5000 | O168: ACERO A36 | P168: Cal 12 | Q168: =+IF(O168="ACERO A36",VLOOKUP(P168,'Velocidades Std 1500 w'!$B$2:$F$15,5,FALSE),IF(O168="INOXIDABLE",VLOOKUP(P168,'Velocidades Std 1500 w'!$B$17:$F$28,5,FALSE),IF(O168="ALUMINIO",VLOOKUP(P168,'Velocidades Std 1500 w'!$B$30:$F$38,5,FALSE)))) -> 4.3859649e-06 | R168: =+Q168*N168 -> 0.021929825 | S168: =+Q168*T168*3600 -> 12.793178 | T168: =(+H168*2+G168*2+V168*1.5)*25.4*1.05 -> 810.2346 | U168: =+T168*R168 -> 17.768303 | V168: 3 | W168: =+IF(O168="ACERO A36",VLOOKUP(P168,'Tiempo Objeto'!$B$2:$C$12,2,FALSE),IF(O168="INOXIDABLE",VLOOKUP(P168,'Tiempo Objeto'!$B$14:$C$22,2,FALSE),IF(O168="ALUMINIO",VLOOKUP(P168,'Tiempo Objeto'!$B$24:$C$32,2,FALSE)))) -> 1.84 | X168: =+W168*V168 -> 5.52 | Y168: =+X168*N168/3600 -> 7.6666667 | Z168: 0 | AA168: =30*Z168+Z168*$C168*1.5 -> 0 | AB168: =+Z168*Analisis!$J$6 -> 0 | AC168: 0 | AD168: =30*AC168+AC168*$C168*1.5 -> 0 | AE168: =+AD168*Analisis!$J$7 -> 0 | AF168: =+L168+U168+Y168+AB168+AE168 -> 30.904594 | AG168: =+AF168/(1-Analisis!$E$9) -> 38.630743 | AH168: =+AG168*C168 -> 0
B169: 11-D-6195-03 | C169: =IFERROR(VLOOKUP(B169,'REQ GALV'!A:B,2,0),0) -> 450 | D169: =+AG169 -> 46.758437 | E169: 16ga | F169: DECAPADO | G169: 0.94 | H169: 16 | I169: 0.105 | J169: 28.24 | K169: =+L169*2.2/J169 -> 0.56813857 | L169: =+VLOOKUP(E169,Material!$H$2:$M$17,6,FALSE)*G169*H169*(1+Material!$K$14) -> 7.2928333 | M169: =+Analisis!$J$5 -> T5.0 | N169: =+VLOOKUP(M169,Material!$A$3:$B$58,2,FALSE) -> 5000 | O169: ACERO A36 | P169: Cal 12 | Q169: =+IF(O169="ACERO A36",VLOOKUP(P169,'Velocidades Std 1500 w'!$B$2:$F$15,5,FALSE),IF(O169="INOXIDABLE",VLOOKUP(P169,'Velocidades Std 1500 w'!$B$17:$F$28,5,FALSE),IF(O169="ALUMINIO",VLOOKUP(P169,'Velocidades Std 1500 w'!$B$30:$F$38,5,FALSE)))) -> 4.3859649e-06 | R169: =+Q169*N169 -> 0.021929825 | S169: =+Q169*T169*3600 -> 16.16202 | T169: =(+H169*2+G169*2+V169*1.5)*25.4*1.05 -> 1023.5946 | U169: =+T169*R169 -> 22.44725 | V169: 3 | W169: =+IF(O169="ACERO A36",VLOOKUP(P169,'Tiempo Objeto'!$B$2:$C$12,2,FALSE),IF(O169="INOXIDABLE",VLOOKUP(P169,'Tiempo Objeto'!$B$14:$C$22,2,FALSE),IF(O169="ALUMINIO",VLOOKUP(P169,'Tiempo Objeto'!$B$24:$C$32,2,FALSE)))) -> 1.84 | X169: =+W169*V169 -> 5.52 | Y169: =+X169*N169/3600 -> 7.6666667 | Z169: 0 | AA169: =30*Z169+Z169*$C169*1.5 -> 0 | AB169: =+Z169*Analisis!$J$6 -> 0 | AC169: 0 | AD169: =30*AC169+AC169*$C169*1.5 -> 0 | AE169: =+AD169*Analisis!$J$7 -> 0 | AF169: =+L169+U169+Y169+AB169+AE169 -> 37.40675 | AG169: =+AF169/(1-Analisis!$E$9) -> 46.758437 | AH169: =+AG169*C169 -> 21041.297 | AI169: =+L169*C169 -> 3281.775
B170: 11-D-6195-04 | C170: =IFERROR(VLOOKUP(B170,'REQ GALV'!A:B,2,0),0) -> 0 | D170: =+AG170 -> 67.077674 | E170: 16ga | F170: DECAPADO | G170: 0.94 | H170: 26 | I170: 0.105 | J170: 28.24 | K170: =+L170*2.2/J170 -> 0.92322518 | L170: =+VLOOKUP(E170,Material!$H$2:$M$17,6,FALSE)*G170*H170*(1+Material!$K$14) -> 11.850854 | M170: =+Analisis!$J$5 -> T5.0 | N170: =+VLOOKUP(M170,Material!$A$3:$B$58,2,FALSE) -> 5000 | O170: ACERO A36 | P170: Cal 12 | Q170: =+IF(O170="ACERO A36",VLOOKUP(P170,'Velocidades Std 1500 w'!$B$2:$F$15,5,FALSE),IF(O170="INOXIDABLE",VLOOKUP(P170,'Velocidades Std 1500 w'!$B$17:$F$28,5,FALSE),IF(O170="ALUMINIO",VLOOKUP(P170,'Velocidades Std 1500 w'!$B$30:$F$38,5,FALSE)))) -> 4.3859649e-06 | R170: =+Q170*N170 -> 0.021929825 | S170: =+Q170*T170*3600 -> 24.584125 | T170: =(+H170*2+G170*2+V170*1.5)*25.4*1.05 -> 1556.9946 | U170: =+T170*R170 -> 34.144618 | V170: 3 | W170: =+IF(O170="ACERO A36",VLOOKUP(P170,'Tiempo Objeto'!$B$2:$C$12,2,FALSE),IF(O170="INOXIDABLE",VLOOKUP(P170,'Tiempo Objeto'!$B$14:$C$22,2,FALSE),IF(O170="ALUMINIO",VLOOKUP(P170,'Tiempo Objeto'!$B$24:$C$32,2,FALSE)))) -> 1.84 | X170: =+W170*V170 -> 5.52 | Y170: =+X170*N170/3600 -> 7.6666667 | Z170: 0 | AA170: =30*Z170+Z170*$C170*1.5 -> 0 | AB170: =+Z170*Analisis!$J$6 -> 0 | AC170: 0 | AD170: =30*AC170+AC170*$C170*1.5 -> 0 | AE170: =+AD170*Analisis!$J$7 -> 0 | AF170: =+L170+U170+Y170+AB170+AE170 -> 53.662139 | AG170: =+AF170/(1-Analisis!$E$9) -> 67.077674 | AH170: =+AG170*C170 -> 0
B171: 11-D-6195-05 | C171: =IFERROR(VLOOKUP(B171,'REQ GALV'!A:B,2,0),0) -> 0 | D171: =+AG171 -> 75.205369 | E171: 16ga | F171: DECAPADO | G171: 0.94 | H171: 30 | I171: 0.105 | J171: 28.24 | K171: =+L171*2.2/J171 -> 1.0652598 | L171: =+VLOOKUP(E171,Material!$H$2:$M$17,6,FALSE)*G171*H171*(1+Material!$K$14) -> 13.674062 | M171: =+Analisis!$J$5 -> T5.0 | N171: =+VLOOKUP(M171,Material!$A$3:$B$58,2,FALSE) -> 5000 | O171: ACERO A36 | P171: Cal 12 | Q171: =+IF(O171="ACERO A36",VLOOKUP(P171,'Velocidades Std 1500 w'!$B$2:$F$15,5,FALSE),IF(O171="INOXIDABLE",VLOOKUP(P171,'Velocidades Std 1500 w'!$B$17:$F$28,5,FALSE),IF(O171="ALUMINIO",VLOOKUP(P171,'Velocidades Std 1500 w'!$B$30:$F$38,5,FALSE)))) -> 4.3859649e-06 | R171: =+Q171*N171 -> 0.021929825 | S171: =+Q171*T171*3600 -> 27.952967 | T171: =(+H171*2+G171*2+V171*1.5)*25.4*1.05 -> 1770.3546 | U171: =+T171*R171 -> 38.823566 | V171: 3 | W171: =+IF(O171="ACERO A36",VLOOKUP(P171,'Tiempo Objeto'!$B$2:$C$12,2,FALSE),IF(O171="INOXIDABLE",VLOOKUP(P171,'Tiempo Objeto'!$B$14:$C$22,2,FALSE),IF(O171="ALUMINIO",VLOOKUP(P171,'Tiempo Objeto'!$B$24:$C$32,2,FALSE)))) -> 1.84 | X171: =+W171*V171 -> 5.52 | Y171: =+X171*N171/3600 -> 7.6666667 | Z171: 0 | AA171: =30*Z171+Z171*$C171*1.5 -> 0 | AB171: =+Z171*Analisis!$J$6 -> 0 | AC171: 0 | AD171: =30*AC171+AC171*$C171*1.5 -> 0 | AE171: =+AD171*Analisis!$J$7 -> 0 | AF171: =+L171+U171+Y171+AB171+AE171 -> 60.164295 | AG171: =+AF171/(1-Analisis!$E$9) -> 75.205369 | AH171: =+AG171*C171 -> 0
B172: 11-D-6195-06 | C172: =IFERROR(VLOOKUP(B172,'REQ GALV'!A:B,2,0),0) -> 0 | D172: =+AG172 -> 87.396911 | E172: 16ga | F172: DECAPADO | G172: 0.94 | H172: 36 | I172: 0.105 | J172: 28.24 | K172: =+L172*2.2/J172 -> 1.2783118 | L172: =+VLOOKUP(E172,Material!$H$2:$M$17,6,FALSE)*G172*H172*(1+Material!$K$14) -> 16.408875 | M172: =+Analisis!$J$5 -> T5.0 | N172: =+VLOOKUP(M172,Material!$A$3:$B$58,2,FALSE) -> 5000 | O172: ACERO A36 | P172: Cal 12 | Q172: =+IF(O172="ACERO A36",VLOOKUP(P172,'Velocidades Std 1500 w'!$B$2:$F$15,5,FALSE),IF(O172="INOXIDABLE",VLOOKUP(P172,'Velocidades Std 1500 w'!$B$17:$F$28,5,FALSE),IF(O172="ALUMINIO",VLOOKUP(P172,'Velocidades Std 1500 w'!$B$30:$F$38,5,FALSE)))) -> 4.3859649e-06 | R172: =+Q172*N172 -> 0.021929825 | S172: =+Q172*T172*3600 -> 33.006231 | T172: =(+H172*2+G172*2+V172*1.5)*25.4*1.05 -> 2090.3946 | U172: =+T172*R172 -> 45.841987 | V172: 3 | W172: =+IF(O172="ACERO A36",VLOOKUP(P172,'Tiempo Objeto'!$B$2:$C$12,2,FALSE),IF(O172="INOXIDABLE",VLOOKUP(P172,'Tiempo Objeto'!$B$14:$C$22,2,FALSE),IF(O172="ALUMINIO",VLOOKUP(P172,'Tiempo Objeto'!$B$24:$C$32,2,FALSE)))) -> 1.84 | X172: =+W172*V172 -> 5.52 | Y172: =+X172*N172/3600 -> 7.6666667 | Z172: 0 | AA172: =30*Z172+Z172*$C172*1.5 -> 0 | AB172: =+Z172*Analisis!$J$6 -> 0 | AC172: 0 | AD172: =30*AC172+AC172*$C172*1.5 -> 0 | AE172: =+AD172*Analisis!$J$7 -> 0 | AF172: =+L172+U172+Y172+AB172+AE172 -> 69.917529 | AG172: =+AF172/(1-Analisis!$E$9) -> 87.396911 | AH172: =+AG172*C172 -> 0
B173: 11-D-6195-07 | C173: =IFERROR(VLOOKUP(B173,'REQ GALV'!A:B,2,0),0) -> 0 | D173: =+AG173 -> 91.460758 | E173: 16ga | F173: DECAPADO | G173: 0.94 | H173: 38 | I173: 0.105 | J173: 28.24 | K173: =+L173*2.2/J173 -> 1.3493291 | L173: =+VLOOKUP(E173,Material!$H$2:$M$17,6,FALSE)*G173*H173*(1+Material!$K$14) -> 17.320479 | M173: =+Analisis!$J$5 -> T5.0 | N173: =+VLOOKUP(M173,Material!$A$3:$B$58,2,FALSE) -> 5000 | O173: ACERO A36 | P173: Cal 12 | Q173: =+IF(O173="ACERO A36",VLOOKUP(P173,'Velocidades Std 1500 w'!$B$2:$F$15,5,FALSE),IF(O173="INOXIDABLE",VLOOKUP(P173,'Velocidades Std 1500 w'!$B$17:$F$28,5,FALSE),IF(O173="ALUMINIO",VLOOKUP(P173,'Velocidades Std 1500 w'!$B$30:$F$38,5,FALSE)))) -> 4.3859649e-06 | R173: =+Q173*N173 -> 0.021929825 | S173: =+Q173*T173*3600 -> 34.690652 | T173: =(+H173*2+G173*2+V173*1.5)*25.4*1.05 -> 2197.0746 | U173: =+T173*R173 -> 48.181461 | V173: 3 | W173: =+IF(O173="ACERO A36",VLOOKUP(P173,'Tiempo Objeto'!$B$2:$C$12,2,FALSE),IF(O173="INOXIDABLE",VLOOKUP(P173,'Tiempo Objeto'!$B$14:$C$22,2,FALSE),IF(O173="ALUMINIO",VLOOKUP(P173,'Tiempo Objeto'!$B$24:$C$32,2,FALSE)))) -> 1.84 | X173: =+W173*V173 -> 5.52 | Y173: =+X173*N173/3600 -> 7.6666667 | Z173: 0 | AA173: =30*Z173+Z173*$C173*1.5 -> 0 | AB173: =+Z173*Analisis!$J$6 -> 0 | AC173: 0 | AD173: =30*AC173+AC173*$C173*1.5 -> 0 | AE173: =+AD173*Analisis!$J$7 -> 0 | AF173: =+L173+U173+Y173+AB173+AE173 -> 73.168606 | AG173: =+AF173/(1-Analisis!$E$9) -> 91.460758 | AH173: =+AG173*C173 -> 0
B174: 11-D-6195-08 | C174: =IFERROR(VLOOKUP(B174,'REQ GALV'!A:B,2,0),0) -> 0 | D174: =+AG174 -> 99.588453 | E174: 16ga | F174: DECAPADO | G174: 0.94 | H174: 42 | I174: 0.105 | J174: 28.24 | K174: =+L174*2.2/J174 -> 1.4913638 | L174: =+VLOOKUP(E174,Material!$H$2:$M$17,6,FALSE)*G174*H174*(1+Material!$K$14) -> 19.143687 | M174: =+Analisis!$J$5 -> T5.0 | N174: =+VLOOKUP(M174,Material!$A$3:$B$58,2,FALSE) -> 5000 | O174: ACERO A36 | P174: Cal 12 | Q174: =+IF(O174="ACERO A36",VLOOKUP(P174,'Velocidades Std 1500 w'!$B$2:$F$15,5,FALSE),IF(O174="INOXIDABLE",VLOOKUP(P174,'Velocidades Std 1500 w'!$B$17:$F$28,5,FALSE),IF(O174="ALUMINIO",VLOOKUP(P174,'Velocidades Std 1500 w'!$B$30:$F$38,5,FALSE)))) -> 4.3859649e-06 | R174: =+Q174*N174 -> 0.021929825 | S174: =+Q174*T174*3600 -> 38.059494 | T174: =(+H174*2+G174*2+V174*1.5)*25.4*1.05 -> 2410.4346 | U174: =+T174*R174 -> 52.860408 | V174: 3 | W174: =+IF(O174="ACERO A36",VLOOKUP(P174,'Tiempo Objeto'!$B$2:$C$12,2,FALSE),IF(O174="INOXIDABLE",VLOOKUP(P174,'Tiempo Objeto'!$B$14:$C$22,2,FALSE),IF(O174="ALUMINIO",VLOOKUP(P174,'Tiempo Objeto'!$B$24:$C$32,2,FALSE)))) -> 1.84 | X174: =+W174*V174 -> 5.52 | Y174: =+X174*N174/3600 -> 7.6666667 | Z174: 0 | AA174: =30*Z174+Z174*$C174*1.5 -> 0 | AB174: =+Z174*Analisis!$J$6 -> 0 | AC174: 0 | AD174: =30*AC174+AC174*$C174*1.5 -> 0 | AE174: =+AD174*Analisis!$J$7 -> 0 | AF174: =+L174+U174+Y174+AB174+AE174 -> 79.670762 | AG174: =+AF174/(1-Analisis!$E$9) -> 99.588453 | AH174: =+AG174*C174 -> 0
B175: 11-D-6195-09 | C175: =IFERROR(VLOOKUP(B175,'REQ GALV'!A:B,2,0),0) -> 0 | D175: =+AG175 -> 107.71615 | E175: 16ga | F175: DECAPADO | G175: 0.94 | H175: 46 | I175: 0.105 | J175: 28.24 | K175: =+L175*2.2/J175 -> 1.6333984 | L175: =+VLOOKUP(E175,Material!$H$2:$M$17,6,FALSE)*G175*H175*(1+Material!$K$14) -> 20.966896 | M175: =+Analisis!$J$5 -> T5.0 | N175: =+VLOOKUP(M175,Material!$A$3:$B$58,2,FALSE) -> 5000 | O175: ACERO A36 | P175: Cal 12 | Q175: =+IF(O175="ACERO A36",VLOOKUP(P175,'Velocidades Std 1500 w'!$B$2:$F$15,5,FALSE),IF(O175="INOXIDABLE",VLOOKUP(P175,'Velocidades Std 1500 w'!$B$17:$F$28,5,FALSE),IF(O175="ALUMINIO",VLOOKUP(P175,'Velocidades Std 1500 w'!$B$30:$F$38,5,FALSE)))) -> 4.3859649e-06 | R175: =+Q175*N175 -> 0.021929825 | S175: =+Q175*T175*3600 -> 41.428336 | T175: =(+H175*2+G175*2+V175*1.5)*25.4*1.05 -> 2623.7946 | U175: =+T175*R175 -> 57.539355 | V175: 3 | W175: =+IF(O175="ACERO A36",VLOOKUP(P175,'Tiempo Objeto'!$B$2:$C$12,2,FALSE),IF(O175="INOXIDABLE",VLOOKUP(P175,'Tiempo Objeto'!$B$14:$C$22,2,FALSE),IF(O175="ALUMINIO",VLOOKUP(P175,'Tiempo Objeto'!$B$24:$C$32,2,FALSE)))) -> 1.84 | X175: =+W175*V175 -> 5.52 | Y175: =+X175*N175/3600 -> 7.6666667 | Z175: 0 | AA175: =30*Z175+Z175*$C175*1.5 -> 0 | AB175: =+Z175*Analisis!$J$6 -> 0 | AC175: 0 | AD175: =30*AC175+AC175*$C175*1.5 -> 0 | AE175: =+AD175*Analisis!$J$7 -> 0 | AF175: =+L175+U175+Y175+AB175+AE175 -> 86.172918 | AG175: =+AF175/(1-Analisis!$E$9) -> 107.71615 | AH175: =+AG175*C175 -> 0
B176: 11-D-7627-01 | C176: =IFERROR(VLOOKUP(B176,'REQ GALV'!A:B,2,0),0) -> 0 | D176: =+AG176 -> 819.1658 | E176: 10ga | F176: DECAPADO | G176: 10.7 | H176: 30 | I176: 0.105 | J176: 28.24 | K176: =+L176*2.2/J176 -> 22.519398 | L176: =+VLOOKUP(E176,Material!$H$2:$M$17,6,FALSE)*G176*H176*(1+Material!$K$14) -> 289.06719 | M176: =+Analisis!$J$5 -> T5.0 | N176: =+VLOOKUP(M176,Material!$A$3:$B$58,2,FALSE) -> 5000 | O176: ACERO A36 | P176: Cal 12 | Q176: =+IF(O176="ACERO A36",VLOOKUP(P176,'Velocidades Std 1500 w'!$B$2:$F$15,5,FALSE),IF(O176="INOXIDABLE",VLOOKUP(P176,'Velocidades Std 1500 w'!$B$17:$F$28,5,FALSE),IF(O176="ALUMINIO",VLOOKUP(P176,'Velocidades Std 1500 w'!$B$30:$F$38,5,FALSE)))) -> 4.3859649e-06 | R176: =+Q176*N176 -> 0.021929825 | S176: =+Q176*T176*3600 -> 46.911126 | T176: =(+H176*2+G176*2+V176*1.5)*25.4*1.05 -> 2971.038 | U176: =+T176*R176 -> 65.154342 | V176: 20 | W176: =+IF(O176="ACERO A36",VLOOKUP(P176,'Tiempo Objeto'!$B$2:$C$12,2,FALSE),IF(O176="INOXIDABLE",VLOOKUP(P176,'Tiempo Objeto'!$B$14:$C$22,2,FALSE),IF(O176="ALUMINIO",VLOOKUP(P176,'Tiempo Objeto'!$B$24:$C$32,2,FALSE)))) -> 1.84 | X176: =+W176*V176 -> 36.8 | Y176: =+X176*N176/3600 -> 51.111111 | Z176: 10 | AA176: =30*Z176+Z176*$C176*1.5 -> 300 | AB176: =+Z176*Analisis!$J$6 -> 250 | AC176: 0 | AD176: =30*AC176+AC176*$C176*1.5 -> 0 | AE176: =+AD176*Analisis!$J$7 -> 0 | AF176: =+L176+U176+Y176+AB176+AE176 -> 655.33264 | AG176: =+AF176/(1-Analisis!$E$9) -> 819.1658 | AH176: =+AG176*C176 -> 0
B177: 11-D-7627-02 | C177: =IFERROR(VLOOKUP(B177,'REQ GALV'!A:B,2,0),0) -> 30 | D177: =+AG177 -> 900.20562 | E177: 10ga | F177: DECAPADO | G177: 10.7 | H177: 36 | I177: 0.105 | J177: 28.24 | K177: =+L177*2.2/J177 -> 27.023278 | L177: =+VLOOKUP(E177,Material!$H$2:$M$17,6,FALSE)*G177*H177*(1+Material!$K$14) -> 346.88063 | M177: =+Analisis!$J$5 -> T5.0 | N177: =+VLOOKUP(M177,Material!$A$3:$B$58,2,FALSE) -> 5000 | O177: ACERO A36 | P177: Cal 12 | Q177: =+IF(O177="ACERO A36",VLOOKUP(P177,'Velocidades Std 1500 w'!$B$2:$F$15,5,FALSE),IF(O177="INOXIDABLE",VLOOKUP(P177,'Velocidades Std 1500 w'!$B$17:$F$28,5,FALSE),IF(O177="ALUMINIO",VLOOKUP(P177,'Velocidades Std 1500 w'!$B$30:$F$38,5,FALSE)))) -> 4.3859649e-06 | R177: =+Q177*N177 -> 0.021929825 | S177: =+Q177*T177*3600 -> 51.964389 | T177: =(+H177*2+G177*2+V177*1.5)*25.4*1.05 -> 3291.078 | U177: =+T177*R177 -> 72.172763 | V177: 20 | W177: =+IF(O177="ACERO A36",VLOOKUP(P177,'Tiempo Objeto'!$B$2:$C$12,2,FALSE),IF(O177="INOXIDABLE",VLOOKUP(P177,'Tiempo Objeto'!$B$14:$C$22,2,FALSE),IF(O177="ALUMINIO",VLOOKUP(P177,'Tiempo Objeto'!$B$24:$C$32,2,FALSE)))) -> 1.84 | X177: =+W177*V177 -> 36.8 | Y177: =+X177*N177/3600 -> 51.111111 | Z177: 10 | AA177: =30*Z177+Z177*$C177*1.5 -> 750 | AB177: =+Z177*Analisis!$J$6 -> 250 | AC177: 0 | AD177: =30*AC177+AC177*$C177*1.5 -> 0 | AE177: =+AD177*Analisis!$J$7 -> 0 | AF177: =+L177+U177+Y177+AB177+AE177 -> 720.1645 | AG177: =+AF177/(1-Analisis!$E$9) -> 900.20562 | AH177: =+AG177*C177 -> 27006.169 | AI177: =+L177*C177 -> 10406.419
B178: 11-D-7627-03 | C178: =IFERROR(VLOOKUP(B178,'REQ GALV'!A:B,2,0),0) -> 0 | D178: =+AG178 -> 900.20562 | E178: 10ga | F178: DECAPADO | G178: 10.7 | H178: 36 | I178: 0.105 | J178: 28.24 | K178: =+L178*2.2/J178 -> 27.023278 | L178: =+VLOOKUP(E178,Material!$H$2:$M$17,6,FALSE)*G178*H178*(1+Material!$K$14) -> 346.88063 | M178: =+Analisis!$J$5 -> T5.0 | N178: =+VLOOKUP(M178,Material!$A$3:$B$58,2,FALSE) -> 5000 | O178: ACERO A36 | P178: Cal 12 | Q178: =+IF(O178="ACERO A36",VLOOKUP(P178,'Velocidades Std 1500 w'!$B$2:$F$15,5,FALSE),IF(O178="INOXIDABLE",VLOOKUP(P178,'Velocidades Std 1500 w'!$B$17:$F$28,5,FALSE),IF(O178="ALUMINIO",VLOOKUP(P178,'Velocidades Std 1500 w'!$B$30:$F$38,5,FALSE)))) -> 4.3859649e-06 | R178: =+Q178*N178 -> 0.021929825 | S178: =+Q178*T178*3600 -> 51.964389 | T178: =(+H178*2+G178*2+V178*1.5)*25.4*1.05 -> 3291.078 | U178: =+T178*R178 -> 72.172763 | V178: 20 | W178: =+IF(O178="ACERO A36",VLOOKUP(P178,'Tiempo Objeto'!$B$2:$C$12,2,FALSE),IF(O178="INOXIDABLE",VLOOKUP(P178,'Tiempo Objeto'!$B$14:$C$22,2,FALSE),IF(O178="ALUMINIO",VLOOKUP(P178,'Tiempo Objeto'!$B$24:$C$32,2,FALSE)))) -> 1.84 | X178: =+W178*V178 -> 36.8 | Y178: =+X178*N178/3600 -> 51.111111 | Z178: 10 | AA178: =30*Z178+Z178*$C178*1.5 -> 300 | AB178: =+Z178*Analisis!$J$6 -> 250 | AC178: 0 | AD178: =30*AC178+AC178*$C178*1.5 -> 0 | AE178: =+AD178*Analisis!$J$7 -> 0 | AF178: =+L178+U178+Y178+AB178+AE178 -> 720.1645 | AG178: =+AF178/(1-Analisis!$E$9) -> 900.20562 | AH178: =+AG178*C178 -> 0
B179: 11-D-7627-04 | C179: =IFERROR(VLOOKUP(B179,'REQ GALV'!A:B,2,0),0) -> 0 | D179: =+AG179 -> 927.2189 | E179: 10ga | F179: DECAPADO | G179: 10.7 | H179: 38 | I179: 0.105 | J179: 28.24 | K179: =+L179*2.2/J179 -> 28.524571 | L179: =+VLOOKUP(E179,Material!$H$2:$M$17,6,FALSE)*G179*H179*(1+Material!$K$14) -> 366.15177 | M179: =+Analisis!$J$5 -> T5.0 | N179: =+VLOOKUP(M179,Material!$A$3:$B$58,2,FALSE) -> 5000 | O179: ACERO A36 | P179: Cal 12 | Q179: =+IF(O179="ACERO A36",VLOOKUP(P179,'Velocidades Std 1500 w'!$B$2:$F$15,5,FALSE),IF(O179="INOXIDABLE",VLOOKUP(P179,'Velocidades Std 1500 w'!$B$17:$F$28,5,FALSE),IF(O179="ALUMINIO",VLOOKUP(P179,'Velocidades Std 1500 w'!$B$30:$F$38,5,FALSE)))) -> 4.3859649e-06 | R179: =+Q179*N179 -> 0.021929825 | S179: =+Q179*T179*3600 -> 53.648811 | T179: =(+H179*2+G179*2+V179*1.5)*25.4*1.05 -> 3397.758 | U179: =+T179*R179 -> 74.512237 | V179: 20 | W179: =+IF(O179="ACERO A36",VLOOKUP(P179,'Tiempo Objeto'!$B$2:$C$12,2,FALSE),IF(O179="INOXIDABLE",VLOOKUP(P179,'Tiempo Objeto'!$B$14:$C$22,2,FALSE),IF(O179="ALUMINIO",VLOOKUP(P179,'Tiempo Objeto'!$B$24:$C$32,2,FALSE)))) -> 1.84 | X179: =+W179*V179 -> 36.8 | Y179: =+X179*N179/3600 -> 51.111111 | Z179: 10 | AA179: =30*Z179+Z179*$C179*1.5 -> 300 | AB179: =+Z179*Analisis!$J$6 -> 250 | AC179: 0 | AD179: =30*AC179+AC179*$C179*1.5 -> 0 | AE179: =+AD179*Analisis!$J$7 -> 0 | AF179: =+L179+U179+Y179+AB179+AE179 -> 741.77512 | AG179: =+AF179/(1-Analisis!$E$9) -> 927.2189 | AH179: =+AG179*C179 -> 0
B180: 11-D-7627-05 | C180: =IFERROR(VLOOKUP(B180,'REQ GALV'!A:B,2,0),0) -> 0 | D180: =+AG180 -> 1089.2985 | E180: 10ga | F180: DECAPADO | G180: 10.7 | H180: 50 | I180: 0.105 | J180: 28.24 | K180: =+L180*2.2/J180 -> 37.532331 | L180: =+VLOOKUP(E180,Material!$H$2:$M$17,6,FALSE)*G180*H180*(1+Material!$K$14) -> 481.77865 | M180: =+Analisis!$J$5 -> T5.0 | N180: =+VLOOKUP(M180,Material!$A$3:$B$58,2,FALSE) -> 5000 | O180: ACERO A36 | P180: Cal 12 | Q180: =+IF(O180="ACERO A36",VLOOKUP(P180,'Velocidades Std 1500 w'!$B$2:$F$15,5,FALSE),IF(O180="INOXIDABLE",VLOOKUP(P180,'Velocidades Std 1500 w'!$B$17:$F$28,5,FALSE),IF(O180="ALUMINIO",VLOOKUP(P180,'Velocidades Std 1500 w'!$B$30:$F$38,5,FALSE)))) -> 4.3859649e-06 | R180: =+Q180*N180 -> 0.021929825 | S180: =+Q180*T180*3600 -> 63.755337 | T180: =(+H180*2+G180*2+V180*1.5)*25.4*1.05 -> 4037.838 | U180: =+T180*R180 -> 88.549079 | V180: 20 | W180: =+IF(O180="ACERO A36",VLOOKUP(P180,'Tiempo Objeto'!$B$2:$C$12,2,FALSE),IF(O180="INOXIDABLE",VLOOKUP(P180,'Tiempo Objeto'!$B$14:$C$22,2,FALSE),IF(O180="ALUMINIO",VLOOKUP(P180,'Tiempo Objeto'!$B$24:$C$32,2,FALSE)))) -> 1.84 | X180: =+W180*V180 -> 36.8 | Y180: =+X180*N180/3600 -> 51.111111 | Z180: 10 | AA180: =30*Z180+Z180*$C180*1.5 -> 300 | AB180: =+Z180*Analisis!$J$6 -> 250 | AC180: 0 | AD180: =30*AC180+AC180*$C180*1.5 -> 0 | AE180: =+AD180*Analisis!$J$7 -> 0 | AF180: =+L180+U180+Y180+AB180+AE180 -> 871.43884 | AG180: =+AF180/(1-Analisis!$E$9) -> 1089.2985 | AH180: =+AG180*C180 -> 0
B181: 11-D-7627-06 | C181: =IFERROR(VLOOKUP(B181,'REQ GALV'!A:B,2,0),0) -> 0 | D181: =+AG181 -> 1170.3384 | E181: 10ga | F181: DECAPADO | G181: 10.7 | H181: 56 | I181: 0.105 | J181: 28.24 | K181: =+L181*2.2/J181 -> 42.03621 | L181: =+VLOOKUP(E181,Material!$H$2:$M$17,6,FALSE)*G181*H181*(1+Material!$K$14) -> 539.59208 | M181: =+Analisis!$J$5 -> T5.0 | N181: =+VLOOKUP(M181,Material!$A$3:$B$58,2,FALSE) -> 5000 | O181: ACERO A36 | P181: Cal 12 | Q181: =+IF(O181="ACERO A36",VLOOKUP(P181,'Velocidades Std 1500 w'!$B$2:$F$15,5,FALSE),IF(O181="INOXIDABLE",VLOOKUP(P181,'Velocidades Std 1500 w'!$B$17:$F$28,5,FALSE),IF(O181="ALUMINIO",VLOOKUP(P181,'Velocidades Std 1500 w'!$B$30:$F$38,5,FALSE)))) -> 4.3859649e-06 | R181: =+Q181*N181 -> 0.021929825 | S181: =+Q181*T181*3600 -> 68.8086 | T181: =(+H181*2+G181*2+V181*1.5)*25.4*1.05 -> 4357.878 | U181: =+T181*R181 -> 95.5675 | V181: 20 | W181: =+IF(O181="ACERO A36",VLOOKUP(P181,'Tiempo Objeto'!$B$2:$C$12,2,FALSE),IF(O181="INOXIDABLE",VLOOKUP(P181,'Tiempo Objeto'!$B$14:$C$22,2,FALSE),IF(O181="ALUMINIO",VLOOKUP(P181,'Tiempo Objeto'!$B$24:$C$32,2,FALSE)))) -> 1.84 | X181: =+W181*V181 -> 36.8 | Y181: =+X181*N181/3600 -> 51.111111 | Z181: 10 | AA181: =30*Z181+Z181*$C181*1.5 -> 300 | AB181: =+Z181*Analisis!$J$6 -> 250 | AC181: 0 | AD181: =30*AC181+AC181*$C181*1.5 -> 0 | AE181: =+AD181*Analisis!$J$7 -> 0 | AF181: =+L181+U181+Y181+AB181+AE181 -> 936.27069 | AG181: =+AF181/(1-Analisis!$E$9) -> 1170.3384 | AH181: =+AG181*C181 -> 0
B182: 11-D-7627-07 | C182: =IFERROR(VLOOKUP(B182,'REQ GALV'!A:B,2,0),0) -> 0 | D182: =+AG182 -> 900.20562 | E182: 10ga | F182: DECAPADO | G182: 10.7 | H182: 36 | I182: 0.105 | J182: 28.24 | K182: =+L182*2.2/J182 -> 27.023278 | L182: =+VLOOKUP(E182,Material!$H$2:$M$17,6,FALSE)*G182*H182*(1+Material!$K$14) -> 346.88063 | M182: =+Analisis!$J$5 -> T5.0 | N182: =+VLOOKUP(M182,Material!$A$3:$B$58,2,FALSE) -> 5000 | O182: ACERO A36 | P182: Cal 12 | Q182: =+IF(O182="ACERO A36",VLOOKUP(P182,'Velocidades Std 1500 w'!$B$2:$F$15,5,FALSE),IF(O182="INOXIDABLE",VLOOKUP(P182,'Velocidades Std 1500 w'!$B$17:$F$28,5,FALSE),IF(O182="ALUMINIO",VLOOKUP(P182,'Velocidades Std 1500 w'!$B$30:$F$38,5,FALSE)))) -> 4.3859649e-06 | R182: =+Q182*N182 -> 0.021929825 | S182: =+Q182*T182*3600 -> 51.964389 | T182: =(+H182*2+G182*2+V182*1.5)*25.4*1.05 -> 3291.078 | U182: =+T182*R182 -> 72.172763 | V182: 20 | W182: =+IF(O182="ACERO A36",VLOOKUP(P182,'Tiempo Objeto'!$B$2:$C$12,2,FALSE),IF(O182="INOXIDABLE",VLOOKUP(P182,'Tiempo Objeto'!$B$14:$C$22,2,FALSE),IF(O182="ALUMINIO",VLOOKUP(P182,'Tiempo Objeto'!$B$24:$C$32,2,FALSE)))) -> 1.84 | X182: =+W182*V182 -> 36.8 | Y182: =+X182*N182/3600 -> 51.111111 | Z182: 10 | AA182: =30*Z182+Z182*$C182*1.5 -> 300 | AB182: =+Z182*Analisis!$J$6 -> 250 | AC182: 0 | AD182: =30*AC182+AC182*$C182*1.5 -> 0 | AE182: =+AD182*Analisis!$J$7 -> 0 | AF182: =+L182+U182+Y182+AB182+AE182 -> 720.1645 | AG182: =+AF182/(1-Analisis!$E$9) -> 900.20562 | AH182: =+AG182*C182 -> 0
B183: 11-D-7627-08 | C183: =IFERROR(VLOOKUP(B183,'REQ GALV'!A:B,2,0),0) -> 0 | D183: =+AG183 -> 900.20562 | E183: 10ga | F183: DECAPADO | G183: 10.7 | H183: 36 | I183: 0.105 | J183: 28.24 | K183: =+L183*2.2/J183 -> 27.023278 | L183: =+VLOOKUP(E183,Material!$H$2:$M$17,6,FALSE)*G183*H183*(1+Material!$K$14) -> 346.88063 | M183: =+Analisis!$J$5 -> T5.0 | N183: =+VLOOKUP(M183,Material!$A$3:$B$58,2,FALSE) -> 5000 | O183: ACERO A36 | P183: Cal 12 | Q183: =+IF(O183="ACERO A36",VLOOKUP(P183,'Velocidades Std 1500 w'!$B$2:$F$15,5,FALSE),IF(O183="INOXIDABLE",VLOOKUP(P183,'Velocidades Std 1500 w'!$B$17:$F$28,5,FALSE),IF(O183="ALUMINIO",VLOOKUP(P183,'Velocidades Std 1500 w'!$B$30:$F$38,5,FALSE)))) -> 4.3859649e-06 | R183: =+Q183*N183 -> 0.021929825 | S183: =+Q183*T183*3600 -> 51.964389 | T183: =(+H183*2+G183*2+V183*1.5)*25.4*1.05 -> 3291.078 | U183: =+T183*R183 -> 72.172763 | V183: 20 | W183: =+IF(O183="ACERO A36",VLOOKUP(P183,'Tiempo Objeto'!$B$2:$C$12,2,FALSE),IF(O183="INOXIDABLE",VLOOKUP(P183,'Tiempo Objeto'!$B$14:$C$22,2,FALSE),IF(O183="ALUMINIO",VLOOKUP(P183,'Tiempo Objeto'!$B$24:$C$32,2,FALSE)))) -> 1.84 | X183: =+W183*V183 -> 36.8 | Y183: =+X183*N183/3600 -> 51.111111 | Z183: 10 | AA183: =30*Z183+Z183*$C183*1.5 -> 300 | AB183: =+Z183*Analisis!$J$6 -> 250 | AC183: 0 | AD183: =30*AC183+AC183*$C183*1.5 -> 0 | AE183: =+AD183*Analisis!$J$7 -> 0 | AF183: =+L183+U183+Y183+AB183+AE183 -> 720.1645 | AG183: =+AF183/(1-Analisis!$E$9) -> 900.20562 | AH183: =+AG183*C183 -> 0
B184: 12-A-6007-01 | C184: =IFERROR(VLOOKUP(B184,'REQ GALV'!A:B,2,0),0) -> 0 | D184: =+AG184 -> 218.34732 | E184: 12ga | F184: DECAPADO | G184: 3.14 | H184: 15 | I184: 0.105 | J184: 28.24 | K184: =+L184*2.2/J184 -> 2.711178 | L184: =+VLOOKUP(E184,Material!$H$2:$M$17,6,FALSE)*G184*H184*(1+Material!$K$14) -> 34.801667 | M184: =+Analisis!$J$5 -> T5.0 | N184: =+VLOOKUP(M184,Material!$A$3:$B$58,2,FALSE) -> 5000 | O184: ACERO A36 | P184: Cal 12 | Q184: =+IF(O184="ACERO A36",VLOOKUP(P184,'Velocidades Std 1500 w'!$B$2:$F$15,5,FALSE),IF(O184="INOXIDABLE",VLOOKUP(P184,'Velocidades Std 1500 w'!$B$17:$F$28,5,FALSE),IF(O184="ALUMINIO",VLOOKUP(P184,'Velocidades Std 1500 w'!$B$30:$F$38,5,FALSE)))) -> 4.3859649e-06 | R184: =+Q184*N184 -> 0.021929825 | S184: =+Q184*T184*3600 -> 27.910857 | T184: =(+H184*2+G184*2+V184*1.5)*25.4*1.05 -> 1767.6876 | U184: =+T184*R184 -> 38.765079 | V184: 20 | W184: =+IF(O184="ACERO A36",VLOOKUP(P184,'Tiempo Objeto'!$B$2:$C$12,2,FALSE),IF(O184="INOXIDABLE",VLOOKUP(P184,'Tiempo Objeto'!$B$14:$C$22,2,FALSE),IF(O184="ALUMINIO",VLOOKUP(P184,'Tiempo Objeto'!$B$24:$C$32,2,FALSE)))) -> 1.84 | X184: =+W184*V184 -> 36.8 | Y184: =+X184*N184/3600 -> 51.111111 | Z184: 2 | AA184: =30*Z184+Z184*$C184*1.5 -> 60 | AB184: =+Z184*Analisis!$J$6 -> 50 | AC184: 0 | AD184: =30*AC184+AC184*$C184*1.5 -> 0 | AE184: =+AD184*Analisis!$J$7 -> 0 | AF184: =+L184+U184+Y184+AB184+AE184 -> 174.67786 | AG184: =+AF184/(1-Analisis!$E$9) -> 218.34732 | AH184: =+AG184*C184 -> 0
B185: 12-A-6007-02 | C185: =IFERROR(VLOOKUP(B185,'REQ GALV'!A:B,2,0),0) -> 0 | D185: =+AG185 -> 227.07194 | E185: 12ga | F185: DECAPADO | G185: 3.14 | H185: 17 | I185: 0.105 | J185: 28.24 | K185: =+L185*2.2/J185 -> 3.0726684 | L185: =+VLOOKUP(E185,Material!$H$2:$M$17,6,FALSE)*G185*H185*(1+Material!$K$14) -> 39.441889 | M185: =+Analisis!$J$5 -> T5.0 | N185: =+VLOOKUP(M185,Material!$A$3:$B$58,2,FALSE) -> 5000 | O185: ACERO A36 | P185: Cal 12 | Q185: =+IF(O185="ACERO A36",VLOOKUP(P185,'Velocidades Std 1500 w'!$B$2:$F$15,5,FALSE),IF(O185="INOXIDABLE",VLOOKUP(P185,'Velocidades Std 1500 w'!$B$17:$F$28,5,FALSE),IF(O185="ALUMINIO",VLOOKUP(P185,'Velocidades Std 1500 w'!$B$30:$F$38,5,FALSE)))) -> 4.3859649e-06 | R185: =+Q185*N185 -> 0.021929825 | S185: =+Q185*T185*3600 -> 29.595278 | T185: =(+H185*2+G185*2+V185*1.5)*25.4*1.05 -> 1874.3676 | U185: =+T185*R185 -> 41.104553 | V185: 20 | W185: =+IF(O185="ACERO A36",VLOOKUP(P185,'Tiempo Objeto'!$B$2:$C$12,2,FALSE),IF(O185="INOXIDABLE",VLOOKUP(P185,'Tiempo Objeto'!$B$14:$C$22,2,FALSE),IF(O185="ALUMINIO",VLOOKUP(P185,'Tiempo Objeto'!$B$24:$C$32,2,FALSE)))) -> 1.84 | X185: =+W185*V185 -> 36.8 | Y185: =+X185*N185/3600 -> 51.111111 | Z185: 2 | AA185: =30*Z185+Z185*$C185*1.5 -> 60 | AB185: =+Z185*Analisis!$J$6 -> 50 | AC185: 0 | AD185: =30*AC185+AC185*$C185*1.5 -> 0 | AE185: =+AD185*Analisis!$J$7 -> 0 | AF185: =+L185+U185+Y185+AB185+AE185 -> 181.65755 | AG185: =+AF185/(1-Analisis!$E$9) -> 227.07194 | AH185: =+AG185*C185 -> 0
B186: 12-A-6007-03 | C186: =IFERROR(VLOOKUP(B186,'REQ GALV'!A:B,2,0),0) -> 0 | D186: =+AG186 -> 275.05735 | E186: 12ga | F186: DECAPADO | G186: 3.14 | H186: 28 | I186: 0.105 | J186: 28.24 | K186: =+L186*2.2/J186 -> 5.0608656 | L186: =+VLOOKUP(E186,Material!$H$2:$M$17,6,FALSE)*G186*H186*(1+Material!$K$14) -> 64.963111 | M186: =+Analisis!$J$5 -> T5.0 | N186: =+VLOOKUP(M186,Material!$A$3:$B$58,2,FALSE) -> 5000 | O186: ACERO A36 | P186: Cal 12 | Q186: =+IF(O186="ACERO A36",VLOOKUP(P186,'Velocidades Std 1500 w'!$B$2:$F$15,5,FALSE),IF(O186="INOXIDABLE",VLOOKUP(P186,'Velocidades Std 1500 w'!$B$17:$F$28,5,FALSE),IF(O186="ALUMINIO",VLOOKUP(P186,'Velocidades Std 1500 w'!$B$30:$F$38,5,FALSE)))) -> 4.3859649e-06 | R186: =+Q186*N186 -> 0.021929825 | S186: =+Q186*T186*3600 -> 38.859594 | T186: =(+H186*2+G186*2+V186*1.5)*25.4*1.05 -> 2461.1076 | U186: =+T186*R186 -> 53.971658 | V186: 20 | W186: =+IF(O186="ACERO A36",VLOOKUP(P186,'Tiempo Objeto'!$B$2:$C$12,2,FALSE),IF(O186="INOXIDABLE",VLOOKUP(P186,'Tiempo Objeto'!$B$14:$C$22,2,FALSE),IF(O186="ALUMINIO",VLOOKUP(P186,'Tiempo Objeto'!$B$24:$C$32,2,FALSE)))) -> 1.84 | X186: =+W186*V186 -> 36.8 | Y186: =+X186*N186/3600 -> 51.111111 | Z186: 2 | AA186: =30*Z186+Z186*$C186*1.5 -> 60 | AB186: =+Z186*Analisis!$J$6 -> 50 | AC186: 0 | AD186: =30*AC186+AC186*$C186*1.5 -> 0 | AE186: =+AD186*Analisis!$J$7 -> 0 | AF186: =+L186+U186+Y186+AB186+AE186 -> 220.04588 | AG186: =+AF186/(1-Analisis!$E$9) -> 275.05735 | AH186: =+AG186*C186 -> 0
B187: 12-A-6007-04 | C187: =IFERROR(VLOOKUP(B187,'REQ GALV'!A:B,2,0),0) -> 0 | D187: =+AG187 -> 305.59352 | E187: 12ga | F187: DECAPADO | G187: 3.14 | H187: 35 | I187: 0.105 | J187: 28.24 | K187: =+L187*2.2/J187 -> 6.326082 | L187: =+VLOOKUP(E187,Material!$H$2:$M$17,6,FALSE)*G187*H187*(1+Material!$K$14) -> 81.203889 | M187: =+Analisis!$J$5 -> T5.0 | N187: =+VLOOKUP(M187,Material!$A$3:$B$58,2,FALSE) -> 5000 | O187: ACERO A36 | P187: Cal 12 | Q187: =+IF(O187="ACERO A36",VLOOKUP(P187,'Velocidades Std 1500 w'!$B$2:$F$15,5,FALSE),IF(O187="INOXIDABLE",VLOOKUP(P187,'Velocidades Std 1500 w'!$B$17:$F$28,5,FALSE),IF(O187="ALUMINIO",VLOOKUP(P187,'Velocidades Std 1500 w'!$B$30:$F$38,5,FALSE)))) -> 4.3859649e-06 | R187: =+Q187*N187 -> 0.021929825 | S187: =+Q187*T187*3600 -> 44.755067 | T187: =(+H187*2+G187*2+V187*1.5)*25.4*1.05 -> 2834.4876 | U187: =+T187*R187 -> 62.159816 | V187: 20 | W187: =+IF(O187="ACERO A36",VLOOKUP(P187,'Tiempo Objeto'!$B$2:$C$12,2,FALSE),IF(O187="INOXIDABLE",VLOOKUP(P187,'Tiempo Objeto'!$B$14:$C$22,2,FALSE),IF(O187="ALUMINIO",VLOOKUP(P187,'Tiempo Objeto'!$B$24:$C$32,2,FALSE)))) -> 1.84 | X187: =+W187*V187 -> 36.8 | Y187: =+X187*N187/3600 -> 51.111111 | Z187: 2 | AA187: =30*Z187+Z187*$C187*1.5 -> 60 | AB187: =+Z187*Analisis!$J$6 -> 50 | AC187: 0 | AD187: =30*AC187+AC187*$C187*1.5 -> 0 | AE187: =+AD187*Analisis!$J$7 -> 0 | AF187: =+L187+U187+Y187+AB187+AE187 -> 244.47482 | AG187: =+AF187/(1-Analisis!$E$9) -> 305.59352 | AH187: =+AG187*C187 -> 0
B188: 12-A-6007-05 | C188: =IFERROR(VLOOKUP(B188,'REQ GALV'!A:B,2,0),0) -> 0 | D188: =+AG188 -> 200.89808 | E188: 12ga | F188: DECAPADO | G188: 3.14 | H188: 11 | I188: 0.105 | J188: 28.24 | K188: =+L188*2.2/J188 -> 1.9881972 | L188: =+VLOOKUP(E188,Material!$H$2:$M$17,6,FALSE)*G188*H188*(1+Material!$K$14) -> 25.521222 | M188: =+Analisis!$J$5 -> T5.0 | N188: =+VLOOKUP(M188,Material!$A$3:$B$58,2,FALSE) -> 5000 | O188: ACERO A36 | P188: Cal 12 | Q188: =+IF(O188="ACERO A36",VLOOKUP(P188,'Velocidades Std 1500 w'!$B$2:$F$15,5,FALSE),IF(O188="INOXIDABLE",VLOOKUP(P188,'Velocidades Std 1500 w'!$B$17:$F$28,5,FALSE),IF(O188="ALUMINIO",VLOOKUP(P188,'Velocidades Std 1500 w'!$B$30:$F$38,5,FALSE)))) -> 4.3859649e-06 | R188: =+Q188*N188 -> 0.021929825 | S188: =+Q188*T188*3600 -> 24.542015 | T188: =(+H188*2+G188*2+V188*1.5)*25.4*1.05 -> 1554.3276 | U188: =+T188*R188 -> 34.086132 | V188: 20 | W188: =+IF(O188="ACERO A36",VLOOKUP(P188,'Tiempo Objeto'!$B$2:$C$12,2,FALSE),IF(O188="INOXIDABLE",VLOOKUP(P188,'Tiempo Objeto'!$B$14:$C$22,2,FALSE),IF(O188="ALUMINIO",VLOOKUP(P188,'Tiempo Objeto'!$B$24:$C$32,2,FALSE)))) -> 1.84 | X188: =+W188*V188 -> 36.8 | Y188: =+X188*N188/3600 -> 51.111111 | Z188: 2 | AA188: =30*Z188+Z188*$C188*1.5 -> 60 | AB188: =+Z188*Analisis!$J$6 -> 50 | AC188: 0 | AD188: =30*AC188+AC188*$C188*1.5 -> 0 | AE188: =+AD188*Analisis!$J$7 -> 0 | AF188: =+L188+U188+Y188+AB188+AE188 -> 160.71846 | AG188: =+AF188/(1-Analisis!$E$9) -> 200.89808 | AH188: =+AG188*C188 -> 0
B189: 12-A-6007-06 | C189: =IFERROR(VLOOKUP(B189,'REQ GALV'!A:B,2,0),0) -> 0 | D189: =+AG189 -> 254.85986 | E189: 12ga | F189: DECAPADO | G189: 3.14 | H189: 23.37 | I189: 0.105 | J189: 28.24 | K189: =+L189*2.2/J189 -> 4.2240153 | L189: =+VLOOKUP(E189,Material!$H$2:$M$17,6,FALSE)*G189*H189*(1+Material!$K$14) -> 54.220997 | M189: =+Analisis!$J$5 -> T5.0 | N189: =+VLOOKUP(M189,Material!$A$3:$B$58,2,FALSE) -> 5000 | O189: ACERO A36 | P189: Cal 12 | Q189: =+IF(O189="ACERO A36",VLOOKUP(P189,'Velocidades Std 1500 w'!$B$2:$F$15,5,FALSE),IF(O189="INOXIDABLE",VLOOKUP(P189,'Velocidades Std 1500 w'!$B$17:$F$28,5,FALSE),IF(O189="ALUMINIO",VLOOKUP(P189,'Velocidades Std 1500 w'!$B$30:$F$38,5,FALSE)))) -> 4.3859649e-06 | R189: =+Q189*N189 -> 0.021929825 | S189: =+Q189*T189*3600 -> 34.960159 | T189: =(+H189*2+G189*2+V189*1.5)*25.4*1.05 -> 2214.1434 | U189: =+T189*R189 -> 48.555776 | V189: 20 | W189: =+IF(O189="ACERO A36",VLOOKUP(P189,'Tiempo Objeto'!$B$2:$C$12,2,FALSE),IF(O189="INOXIDABLE",VLOOKUP(P189,'Tiempo Objeto'!$B$14:$C$22,2,FALSE),IF(O189="ALUMINIO",VLOOKUP(P189,'Tiempo Objeto'!$B$24:$C$32,2,FALSE)))) -> 1.84 | X189: =+W189*V189 -> 36.8 | Y189: =+X189*N189/3600 -> 51.111111 | Z189: 2 | AA189: =30*Z189+Z189*$C189*1.5 -> 60 | AB189: =+Z189*Analisis!$J$6 -> 50 | AC189: 0 | AD189: =30*AC189+AC189*$C189*1.5 -> 0 | AE189: =+AD189*Analisis!$J$7 -> 0 | AF189: =+L189+U189+Y189+AB189+AE189 -> 203.88788 | AG189: =+AF189/(1-Analisis!$E$9) -> 254.85986 | AH189: =+AG189*C189 -> 0
... B191: 12-A-6007-08 | C191: =IFERROR(VLOOKUP(B191,'REQ GALV'!A:B,2,0),0) -> 0 | D191: =+AG191 -> 248.88349 | E191: 12ga | F191: DECAPADO | G191: 3.14 | H191: 22 | I191: 0.105 | J191: 28.24 | K191: =+L191*2.2/J191 -> 3.9763944 | L191: =+VLOOKUP(E191,Material!$H$2:$M$17,6,FALSE)*G191*H191*(1+Material!$K$14) -> 51.042444 | M191: =+Analisis!$J$5 -> T5.0 | N191: =+VLOOKUP(M191,Material!$A$3:$B$58,2,FALSE) -> 5000 | O191: ACERO A36 | P191: Cal 12 | Q191: =+IF(O191="ACERO A36",VLOOKUP(P191,'Velocidades Std 1500 w'!$B$2:$F$15,5,FALSE),IF(O191="INOXIDABLE",VLOOKUP(P191,'Velocidades Std 1500 w'!$B$17:$F$28,5,FALSE),IF(O191="ALUMINIO",VLOOKUP(P191,'Velocidades Std 1500 w'!$B$30:$F$38,5,FALSE)))) -> 4.3859649e-06 | R191: =+Q191*N191 -> 0.021929825 | S191: =+Q191*T191*3600 -> 33.806331 | T191: =(+H191*2+G191*2+V191*1.5)*25.4*1.05 -> 2141.0676 | U191: =+T191*R191 -> 46.953237 | V191: 20 | W191: =+IF(O191="ACERO A36",VLOOKUP(P191,'Tiempo Objeto'!$B$2:$C$12,2,FALSE),IF(O191="INOXIDABLE",VLOOKUP(P191,'Tiempo Objeto'!$B$14:$C$22,2,FALSE),IF(O191="ALUMINIO",VLOOKUP(P191,'Tiempo Objeto'!$B$24:$C$32,2,FALSE)))) -> 1.84 | X191: =+W191*V191 -> 36.8 | Y191: =+X191*N191/3600 -> 51.111111 | Z191: 2 | AA191: =30*Z191+Z191*$C191*1.5 -> 60 | AB191: =+Z191*Analisis!$J$6 -> 50 | AC191: 0 | AD191: =30*AC191+AC191*$C191*1.5 -> 0 | AE191: =+AD191*Analisis!$J$7 -> 0 | AF191: =+L191+U191+Y191+AB191+AE191 -> 199.10679 | AG191: =+AF191/(1-Analisis!$E$9) -> 248.88349 | AH191: =+AG191*C191 -> 0
B192: 12-A-6073-01 | C192: =IFERROR(VLOOKUP(B192,'REQ GALV'!A:B,2,0),0) -> 90 | D192: =+AG192 -> 857.49408 | E192: 16ga | F192: DECAPADO | G192: 15.59 | H192: 45.72 | I192: 0.105 | J192: 28.24 | K192: =+L192*2.2/J192 -> 26.92519 | L192: =+VLOOKUP(E192,Material!$H$2:$M$17,6,FALSE)*G192*H192*(1+Material!$K$14) -> 345.62153 | M192: =+Analisis!$J$5 -> T5.0 | N192: =+VLOOKUP(M192,Material!$A$3:$B$58,2,FALSE) -> 5000 | O192: ACERO A36 | P192: Cal 12 | Q192: =+IF(O192="ACERO A36",VLOOKUP(P192,'Velocidades Std 1500 w'!$B$2:$F$15,5,FALSE),IF(O192="INOXIDABLE",VLOOKUP(P192,'Velocidades Std 1500 w'!$B$17:$F$28,5,FALSE),IF(O192="ALUMINIO",VLOOKUP(P192,'Velocidades Std 1500 w'!$B$30:$F$38,5,FALSE)))) -> 4.3859649e-06 | R192: =+Q192*N192 -> 0.021929825 | S192: =+Q192*T192*3600 -> 64.269085 | T192: =(+H192*2+G192*2+V192*1.5)*25.4*1.05 -> 4070.3754 | U192: =+T192*R192 -> 89.262618 | V192: 20 | W192: =+IF(O192="ACERO A36",VLOOKUP(P192,'Tiempo Objeto'!$B$2:$C$12,2,FALSE),IF(O192="INOXIDABLE",VLOOKUP(P192,'Tiempo Objeto'!$B$14:$C$22,2,FALSE),IF(O192="ALUMINIO",VLOOKUP(P192,'Tiempo Objeto'!$B$24:$C$32,2,FALSE)))) -> 1.84 | X192: =+W192*V192 -> 36.8 | Y192: =+X192*N192/3600 -> 51.111111 | Z192: 8 | AA192: =30*Z192+Z192*$C192*1.5 -> 1320 | AB192: =+Z192*Analisis!$J$6 -> 200 | AC192: 0 | AD192: =30*AC192+AC192*$C192*1.5 -> 0 | AE192: =+AD192*Analisis!$J$7 -> 0 | AF192: =+L192+U192+Y192+AB192+AE192 -> 685.99526 | AG192: =+AF192/(1-Analisis!$E$9) -> 857.49408 | AH192: =+AG192*C192 -> 77174.467 | AI192: =+L192*C192 -> 31105.938
B193: 12-A-6076-01 | C193: =IFERROR(VLOOKUP(B193,'REQ GALV'!A:B,2,0),0) -> 0 | D193: =+AG193 -> 1255.3136 | E193: 16ga | F193: DECAPADO | G193: 25.59 | H193: 51.97 | I193: 0.105 | J193: 28.24 | K193: =+L193*2.2/J193 -> 50.237665 | L193: =+VLOOKUP(E193,Material!$H$2:$M$17,6,FALSE)*G193*H193*(1+Material!$K$14) -> 644.86893 | M193: =+Analisis!$J$5 -> T5.0 | N193: =+VLOOKUP(M193,Material!$A$3:$B$58,2,FALSE) -> 5000 | O193: ACERO A36 | P193: Cal 12 | Q193: =+IF(O193="ACERO A36",VLOOKUP(P193,'Velocidades Std 1500 w'!$B$2:$F$15,5,FALSE),IF(O193="INOXIDABLE",VLOOKUP(P193,'Velocidades Std 1500 w'!$B$17:$F$28,5,FALSE),IF(O193="ALUMINIO",VLOOKUP(P193,'Velocidades Std 1500 w'!$B$30:$F$38,5,FALSE)))) -> 4.3859649e-06 | R193: =+Q193*N193 -> 0.021929825 | S193: =+Q193*T193*3600 -> 77.955006 | T193: =(+H193*2+G193*2+V193*1.5)*25.4*1.05 -> 4937.1504 | U193: =+T193*R193 -> 108.27084 | V193: 20 | W193: =+IF(O193="ACERO A36",VLOOKUP(P193,'Tiempo Objeto'!$B$2:$C$12,2,FALSE),IF(O193="INOXIDABLE",VLOOKUP(P193,'Tiempo Objeto'!$B$14:$C$22,2,FALSE),IF(O193="ALUMINIO",VLOOKUP(P193,'Tiempo Objeto'!$B$24:$C$32,2,FALSE)))) -> 1.84 | X193: =+W193*V193 -> 36.8 | Y193: =+X193*N193/3600 -> 51.111111 | Z193: 8 | AA193: =30*Z193+Z193*$C193*1.5 -> 240 | AB193: =+Z193*Analisis!$J$6 -> 200 | AC193: 0 | AD193: =30*AC193+AC193*$C193*1.5 -> 0 | AE193: =+AD193*Analisis!$J$7 -> 0 | AF193: =+L193+U193+Y193+AB193+AE193 -> 1004.2509 | AG193: =+AF193/(1-Analisis!$E$9) -> 1255.3136 | AH193: =+AG193*C193 -> 0
B194: 12-A-6077-01 | C194: =IFERROR(VLOOKUP(B194,'REQ GALV'!A:B,2,0),0) -> 0 | D194: =+AG194 -> 1363.2019 | E194: 12ga | F194: DECAPADO | G194: 25.58 | H194: 39.46 | I194: 0.105 | J194: 28.24 | K194: =+L194*2.2/J194 -> 58.10249 | L194: =+VLOOKUP(E194,Material!$H$2:$M$17,6,FALSE)*G194*H194*(1+Material!$K$14) -> 745.82469 | M194: =+Analisis!$J$5 -> T5.0 | N194: =+VLOOKUP(M194,Material!$A$3:$B$58,2,FALSE) -> 5000 | O194: ACERO A36 | P194: Cal 12 | Q194: =+IF(O194="ACERO A36",VLOOKUP(P194,'Velocidades Std 1500 w'!$B$2:$F$15,5,FALSE),IF(O194="INOXIDABLE",VLOOKUP(P194,'Velocidades Std 1500 w'!$B$17:$F$28,5,FALSE),IF(O194="ALUMINIO",VLOOKUP(P194,'Velocidades Std 1500 w'!$B$30:$F$38,5,FALSE)))) -> 4.3859649e-06 | R194: =+Q194*N194 -> 0.021929825 | S194: =+Q194*T194*3600 -> 67.410531 | T194: =(+H194*2+G194*2+V194*1.5)*25.4*1.05 -> 4269.3336 | U194: =+T194*R194 -> 93.625737 | V194: 20 | W194: =+IF(O194="ACERO A36",VLOOKUP(P194,'Tiempo Objeto'!$B$2:$C$12,2,FALSE),IF(O194="INOXIDABLE",VLOOKUP(P194,'Tiempo Objeto'!$B$14:$C$22,2,FALSE),IF(O194="ALUMINIO",VLOOKUP(P194,'Tiempo Objeto'!$B$24:$C$32,2,FALSE)))) -> 1.84 | X194: =+W194*V194 -> 36.8 | Y194: =+X194*N194/3600 -> 51.111111 | Z194: 8 | AA194: =30*Z194+Z194*$C194*1.5 -> 240 | AB194: =+Z194*Analisis!$J$6 -> 200 | AC194: 0 | AD194: =30*AC194+AC194*$C194*1.5 -> 0 | AE194: =+AD194*Analisis!$J$7 -> 0 | AF194: =+L194+U194+Y194+AB194+AE194 -> 1090.5615 | AG194: =+AF194/(1-Analisis!$E$9) -> 1363.2019 | AH194: =+AG194*C194 -> 0
B195: 12-D-6006-01 | C195: =IFERROR(VLOOKUP(B195,'REQ GALV'!A:B,2,0),0) -> 0 | D195: =+AG195 -> 502.17493 | E195: 12ga | F195: DECAPADO | G195: 4.14 | H195: 14.09 | I195: 0.105 | J195: 28.24 | K195: =+L195*2.2/J195 -> 3.3577508 | L195: =+VLOOKUP(E195,Material!$H$2:$M$17,6,FALSE)*G195*H195*(1+Material!$K$14) -> 43.10131 | M195: =+Analisis!$J$5 -> T5.0 | N195: =+VLOOKUP(M195,Material!$A$3:$B$58,2,FALSE) -> 5000 | O195: ACERO A36 | P195: Cal 12 | Q195: =+IF(O195="ACERO A36",VLOOKUP(P195,'Velocidades Std 1500 w'!$B$2:$F$15,5,FALSE),IF(O195="INOXIDABLE",VLOOKUP(P195,'Velocidades Std 1500 w'!$B$17:$F$28,5,FALSE),IF(O195="ALUMINIO",VLOOKUP(P195,'Velocidades Std 1500 w'!$B$30:$F$38,5,FALSE)))) -> 4.3859649e-06 | R195: =+Q195*N195 -> 0.021929825 | S195: =+Q195*T195*3600 -> 40.619814 | T195: =(+H195*2+G195*2+V195*1.5)*25.4*1.05 -> 2572.5882 | U195: =+T195*R195 -> 56.416408 | V195: 40 | W195: =+IF(O195="ACERO A36",VLOOKUP(P195,'Tiempo Objeto'!$B$2:$C$12,2,FALSE),IF(O195="INOXIDABLE",VLOOKUP(P195,'Tiempo Objeto'!$B$14:$C$22,2,FALSE),IF(O195="ALUMINIO",VLOOKUP(P195,'Tiempo Objeto'!$B$24:$C$32,2,FALSE)))) -> 1.84 | X195: =+W195*V195 -> 73.6 | Y195: =+X195*N195/3600 -> 102.22222 | Z195: 8 | AA195: =30*Z195+Z195*$C195*1.5 -> 240 | AB195: =+Z195*Analisis!$J$6 -> 200 | AC195: 0 | AD195: =30*AC195+AC195*$C195*1.5 -> 0 | AE195: =+AD195*Analisis!$J$7 -> 0 | AF195: =+L195+U195+Y195+AB195+AE195 -> 401.73994 | AG195: =+AF195/(1-Analisis!$E$9) -> 502.17493 | AH195: =+AG195*C195 -> 0
B196: 12-D-6006-02 | C196: =IFERROR(VLOOKUP(B196,'REQ GALV'!A:B,2,0),0) -> 0 | D196: =+AG196 -> 523.31861 | E196: 12ga | F196: DECAPADO | G196: 4.14 | H196: 18.09 | I196: 0.105 | J196: 28.24 | K196: =+L196*2.2/J196 -> 4.3109802 | L196: =+VLOOKUP(E196,Material!$H$2:$M$17,6,FALSE)*G196*H196*(1+Material!$K$14) -> 55.33731 | M196: =+Analisis!$J$5 -> T5.0 | N196: =+VLOOKUP(M196,Material!$A$3:$B$58,2,FALSE) -> 5000 | O196: ACERO A36 | P196: Cal 12 | Q196: =+IF(O196="ACERO A36",VLOOKUP(P196,'Velocidades Std 1500 w'!$B$2:$F$15,5,FALSE),IF(O196="INOXIDABLE",VLOOKUP(P196,'Velocidades Std 1500 w'!$B$17:$F$28,5,FALSE),IF(O196="ALUMINIO",VLOOKUP(P196,'Velocidades Std 1500 w'!$B$30:$F$38,5,FALSE)))) -> 4.3859649e-06 | R196: =+Q196*N196 -> 0.021929825 | S196: =+Q196*T196*3600 -> 43.988656 | T196: =(+H196*2+G196*2+V196*1.5)*25.4*1.05 -> 2785.9482 | U196: =+T196*R196 -> 61.095355 | V196: 40 | W196: =+IF(O196="ACERO A36",VLOOKUP(P196,'Tiempo Objeto'!$B$2:$C$12,2,FALSE),IF(O196="INOXIDABLE",VLOOKUP(P196,'Tiempo Objeto'!$B$14:$C$22,2,FALSE),IF(O196="ALUMINIO",VLOOKUP(P196,'Tiempo Objeto'!$B$24:$C$32,2,FALSE)))) -> 1.84 | X196: =+W196*V196 -> 73.6 | Y196: =+X196*N196/3600 -> 102.22222 | Z196: 8 | AA196: =30*Z196+Z196*$C196*1.5 -> 240 | AB196: =+Z196*Analisis!$J$6 -> 200 | AC196: 0 | AD196: =30*AC196+AC196*$C196*1.5 -> 0 | AE196: =+AD196*Analisis!$J$7 -> 0 | AF196: =+L196+U196+Y196+AB196+AE196 -> 418.65489 | AG196: =+AF196/(1-Analisis!$E$9) -> 523.31861 | AH196: =+AG196*C196 -> 0
B197: 12-D-6006-03 | C197: =IFERROR(VLOOKUP(B197,'REQ GALV'!A:B,2,0),0) -> 180 | D197: =+AG197 -> 533.89045 | E197: 12ga | F197: DECAPADO | G197: 4.14 | H197: 20.09 | I197: 0.105 | J197: 28.24 | K197: =+L197*2.2/J197 -> 4.787595 | L197: =+VLOOKUP(E197,Material!$H$2:$M$17,6,FALSE)*G197*H197*(1+Material!$K$14) -> 61.45531 | M197: =+Analisis!$J$5 -> T5.0 | N197: =+VLOOKUP(M197,Material!$A$3:$B$58,2,FALSE) -> 5000 | O197: ACERO A36 | P197: Cal 12 | Q197: =+IF(O197="ACERO A36",VLOOKUP(P197,'Velocidades Std 1500 w'!$B$2:$F$15,5,FALSE),IF(O197="INOXIDABLE",VLOOKUP(P197,'Velocidades Std 1500 w'!$B$17:$F$28,5,FALSE),IF(O197="ALUMINIO",VLOOKUP(P197,'Velocidades Std 1500 w'!$B$30:$F$38,5,FALSE)))) -> 4.3859649e-06 | R197: =+Q197*N197 -> 0.021929825 | S197: =+Q197*T197*3600 -> 45.673077 | T197: =(+H197*2+G197*2+V197*1.5)*25.4*1.05 -> 2892.6282 | U197: =+T197*R197 -> 63.434829 | V197: 40 | W197: =+IF(O197="ACERO A36",VLOOKUP(P197,'Tiempo Objeto'!$B$2:$C$12,2,FALSE),IF(O197="INOXIDABLE",VLOOKUP(P197,'Tiempo Objeto'!$B$14:$C$22,2,FALSE),IF(O197="ALUMINIO",VLOOKUP(P197,'Tiempo Objeto'!$B$24:$C$32,2,FALSE)))) -> 1.84 | X197: =+W197*V197 -> 73.6 | Y197: =+X197*N197/3600 -> 102.22222 | Z197: 8 | AA197: =30*Z197+Z197*$C197*1.5 -> 2400 | AB197: =+Z197*Analisis!$J$6 -> 200 | AC197: 0 | AD197: =30*AC197+AC197*$C197*1.5 -> 0 | AE197: =+AD197*Analisis!$J$7 -> 0 | AF197: =+L197+U197+Y197+AB197+AE197 -> 427.11236 | AG197: =+AF197/(1-Analisis!$E$9) -> 533.89045 | AH197: =+AG197*C197 -> 96100.281 | AI197: =+L197*C197 -> 11061.956
B198: 12-D-6006-04 | C198: =IFERROR(VLOOKUP(B198,'REQ GALV'!A:B,2,0),0) -> 0 | D198: =+AG198 -> 565.60598 | E198: 12ga | F198: DECAPADO | G198: 4.14 | H198: 26.09 | I198: 0.105 | J198: 28.24 | K198: =+L198*2.2/J198 -> 6.2174392 | L198: =+VLOOKUP(E198,Material!$H$2:$M$17,6,FALSE)*G198*H198*(1+Material!$K$14) -> 79.80931 | M198: =+Analisis!$J$5 -> T5.0 | N198: =+VLOOKUP(M198,Material!$A$3:$B$58,2,FALSE) -> 5000 | O198: ACERO A36 | P198: Cal 12 | Q198: =+IF(O198="ACERO A36",VLOOKUP(P198,'Velocidades Std 1500 w'!$B$2:$F$15,5,FALSE),IF(O198="INOXIDABLE",VLOOKUP(P198,'Velocidades Std 1500 w'!$B$17:$F$28,5,FALSE),IF(O198="ALUMINIO",VLOOKUP(P198,'Velocidades Std 1500 w'!$B$30:$F$38,5,FALSE)))) -> 4.3859649e-06 | R198: =+Q198*N198 -> 0.021929825 | S198: =+Q198*T198*3600 -> 50.72634 | T198: =(+H198*2+G198*2+V198*1.5)*25.4*1.05 -> 3212.6682 | U198: =+T198*R198 -> 70.45325 | V198: 40 | W198: =+IF(O198="ACERO A36",VLOOKUP(P198,'Tiempo Objeto'!$B$2:$C$12,2,FALSE),IF(O198="INOXIDABLE",VLOOKUP(P198,'Tiempo Objeto'!$B$14:$C$22,2,FALSE),IF(O198="ALUMINIO",VLOOKUP(P198,'Tiempo Objeto'!$B$24:$C$32,2,FALSE)))) -> 1.84 | X198: =+W198*V198 -> 73.6 | Y198: =+X198*N198/3600 -> 102.22222 | Z198: 8 | AA198: =30*Z198+Z198*$C198*1.5 -> 240 | AB198: =+Z198*Analisis!$J$6 -> 200 | AC198: 0 | AD198: =30*AC198+AC198*$C198*1.5 -> 0 | AE198: =+AD198*Analisis!$J$7 -> 0 | AF198: =+L198+U198+Y198+AB198+AE198 -> 452.48478 | AG198: =+AF198/(1-Analisis!$E$9) -> 565.60598 | AH198: =+AG198*C198 -> 0
B199: 12-D-6006-05 | C199: =IFERROR(VLOOKUP(B199,'REQ GALV'!A:B,2,0),0) -> 300 | D199: =+AG199 -> 597.3215 | E199: 12ga | F199: DECAPADO | G199: 4.14 | H199: 32.09 | I199: 0.105 | J199: 28.24 | K199: =+L199*2.2/J199 -> 7.6472834 | L199: =+VLOOKUP(E199,Material!$H$2:$M$17,6,FALSE)*G199*H199*(1+Material!$K$14) -> 98.16331 | M199: =+Analisis!$J$5 -> T5.0 | N199: =+VLOOKUP(M199,Material!$A$3:$B$58,2,FALSE) -> 5000 | O199: ACERO A36 | P199: Cal 12 | Q199: =+IF(O199="ACERO A36",VLOOKUP(P199,'Velocidades Std 1500 w'!$B$2:$F$15,5,FALSE),IF(O199="INOXIDABLE",VLOOKUP(P199,'Velocidades Std 1500 w'!$B$17:$F$28,5,FALSE),IF(O199="ALUMINIO",VLOOKUP(P199,'Velocidades Std 1500 w'!$B$30:$F$38,5,FALSE)))) -> 4.3859649e-06 | R199: =+Q199*N199 -> 0.021929825 | S199: =+Q199*T199*3600 -> 55.779603 | T199: =(+H199*2+G199*2+V199*1.5)*25.4*1.05 -> 3532.7082 | U199: =+T199*R199 -> 77.471671 | V199: 40 | W199: =+IF(O199="ACERO A36",VLOOKUP(P199,'Tiempo Objeto'!$B$2:$C$12,2,FALSE),IF(O199="INOXIDABLE",VLOOKUP(P199,'Tiempo Objeto'!$B$14:$C$22,2,FALSE),IF(O199="ALUMINIO",VLOOKUP(P199,'Tiempo Objeto'!$B$24:$C$32,2,FALSE)))) -> 1.84 | X199: =+W199*V199 -> 73.6 | Y199: =+X199*N199/3600 -> 102.22222 | Z199: 8 | AA199: =30*Z199+Z199*$C199*1.5 -> 3840 | AB199: =+Z199*Analisis!$J$6 -> 200 | AC199: 0 | AD199: =30*AC199+AC199*$C199*1.5 -> 0 | AE199: =+AD199*Analisis!$J$7 -> 0 | AF199: =+L199+U199+Y199+AB199+AE199 -> 477.8572 | AG199: =+AF199/(1-Analisis!$E$9) -> 597.3215 | AH199: =+AG199*C199 -> 179196.45 | AI199: =+L199*C199 -> 29448.993
B200: 12-D-6006-06 | C200: =IFERROR(VLOOKUP(B200,'REQ GALV'!A:B,2,0),0) -> 420 | D200: =+AG200 -> 629.03703 | E200: 12ga | F200: DECAPADO | G200: 4.14 | H200: 38.09 | I200: 0.105 | J200: 28.24 | K200: =+L200*2.2/J200 -> 9.0771275 | L200: =+VLOOKUP(E200,Material!$H$2:$M$17,6,FALSE)*G200*H200*(1+Material!$K$14) -> 116.51731 | M200: =+Analisis!$J$5 -> T5.0 | N200: =+VLOOKUP(M200,Material!$A$3:$B$58,2,FALSE) -> 5000 | O200: ACERO A36 | P200: Cal 12 | Q200: =+IF(O200="ACERO A36",VLOOKUP(P200,'Velocidades Std 1500 w'!$B$2:$F$15,5,FALSE),IF(O200="INOXIDABLE",VLOOKUP(P200,'Velocidades Std 1500 w'!$B$17:$F$28,5,FALSE),IF(O200="ALUMINIO",VLOOKUP(P200,'Velocidades Std 1500 w'!$B$30:$F$38,5,FALSE)))) -> 4.3859649e-06 | R200: =+Q200*N200 -> 0.021929825 | S200: =+Q200*T200*3600 -> 60.832866 | T200: =(+H200*2+G200*2+V200*1.5)*25.4*1.05 -> 3852.7482 | U200: =+T200*R200 -> 84.490092 | V200: 40 | W200: =+IF(O200="ACERO A36",VLOOKUP(P200,'Tiempo Objeto'!$B$2:$C$12,2,FALSE),IF(O200="INOXIDABLE",VLOOKUP(P200,'Tiempo Objeto'!$B$14:$C$22,2,FALSE),IF(O200="ALUMINIO",VLOOKUP(P200,'Tiempo Objeto'!$B$24:$C$32,2,FALSE)))) -> 1.84 | X200: =+W200*V200 -> 73.6 | Y200: =+X200*N200/3600 -> 102.22222 | Z200: 8 | AA200: =30*Z200+Z200*$C200*1.5 -> 5280 | AB200: =+Z200*Analisis!$J$6 -> 200 | AC200: 0 | AD200: =30*AC200+AC200*$C200*1.5 -> 0 | AE200: =+AD200*Analisis!$J$7 -> 0 | AF200: =+L200+U200+Y200+AB200+AE200 -> 503.22962 | AG200: =+AF200/(1-Analisis!$E$9) -> 629.03703 | AH200: =+AG200*C200 -> 264195.55 | AI200: =+L200*C200 -> 48937.27
B201: 12-D-6006-07 | C201: =IFERROR(VLOOKUP(B201,'REQ GALV'!A:B,2,0),0) -> 120 | D201: =+AG201 -> 671.3244 | E201: 12ga | F201: DECAPADO | G201: 4.14 | H201: 46.09 | I201: 0.105 | J201: 28.24 | K201: =+L201*2.2/J201 -> 10.983586 | L201: =+VLOOKUP(E201,Material!$H$2:$M$17,6,FALSE)*G201*H201*(1+Material!$K$14) -> 140.98931 | M201: =+Analisis!$J$5 -> T5.0 | N201: =+VLOOKUP(M201,Material!$A$3:$B$58,2,FALSE) -> 5000 | O201: ACERO A36 | P201: Cal 12 | Q201: =+IF(O201="ACERO A36",VLOOKUP(P201,'Velocidades Std 1500 w'!$B$2:$F$15,5,FALSE),IF(O201="INOXIDABLE",VLOOKUP(P201,'Velocidades Std 1500 w'!$B$17:$F$28,5,FALSE),IF(O201="ALUMINIO",VLOOKUP(P201,'Velocidades Std 1500 w'!$B$30:$F$38,5,FALSE)))) -> 4.3859649e-06 | R201: =+Q201*N201 -> 0.021929825 | S201: =+Q201*T201*3600 -> 67.570551 | T201: =(+H201*2+G201*2+V201*1.5)*25.4*1.05 -> 4279.4682 | U201: =+T201*R201 -> 93.847987 | V201: 40 | W201: =+IF(O201="ACERO A36",VLOOKUP(P201,'Tiempo Objeto'!$B$2:$C$12,2,FALSE),IF(O201="INOXIDABLE",VLOOKUP(P201,'Tiempo Objeto'!$B$14:$C$22,2,FALSE),IF(O201="ALUMINIO",VLOOKUP(P201,'Tiempo Objeto'!$B$24:$C$32,2,FALSE)))) -> 1.84 | X201: =+W201*V201 -> 73.6 | Y201: =+X201*N201/3600 -> 102.22222 | Z201: 8 | AA201: =30*Z201+Z201*$C201*1.5 -> 1680 | AB201: =+Z201*Analisis!$J$6 -> 200 | AC201: 0 | AD201: =30*AC201+AC201*$C201*1.5 -> 0 | AE201: =+AD201*Analisis!$J$7 -> 0 | AF201: =+L201+U201+Y201+AB201+AE201 -> 537.05952 | AG201: =+AF201/(1-Analisis!$E$9) -> 671.3244 | AH201: =+AG201*C201 -> 80558.928 | AI201: =+L201*C201 -> 16918.717
B202: 12-D-6006-08 | C202: =IFERROR(VLOOKUP(B202,'REQ GALV'!A:B,2,0),0) -> 0 | D202: =+AG202 -> 613.17927 | E202: 12ga | F202: DECAPADO | G202: 4.14 | H202: 35.09 | I202: 0.105 | J202: 28.24 | K202: =+L202*2.2/J202 -> 8.3622055 | L202: =+VLOOKUP(E202,Material!$H$2:$M$17,6,FALSE)*G202*H202*(1+Material!$K$14) -> 107.34031 | M202: =+Analisis!$J$5 -> T5.0 | N202: =+VLOOKUP(M202,Material!$A$3:$B$58,2,FALSE) -> 5000 | O202: ACERO A36 | P202: Cal 12 | Q202: =+IF(O202="ACERO A36",VLOOKUP(P202,'Velocidades Std 1500 w'!$B$2:$F$15,5,FALSE),IF(O202="INOXIDABLE",VLOOKUP(P202,'Velocidades Std 1500 w'!$B$17:$F$28,5,FALSE),IF(O202="ALUMINIO",VLOOKUP(P202,'Velocidades Std 1500 w'!$B$30:$F$38,5,FALSE)))) -> 4.3859649e-06 | R202: =+Q202*N202 -> 0.021929825 | S202: =+Q202*T202*3600 -> 58.306235 | T202: =(+H202*2+G202*2+V202*1.5)*25.4*1.05 -> 3692.7282 | U202: =+T202*R202 -> 80.980882 | V202: 40 | W202: =+IF(O202="ACERO A36",VLOOKUP(P202,'Tiempo Objeto'!$B$2:$C$12,2,FALSE),IF(O202="INOXIDABLE",VLOOKUP(P202,'Tiempo Objeto'!$B$14:$C$22,2,FALSE),IF(O202="ALUMINIO",VLOOKUP(P202,'Tiempo Objeto'!$B$24:$C$32,2,FALSE)))) -> 1.84 | X202: =+W202*V202 -> 73.6 | Y202: =+X202*N202/3600 -> 102.22222 | Z202: 8 | AA202: =30*Z202+Z202*$C202*1.5 -> 240 | AB202: =+Z202*Analisis!$J$6 -> 200 | AC202: 0 | AD202: =30*AC202+AC202*$C202*1.5 -> 0 | AE202: =+AD202*Analisis!$J$7 -> 0 | AF202: =+L202+U202+Y202+AB202+AE202 -> 490.54341 | AG202: =+AF202/(1-Analisis!$E$9) -> 613.17927 | AH202: =+AG202*C202 -> 0
B203: 12-D-6006-09 | C203: =IFERROR(VLOOKUP(B203,'REQ GALV'!A:B,2,0),0) -> 0 | D203: =+AG203 -> 703.03993 | E203: 12ga | F203: DECAPADO | G203: 4.14 | H203: 52.09 | I203: 0.105 | J203: 28.24 | K203: =+L203*2.2/J203 -> 12.413431 | L203: =+VLOOKUP(E203,Material!$H$2:$M$17,6,FALSE)*G203*H203*(1+Material!$K$14) -> 159.34331 | M203: =+Analisis!$J$5 -> T5.0 | N203: =+VLOOKUP(M203,Material!$A$3:$B$58,2,FALSE) -> 5000 | O203: ACERO A36 | P203: Cal 12 | Q203: =+IF(O203="ACERO A36",VLOOKUP(P203,'Velocidades Std 1500 w'!$B$2:$F$15,5,FALSE),IF(O203="INOXIDABLE",VLOOKUP(P203,'Velocidades Std 1500 w'!$B$17:$F$28,5,FALSE),IF(O203="ALUMINIO",VLOOKUP(P203,'Velocidades Std 1500 w'!$B$30:$F$38,5,FALSE)))) -> 4.3859649e-06 | R203: =+Q203*N203 -> 0.021929825 | S203: =+Q203*T203*3600 -> 72.623814 | T203: =(+H203*2+G203*2+V203*1.5)*25.4*1.05 -> 4599.5082 | U203: =+T203*R203 -> 100.86641 | V203: 40 | W203: =+IF(O203="ACERO A36",VLOOKUP(P203,'Tiempo Objeto'!$B$2:$C$12,2,FALSE),IF(O203="INOXIDABLE",VLOOKUP(P203,'Tiempo Objeto'!$B$14:$C$22,2,FALSE),IF(O203="ALUMINIO",VLOOKUP(P203,'Tiempo Objeto'!$B$24:$C$32,2,FALSE)))) -> 1.84 | X203: =+W203*V203 -> 73.6 | Y203: =+X203*N203/3600 -> 102.22222 | Z203: 8 | AA203: =30*Z203+Z203*$C203*1.5 -> 240 | AB203: =+Z203*Analisis!$J$6 -> 200 | AC203: 0 | AD203: =30*AC203+AC203*$C203*1.5 -> 0 | AE203: =+AD203*Analisis!$J$7 -> 0 | AF203: =+L203+U203+Y203+AB203+AE203 -> 562.43194 | AG203: =+AF203/(1-Analisis!$E$9) -> 703.03993 | AH203: =+AG203*C203 -> 0
B204: 12-D-6006-10 | C204: =IFERROR(VLOOKUP(B204,'REQ GALV'!A:B,2,0),0) -> 0 | D204: =+AG204 -> 734.75545 | E204: 12ga | F204: DECAPADO | G204: 4.14 | H204: 58.09 | I204: 0.105 | J204: 28.24 | K204: =+L204*2.2/J204 -> 13.843275 | L204: =+VLOOKUP(E204,Material!$H$2:$M$17,6,FALSE)*G204*H204*(1+Material!$K$14) -> 177.69731 | M204: =+Analisis!$J$5 -> T5.0 | N204: =+VLOOKUP(M204,Material!$A$3:$B$58,2,FALSE) -> 5000 | O204: ACERO A36 | P204: Cal 12 | Q204: =+IF(O204="ACERO A36",VLOOKUP(P204,'Velocidades Std 1500 w'!$B$2:$F$15,5,FALSE),IF(O204="INOXIDABLE",VLOOKUP(P204,'Velocidades Std 1500 w'!$B$17:$F$28,5,FALSE),IF(O204="ALUMINIO",VLOOKUP(P204,'Velocidades Std 1500 w'!$B$30:$F$38,5,FALSE)))) -> 4.3859649e-06 | R204: =+Q204*N204 -> 0.021929825 | S204: =+Q204*T204*3600 -> 77.677077 | T204: =(+H204*2+G204*2+V204*1.5)*25.4*1.05 -> 4919.5482 | U204: =+T204*R204 -> 107.88483 | V204: 40 | W204: =+IF(O204="ACERO A36",VLOOKUP(P204,'Tiempo Objeto'!$B$2:$C$12,2,FALSE),IF(O204="INOXIDABLE",VLOOKUP(P204,'Tiempo Objeto'!$B$14:$C$22,2,FALSE),IF(O204="ALUMINIO",VLOOKUP(P204,'Tiempo Objeto'!$B$24:$C$32,2,FALSE)))) -> 1.84 | X204: =+W204*V204 -> 73.6 | Y204: =+X204*N204/3600 -> 102.22222 | Z204: 8 | AA204: =30*Z204+Z204*$C204*1.5 -> 240 | AB204: =+Z204*Analisis!$J$6 -> 200 | AC204: 0 | AD204: =30*AC204+AC204*$C204*1.5 -> 0 | AE204: =+AD204*Analisis!$J$7 -> 0 | AF204: =+L204+U204+Y204+AB204+AE204 -> 587.80436 | AG204: =+AF204/(1-Analisis!$E$9) -> 734.75545 | AH204: =+AG204*C204 -> 0
B205: 12-D-6006-11 | C205: =IFERROR(VLOOKUP(B205,'REQ GALV'!A:B,2,0),0) -> 0 | D205: =+AG205 -> 576.17782 | E205: 12ga | F205: DECAPADO | G205: 4.14 | H205: 28.09 | I205: 0.105 | J205: 28.24 | K205: =+L205*2.2/J205 -> 6.6940539 | L205: =+VLOOKUP(E205,Material!$H$2:$M$17,6,FALSE)*G205*H205*(1+Material!$K$14) -> 85.92731 | M205: =+Analisis!$J$5 -> T5.0 | N205: =+VLOOKUP(M205,Material!$A$3:$B$58,2,FALSE) -> 5000 | O205: ACERO A36 | P205: Cal 12 | Q205: =+IF(O205="ACERO A36",VLOOKUP(P205,'Velocidades Std 1500 w'!$B$2:$F$15,5,FALSE),IF(O205="INOXIDABLE",VLOOKUP(P205,'Velocidades Std 1500 w'!$B$17:$F$28,5,FALSE),IF(O205="ALUMINIO",VLOOKUP(P205,'Velocidades Std 1500 w'!$B$30:$F$38,5,FALSE)))) -> 4.3859649e-06 | R205: =+Q205*N205 -> 0.021929825 | S205: =+Q205*T205*3600 -> 52.410761 | T205: =(+H205*2+G205*2+V205*1.5)*25.4*1.05 -> 3319.3482 | U205: =+T205*R205 -> 72.792724 | V205: 40 | W205: =+IF(O205="ACERO A36",VLOOKUP(P205,'Tiempo Objeto'!$B$2:$C$12,2,FALSE),IF(O205="INOXIDABLE",VLOOKUP(P205,'Tiempo Objeto'!$B$14:$C$22,2,FALSE),IF(O205="ALUMINIO",VLOOKUP(P205,'Tiempo Objeto'!$B$24:$C$32,2,FALSE)))) -> 1.84 | X205: =+W205*V205 -> 73.6 | Y205: =+X205*N205/3600 -> 102.22222 | Z205: 8 | AA205: =30*Z205+Z205*$C205*1.5 -> 240 | AB205: =+Z205*Analisis!$J$6 -> 200 | AC205: 0 | AD205: =30*AC205+AC205*$C205*1.5 -> 0 | AE205: =+AD205*Analisis!$J$7 -> 0 | AF205: =+L205+U205+Y205+AB205+AE205 -> 460.94226 | AG205: =+AF205/(1-Analisis!$E$9) -> 576.17782 | AH205: =+AG205*C205 -> 0
B206: 12-D-6006-12 | C206: =IFERROR(VLOOKUP(B206,'REQ GALV'!A:B,2,0),0) -> 0 | D206: =+AG206 -> 639.60887 | E206: 12ga | F206: DECAPADO | G206: 4.14 | H206: 40.09 | I206: 0.105 | J206: 28.24 | K206: =+L206*2.2/J206 -> 9.5537423 | L206: =+VLOOKUP(E206,Material!$H$2:$M$17,6,FALSE)*G206*H206*(1+Material!$K$14) -> 122.63531 | M206: =+Analisis!$J$5 -> T5.0 | N206: =+VLOOKUP(M206,Material!$A$3:$B$58,2,FALSE) -> 5000 | O206: ACERO A36 | P206: Cal 12 | Q206: =+IF(O206="ACERO A36",VLOOKUP(P206,'Velocidades Std 1500 w'!$B$2:$F$15,5,FALSE),IF(O206="INOXIDABLE",VLOOKUP(P206,'Velocidades Std 1500 w'!$B$17:$F$28,5,FALSE),IF(O206="ALUMINIO",VLOOKUP(P206,'Velocidades Std 1500 w'!$B$30:$F$38,5,FALSE)))) -> 4.3859649e-06 | R206: =+Q206*N206 -> 0.021929825 | S206: =+Q206*T206*3600 -> 62.517287 | T206: =(+H206*2+G206*2+V206*1.5)*25.4*1.05 -> 3959.4282 | U206: =+T206*R206 -> 86.829566 | V206: 40 | W206: =+IF(O206="ACERO A36",VLOOKUP(P206,'Tiempo Objeto'!$B$2:$C$12,2,FALSE),IF(O206="INOXIDABLE",VLOOKUP(P206,'Tiempo Objeto'!$B$14:$C$22,2,FALSE),IF(O206="ALUMINIO",VLOOKUP(P206,'Tiempo Objeto'!$B$24:$C$32,2,FALSE)))) -> 1.84 | X206: =+W206*V206 -> 73.6 | Y206: =+X206*N206/3600 -> 102.22222 | Z206: 8 | AA206: =30*Z206+Z206*$C206*1.5 -> 240 | AB206: =+Z206*Analisis!$J$6 -> 200 | AC206: 0 | AD206: =30*AC206+AC206*$C206*1.5 -> 0 | AE206: =+AD206*Analisis!$J$7 -> 0 | AF206: =+L206+U206+Y206+AB206+AE206 -> 511.6871 | AG206: =+AF206/(1-Analisis!$E$9) -> 639.60887 | AH206: =+AG206*C206 -> 0
B207: 12-D-6006-13 | C207: =IFERROR(VLOOKUP(B207,'REQ GALV'!A:B,2,0),0) -> 0 | D207: =+AG207 -> 681.89624 | E207: 12ga | F207: DECAPADO | G207: 4.14 | H207: 48.09 | I207: 0.105 | J207: 28.24 | K207: =+L207*2.2/J207 -> 11.460201 | L207: =+VLOOKUP(E207,Material!$H$2:$M$17,6,FALSE)*G207*H207*(1+Material!$K$14) -> 147.10731 | M207: =+Analisis!$J$5 -> T5.0 | N207: =+VLOOKUP(M207,Material!$A$3:$B$58,2,FALSE) -> 5000 | O207: ACERO A36 | P207: Cal 12 | Q207: =+IF(O207="ACERO A36",VLOOKUP(P207,'Velocidades Std 1500 w'!$B$2:$F$15,5,FALSE),IF(O207="INOXIDABLE",VLOOKUP(P207,'Velocidades Std 1500 w'!$B$17:$F$28,5,FALSE),IF(O207="ALUMINIO",VLOOKUP(P207,'Velocidades Std 1500 w'!$B$30:$F$38,5,FALSE)))) -> 4.3859649e-06 | R207: =+Q207*N207 -> 0.021929825 | S207: =+Q207*T207*3600 -> 69.254972 | T207: =(+H207*2+G207*2+V207*1.5)*25.4*1.05 -> 4386.1482 | U207: =+T207*R207 -> 96.187461 | V207: 40 | W207: =+IF(O207="ACERO A36",VLOOKUP(P207,'Tiempo Objeto'!$B$2:$C$12,2,FALSE),IF(O207="INOXIDABLE",VLOOKUP(P207,'Tiempo Objeto'!$B$14:$C$22,2,FALSE),IF(O207="ALUMINIO",VLOOKUP(P207,'Tiempo Objeto'!$B$24:$C$32,2,FALSE)))) -> 1.84 | X207: =+W207*V207 -> 73.6 | Y207: =+X207*N207/3600 -> 102.22222 | Z207: 8 | AA207: =30*Z207+Z207*$C207*1.5 -> 240 | AB207: =+Z207*Analisis!$J$6 -> 200 | AC207: 0 | AD207: =30*AC207+AC207*$C207*1.5 -> 0 | AE207: =+AD207*Analisis!$J$7 -> 0 | AF207: =+L207+U207+Y207+AB207+AE207 -> 545.51699 | AG207: =+AF207/(1-Analisis!$E$9) -> 681.89624 | AH207: =+AG207*C207 -> 0
B208: 12-D-6006-14 | C208: =IFERROR(VLOOKUP(B208,'REQ GALV'!A:B,2,0),0) -> 180 | D208: =+AG208 -> 560.32006 | E208: 12ga | F208: DECAPADO | G208: 4.14 | H208: 25.09 | I208: 0.105 | J208: 28.24 | K208: =+L208*2.2/J208 -> 5.9791318 | L208: =+VLOOKUP(E208,Material!$H$2:$M$17,6,FALSE)*G208*H208*(1+Material!$K$14) -> 76.75031 | M208: =+Analisis!$J$5 -> T5.0 | N208: =+VLOOKUP(M208,Material!$A$3:$B$58,2,FALSE) -> 5000 | O208: ACERO A36 | P208: Cal 12 | Q208: =+IF(O208="ACERO A36",VLOOKUP(P208,'Velocidades Std 1500 w'!$B$2:$F$15,5,FALSE),IF(O208="INOXIDABLE",VLOOKUP(P208,'Velocidades Std 1500 w'!$B$17:$F$28,5,FALSE),IF(O208="ALUMINIO",VLOOKUP(P208,'Velocidades Std 1500 w'!$B$30:$F$38,5,FALSE)))) -> 4.3859649e-06 | R208: =+Q208*N208 -> 0.021929825 | S208: =+Q208*T208*3600 -> 49.884129 | T208: =(+H208*2+G208*2+V208*1.5)*25.4*1.05 -> 3159.3282 | U208: =+T208*R208 -> 69.283513 | V208: 40 | W208: =+IF(O208="ACERO A36",VLOOKUP(P208,'Tiempo Objeto'!$B$2:$C$12,2,FALSE),IF(O208="INOXIDABLE",VLOOKUP(P208,'Tiempo Objeto'!$B$14:$C$22,2,FALSE),IF(O208="ALUMINIO",VLOOKUP(P208,'Tiempo Objeto'!$B$24:$C$32,2,FALSE)))) -> 1.84 | X208: =+W208*V208 -> 73.6 | Y208: =+X208*N208/3600 -> 102.22222 | Z208: 8 | AA208: =30*Z208+Z208*$C208*1.5 -> 2400 | AB208: =+Z208*Analisis!$J$6 -> 200 | AC208: 0 | AD208: =30*AC208+AC208*$C208*1.5 -> 0 | AE208: =+AD208*Analisis!$J$7 -> 0 | AF208: =+L208+U208+Y208+AB208+AE208 -> 448.25605 | AG208: =+AF208/(1-Analisis!$E$9) -> 560.32006 | AH208: =+AG208*C208 -> 100857.61 | AI208: =+L208*C208 -> 13815.056
B209: 12-D-6007-01 | C209: =IFERROR(VLOOKUP(B209,'REQ GALV'!A:B,2,0),0) -> 900 | D209: =+AG209 -> 570.46956 | E209: 12ga | F209: DECAPADO | G209: 4.75 | H209: 38.29 | I209: 0.105 | J209: 28.24 | K209: =+L209*2.2/J209 -> 10.469263 | L209: =+VLOOKUP(E209,Material!$H$2:$M$17,6,FALSE)*G209*H209*(1+Material!$K$14) -> 134.38726 | M209: =+Analisis!$J$5 -> T5.0 | N209: =+VLOOKUP(M209,Material!$A$3:$B$58,2,FALSE) -> 5000 | O209: ACERO A36 | P209: Cal 12 | Q209: =+IF(O209="ACERO A36",VLOOKUP(P209,'Velocidades Std 1500 w'!$B$2:$F$15,5,FALSE),IF(O209="INOXIDABLE",VLOOKUP(P209,'Velocidades Std 1500 w'!$B$17:$F$28,5,FALSE),IF(O209="ALUMINIO",VLOOKUP(P209,'Velocidades Std 1500 w'!$B$30:$F$38,5,FALSE)))) -> 4.3859649e-06 | R209: =+Q209*N209 -> 0.021929825 | S209: =+Q209*T209*3600 -> 67.831636 | T209: =(+H209*2+G209*2+V209*1.5)*25.4*1.05 -> 4296.0036 | U209: =+T209*R209 -> 94.210605 | V209: 50 | W209: =+IF(O209="ACERO A36",VLOOKUP(P209,'Tiempo Objeto'!$B$2:$C$12,2,FALSE),IF(O209="INOXIDABLE",VLOOKUP(P209,'Tiempo Objeto'!$B$14:$C$22,2,FALSE),IF(O209="ALUMINIO",VLOOKUP(P209,'Tiempo Objeto'!$B$24:$C$32,2,FALSE)))) -> 1.84 | X209: =+W209*V209 -> 92 | Y209: =+X209*N209/3600 -> 127.77778 | Z209: 4 | AA209: =30*Z209+Z209*$C209*1.5 -> 5520 | AB209: =+Z209*Analisis!$J$6 -> 100 | AC209: 0 | AD209: =30*AC209+AC209*$C209*1.5 -> 0 | AE209: =+AD209*Analisis!$J$7 -> 0 | AF209: =+L209+U209+Y209+AB209+AE209 -> 456.37565 | AG209: =+AF209/(1-Analisis!$E$9) -> 570.46956 | AH209: =+AG209*C209 -> 513422.6 | AI209: =+L209*C209 -> 120948.54
B210: 12-D-6007-02 | C210: =IFERROR(VLOOKUP(B210,'REQ GALV'!A:B,2,0),0) -> 0 | D210: =+AG210 -> 628.9628 | E210: 12ga | F210: DECAPADO | G210: 4.75 | H210: 48.29 | I210: 0.105 | J210: 28.24 | K210: =+L210*2.2/J210 -> 13.203466 | L210: =+VLOOKUP(E210,Material!$H$2:$M$17,6,FALSE)*G210*H210*(1+Material!$K$14) -> 169.48449 | M210: =+Analisis!$J$5 -> T5.0 | N210: =+VLOOKUP(M210,Material!$A$3:$B$58,2,FALSE) -> 5000 | O210: ACERO A36 | P210: Cal 12 | Q210: =+IF(O210="ACERO A36",VLOOKUP(P210,'Velocidades Std 1500 w'!$B$2:$F$15,5,FALSE),IF(O210="INOXIDABLE",VLOOKUP(P210,'Velocidades Std 1500 w'!$B$17:$F$28,5,FALSE),IF(O210="ALUMINIO",VLOOKUP(P210,'Velocidades Std 1500 w'!$B$30:$F$38,5,FALSE)))) -> 4.3859649e-06 | R210: =+Q210*N210 -> 0.021929825 | S210: =+Q210*T210*3600 -> 76.253741 | T210: =(+H210*2+G210*2+V210*1.5)*25.4*1.05 -> 4829.4036 | U210: =+T210*R210 -> 105.90797 | V210: 50 | W210: =+IF(O210="ACERO A36",VLOOKUP(P210,'Tiempo Objeto'!$B$2:$C$12,2,FALSE),IF(O210="INOXIDABLE",VLOOKUP(P210,'Tiempo Objeto'!$B$14:$C$22,2,FALSE),IF(O210="ALUMINIO",VLOOKUP(P210,'Tiempo Objeto'!$B$24:$C$32,2,FALSE)))) -> 1.84 | X210: =+W210*V210 -> 92 | Y210: =+X210*N210/3600 -> 127.77778 | Z210: 4 | AA210: =30*Z210+Z210*$C210*1.5 -> 120 | AB210: =+Z210*Analisis!$J$6 -> 100 | AC210: 0 | AD210: =30*AC210+AC210*$C210*1.5 -> 0 | AE210: =+AD210*Analisis!$J$7 -> 0 | AF210: =+L210+U210+Y210+AB210+AE210 -> 503.17024 | AG210: =+AF210/(1-Analisis!$E$9) -> 628.9628 | AH210: =+AG210*C210 -> 0
B211: 12-D-6007-03 | C211: =IFERROR(VLOOKUP(B211,'REQ GALV'!A:B,2,0),0) -> 0 | D211: =+AG211 -> 687.45604 | E211: 12ga | F211: DECAPADO | G211: 4.75 | H211: 58.29 | I211: 0.105 | J211: 28.24 | K211: =+L211*2.2/J211 -> 15.937668 | L211: =+VLOOKUP(E211,Material!$H$2:$M$17,6,FALSE)*G211*H211*(1+Material!$K$14) -> 204.58171 | M211: =+Analisis!$J$5 -> T5.0 | N211: =+VLOOKUP(M211,Material!$A$3:$B$58,2,FALSE) -> 5000 | O211: ACERO A36 | P211: Cal 12 | Q211: =+IF(O211="ACERO A36",VLOOKUP(P211,'Velocidades Std 1500 w'!$B$2:$F$15,5,FALSE),IF(O211="INOXIDABLE",VLOOKUP(P211,'Velocidades Std 1500 w'!$B$17:$F$28,5,FALSE),IF(O211="ALUMINIO",VLOOKUP(P211,'Velocidades Std 1500 w'!$B$30:$F$38,5,FALSE)))) -> 4.3859649e-06 | R211: =+Q211*N211 -> 0.021929825 | S211: =+Q211*T211*3600 -> 84.675846 | T211: =(+H211*2+G211*2+V211*1.5)*25.4*1.05 -> 5362.8036 | U211: =+T211*R211 -> 117.60534 | V211: 50 | W211: =+IF(O211="ACERO A36",VLOOKUP(P211,'Tiempo Objeto'!$B$2:$C$12,2,FALSE),IF(O211="INOXIDABLE",VLOOKUP(P211,'Tiempo Objeto'!$B$14:$C$22,2,FALSE),IF(O211="ALUMINIO",VLOOKUP(P211,'Tiempo Objeto'!$B$24:$C$32,2,FALSE)))) -> 1.84 | X211: =+W211*V211 -> 92 | Y211: =+X211*N211/3600 -> 127.77778 | Z211: 4 | AA211: =30*Z211+Z211*$C211*1.5 -> 120 | AB211: =+Z211*Analisis!$J$6 -> 100 | AC211: 0 | AD211: =30*AC211+AC211*$C211*1.5 -> 0 | AE211: =+AD211*Analisis!$J$7 -> 0 | AF211: =+L211+U211+Y211+AB211+AE211 -> 549.96483 | AG211: =+AF211/(1-Analisis!$E$9) -> 687.45604 | AH211: =+AG211*C211 -> 0
B212: 12-D-6008-01 | C212: =IFERROR(VLOOKUP(B212,'REQ GALV'!A:B,2,0),0) -> 0 | D212: =+AG212 -> 202.45576 | E212: 10ga | F212: DECAPADO | G212: 5.16 | H212: 12.31 | I212: 0.105 | J212: 28.24 | K212: =+L212*2.2/J212 -> 4.456147 | L212: =+VLOOKUP(E212,Material!$H$2:$M$17,6,FALSE)*G212*H212*(1+Material!$K$14) -> 57.200723 | M212: =+Analisis!$J$5 -> T5.0 | N212: =+VLOOKUP(M212,Material!$A$3:$B$58,2,FALSE) -> 5000 | O212: ACERO A36 | P212: Cal 12 | Q212: =+IF(O212="ACERO A36",VLOOKUP(P212,'Velocidades Std 1500 w'!$B$2:$F$15,5,FALSE),IF(O212="INOXIDABLE",VLOOKUP(P212,'Velocidades Std 1500 w'!$B$17:$F$28,5,FALSE),IF(O212="ALUMINIO",VLOOKUP(P212,'Velocidades Std 1500 w'!$B$30:$F$38,5,FALSE)))) -> 4.3859649e-06 | R212: =+Q212*N212 -> 0.021929825 | S212: =+Q212*T212*3600 -> 21.029997 | T212: =(+H212*2+G212*2+V212*1.5)*25.4*1.05 -> 1331.8998 | U212: =+T212*R212 -> 29.208329 | V212: 10 | W212: =+IF(O212="ACERO A36",VLOOKUP(P212,'Tiempo Objeto'!$B$2:$C$12,2,FALSE),IF(O212="INOXIDABLE",VLOOKUP(P212,'Tiempo Objeto'!$B$14:$C$22,2,FALSE),IF(O212="ALUMINIO",VLOOKUP(P212,'Tiempo Objeto'!$B$24:$C$32,2,FALSE)))) -> 1.84 | X212: =+W212*V212 -> 18.4 | Y212: =+X212*N212/3600 -> 25.555556 | Z212: 2 | AA212: =30*Z212+Z212*$C212*1.5 -> 60 | AB212: =+Z212*Analisis!$J$6 -> 50 | AC212: 0 | AD212: =30*AC212+AC212*$C212*1.5 -> 0 | AE212: =+AD212*Analisis!$J$7 -> 0 | AF212: =+L212+U212+Y212+AB212+AE212 -> 161.96461 | AG212: =+AF212/(1-Analisis!$E$9) -> 202.45576 | AH212: =+AG212*C212 -> 0
B213: 12-D-6009-01 | C213: =IFERROR(VLOOKUP(B213,'REQ GALV'!A:B,2,0),0) -> 0 | D213: =+AG213 -> 202.45576 | E213: 10ga | F213: DECAPADO | G213: 5.16 | H213: 12.31 | I213: 0.105 | J213: 28.24 | K213: =+L213*2.2/J213 -> 4.456147 | L213: =+VLOOKUP(E213,Material!$H$2:$M$17,6,FALSE)*G213*H213*(1+Material!$K$14) -> 57.200723 | M213: =+Analisis!$J$5 -> T5.0 | N213: =+VLOOKUP(M213,Material!$A$3:$B$58,2,FALSE) -> 5000 | O213: ACERO A36 | P213: Cal 12 | Q213: =+IF(O213="ACERO A36",VLOOKUP(P213,'Velocidades Std 1500 w'!$B$2:$F$15,5,FALSE),IF(O213="INOXIDABLE",VLOOKUP(P213,'Velocidades Std 1500 w'!$B$17:$F$28,5,FALSE),IF(O213="ALUMINIO",VLOOKUP(P213,'Velocidades Std 1500 w'!$B$30:$F$38,5,FALSE)))) -> 4.3859649e-06 | R213: =+Q213*N213 -> 0.021929825 | S213: =+Q213*T213*3600 -> 21.029997 | T213: =(+H213*2+G213*2+V213*1.5)*25.4*1.05 -> 1331.8998 | U213: =+T213*R213 -> 29.208329 | V213: 10 | W213: =+IF(O213="ACERO A36",VLOOKUP(P213,'Tiempo Objeto'!$B$2:$C$12,2,FALSE),IF(O213="INOXIDABLE",VLOOKUP(P213,'Tiempo Objeto'!$B$14:$C$22,2,FALSE),IF(O213="ALUMINIO",VLOOKUP(P213,'Tiempo Objeto'!$B$24:$C$32,2,FALSE)))) -> 1.84 | X213: =+W213*V213 -> 18.4 | Y213: =+X213*N213/3600 -> 25.555556 | Z213: 2 | AA213: =30*Z213+Z213*$C213*1.5 -> 60 | AB213: =+Z213*Analisis!$J$6 -> 50 | AC213: 0 | AD213: =30*AC213+AC213*$C213*1.5 -> 0 | AE213: =+AD213*Analisis!$J$7 -> 0 | AF213: =+L213+U213+Y213+AB213+AE213 -> 161.96461 | AG213: =+AF213/(1-Analisis!$E$9) -> 202.45576 | AH213: =+AG213*C213 -> 0
B214: 12-D-6015-01 | C214: =IFERROR(VLOOKUP(B214,'REQ GALV'!A:B,2,0),0) -> 0 | D214: =+AG214 -> 240.70803 | E214: 10ga | F214: DECAPADO | G214: 3.51 | H214: 12.5 | I214: 0.105 | J214: 28.24 | K214: =+L214*2.2/J214 -> 3.0780019 | L214: =+VLOOKUP(E214,Material!$H$2:$M$17,6,FALSE)*G214*H214*(1+Material!$K$14) -> 39.510352 | M214: =+Analisis!$J$5 -> T5.0 | N214: =+VLOOKUP(M214,Material!$A$3:$B$58,2,FALSE) -> 5000 | O214: ACERO A36 | P214: Cal 12 | Q214: =+IF(O214="ACERO A36",VLOOKUP(P214,'Velocidades Std 1500 w'!$B$2:$F$15,5,FALSE),IF(O214="INOXIDABLE",VLOOKUP(P214,'Velocidades Std 1500 w'!$B$17:$F$28,5,FALSE),IF(O214="ALUMINIO",VLOOKUP(P214,'Velocidades Std 1500 w'!$B$30:$F$38,5,FALSE)))) -> 4.3859649e-06 | R214: =+Q214*N214 -> 0.021929825 | S214: =+Q214*T214*3600 -> 19.800369 | T214: =(+H214*2+G214*2+V214*1.5)*25.4*1.05 -> 1254.0234 | U214: =+T214*R214 -> 27.500513 | V214: 10 | W214: =+IF(O214="ACERO A36",VLOOKUP(P214,'Tiempo Objeto'!$B$2:$C$12,2,FALSE),IF(O214="INOXIDABLE",VLOOKUP(P214,'Tiempo Objeto'!$B$14:$C$22,2,FALSE),IF(O214="ALUMINIO",VLOOKUP(P214,'Tiempo Objeto'!$B$24:$C$32,2,FALSE)))) -> 1.84 | X214: =+W214*V214 -> 18.4 | Y214: =+X214*N214/3600 -> 25.555556 | Z214: 4 | AA214: =30*Z214+Z214*$C214*1.5 -> 120 | AB214: =+Z214*Analisis!$J$6 -> 100 | AC214: 0 | AD214: =30*AC214+AC214*$C214*1.5 -> 0 | AE214: =+AD214*Analisis!$J$7 -> 0 | AF214: =+L214+U214+Y214+AB214+AE214 -> 192.56642 | AG214: =+AF214/(1-Analisis!$E$9) -> 240.70803 | AH214: =+AG214*C214 -> 0
B215: 12-D-6015-02 | C215: =IFERROR(VLOOKUP(B215,'REQ GALV'!A:B,2,0),0) -> 0 | D215: =+AG215 -> 284.01368 | E215: 10ga | F215: DECAPADO | G215: 3.51 | H215: 20.5 | I215: 0.105 | J215: 28.24 | K215: =+L215*2.2/J215 -> 5.0479231 | L215: =+VLOOKUP(E215,Material!$H$2:$M$17,6,FALSE)*G215*H215*(1+Material!$K$14) -> 64.796977 | M215: =+Analisis!$J$5 -> T5.0 | N215: =+VLOOKUP(M215,Material!$A$3:$B$58,2,FALSE) -> 5000 | O215: ACERO A36 | P215: Cal 12 | Q215: =+IF(O215="ACERO A36",VLOOKUP(P215,'Velocidades Std 1500 w'!$B$2:$F$15,5,FALSE),IF(O215="INOXIDABLE",VLOOKUP(P215,'Velocidades Std 1500 w'!$B$17:$F$28,5,FALSE),IF(O215="ALUMINIO",VLOOKUP(P215,'Velocidades Std 1500 w'!$B$30:$F$38,5,FALSE)))) -> 4.3859649e-06 | R215: =+Q215*N215 -> 0.021929825 | S215: =+Q215*T215*3600 -> 26.538054 | T215: =(+H215*2+G215*2+V215*1.5)*25.4*1.05 -> 1680.7434 | U215: =+T215*R215 -> 36.858408 | V215: 10 | W215: =+IF(O215="ACERO A36",VLOOKUP(P215,'Tiempo Objeto'!$B$2:$C$12,2,FALSE),IF(O215="INOXIDABLE",VLOOKUP(P215,'Tiempo Objeto'!$B$14:$C$22,2,FALSE),IF(O215="ALUMINIO",VLOOKUP(P215,'Tiempo Objeto'!$B$24:$C$32,2,FALSE)))) -> 1.84 | X215: =+W215*V215 -> 18.4 | Y215: =+X215*N215/3600 -> 25.555556 | Z215: 4 | AA215: =30*Z215+Z215*$C215*1.5 -> 120 | AB215: =+Z215*Analisis!$J$6 -> 100 | AC215: 0 | AD215: =30*AC215+AC215*$C215*1.5 -> 0 | AE215: =+AD215*Analisis!$J$7 -> 0 | AF215: =+L215+U215+Y215+AB215+AE215 -> 227.21094 | AG215: =+AF215/(1-Analisis!$E$9) -> 284.01368 | AH215: =+AG215*C215 -> 0
B216: 12-D-6015-03 | C216: =IFERROR(VLOOKUP(B216,'REQ GALV'!A:B,2,0),0) -> 60 | D216: =+AG216 -> 316.49291 | E216: 10ga | F216: DECAPADO | G216: 3.51 | H216: 26.5 | I216: 0.105 | J216: 28.24 | K216: =+L216*2.2/J216 -> 6.525364 | L216: =+VLOOKUP(E216,Material!$H$2:$M$17,6,FALSE)*G216*H216*(1+Material!$K$14) -> 83.761945 | M216: =+Analisis!$J$5 -> T5.0 | N216: =+VLOOKUP(M216,Material!$A$3:$B$58,2,FALSE) -> 5000 | O216: ACERO A36 | P216: Cal 12 | Q216: =+IF(O216="ACERO A36",VLOOKUP(P216,'Velocidades Std 1500 w'!$B$2:$F$15,5,FALSE),IF(O216="INOXIDABLE",VLOOKUP(P216,'Velocidades Std 1500 w'!$B$17:$F$28,5,FALSE),IF(O216="ALUMINIO",VLOOKUP(P216,'Velocidades Std 1500 w'!$B$30:$F$38,5,FALSE)))) -> 4.3859649e-06 | R216: =+Q216*N216 -> 0.021929825 | S216: =+Q216*T216*3600 -> 31.591317 | T216: =(+H216*2+G216*2+V216*1.5)*25.4*1.05 -> 2000.7834 | U216: =+T216*R216 -> 43.876829 | V216: 10 | W216: =+IF(O216="ACERO A36",VLOOKUP(P216,'Tiempo Objeto'!$B$2:$C$12,2,FALSE),IF(O216="INOXIDABLE",VLOOKUP(P216,'Tiempo Objeto'!$B$14:$C$22,2,FALSE),IF(O216="ALUMINIO",VLOOKUP(P216,'Tiempo Objeto'!$B$24:$C$32,2,FALSE)))) -> 1.84 | X216: =+W216*V216 -> 18.4 | Y216: =+X216*N216/3600 -> 25.555556 | Z216: 4 | AA216: =30*Z216+Z216*$C216*1.5 -> 480 | AB216: =+Z216*Analisis!$J$6 -> 100 | AC216: 0 | AD216: =30*AC216+AC216*$C216*1.5 -> 0 | AE216: =+AD216*Analisis!$J$7 -> 0 | AF216: =+L216+U216+Y216+AB216+AE216 -> 253.19433 | AG216: =+AF216/(1-Analisis!$E$9) -> 316.49291 | AH216: =+AG216*C216 -> 18989.575 | AI216: =+L216*C216 -> 5025.7167
B217: 12-D-6015-04 | C217: =IFERROR(VLOOKUP(B217,'REQ GALV'!A:B,2,0),0) -> 210 | D217: =+AG217 -> 348.97215 | E217: 10ga | F217: DECAPADO | G217: 3.51 | H217: 32.5 | I217: 0.105 | J217: 28.24 | K217: =+L217*2.2/J217 -> 8.0028049 | L217: =+VLOOKUP(E217,Material!$H$2:$M$17,6,FALSE)*G217*H217*(1+Material!$K$14) -> 102.72691 | M217: =+Analisis!$J$5 -> T5.0 | N217: =+VLOOKUP(M217,Material!$A$3:$B$58,2,FALSE) -> 5000 | O217: ACERO A36 | P217: Cal 12 | Q217: =+IF(O217="ACERO A36",VLOOKUP(P217,'Velocidades Std 1500 w'!$B$2:$F$15,5,FALSE),IF(O217="INOXIDABLE",VLOOKUP(P217,'Velocidades Std 1500 w'!$B$17:$F$28,5,FALSE),IF(O217="ALUMINIO",VLOOKUP(P217,'Velocidades Std 1500 w'!$B$30:$F$38,5,FALSE)))) -> 4.3859649e-06 | R217: =+Q217*N217 -> 0.021929825 | S217: =+Q217*T217*3600 -> 36.64458 | T217: =(+H217*2+G217*2+V217*1.5)*25.4*1.05 -> 2320.8234 | U217: =+T217*R217 -> 50.89525 | V217: 10 | W217: =+IF(O217="ACERO A36",VLOOKUP(P217,'Tiempo Objeto'!$B$2:$C$12,2,FALSE),IF(O217="INOXIDABLE",VLOOKUP(P217,'Tiempo Objeto'!$B$14:$C$22,2,FALSE),IF(O217="ALUMINIO",VLOOKUP(P217,'Tiempo Objeto'!$B$24:$C$32,2,FALSE)))) -> 1.84 | X217: =+W217*V217 -> 18.4 | Y217: =+X217*N217/3600 -> 25.555556 | Z217: 4 | AA217: =30*Z217+Z217*$C217*1.5 -> 1380 | AB217: =+Z217*Analisis!$J$6 -> 100 | AC217: 0 | AD217: =30*AC217+AC217*$C217*1.5 -> 0 | AE217: =+AD217*Analisis!$J$7 -> 0 | AF217: =+L217+U217+Y217+AB217+AE217 -> 279.17772 | AG217: =+AF217/(1-Analisis!$E$9) -> 348.97215 | AH217: =+AG217*C217 -> 73284.151 | AI217: =+L217*C217 -> 21572.652
...

Sheet Tiempo Objeto
A1: Material | B1: Calibre | C1: ACERO A36
A2: ACERO A36 | B2: 3/8´´ | C2: 8.35 | O2: Cal 10
A3: ACERO A36 | B3: 5/16´´ | C3: 4.41
A4: ACERO A36 | B4: 1/4´´ | C4: 3.12
A5: ACERO A36 | B5: 3/16´´ | C5: 2.46
A6: ACERO A36 | B6: Cal 10 | C6: 2.14
A7: ACERO A36 | B7: 1/8" | C7: 2.02
A8: ACERO A36 | B8: Cal 12 | C8: 1.84
A9: ACERO A36 | B9: Cal 14 | C9: 0.94
A10: ACERO A36 | B10: Cal 16 | C10: 0.74
A11: ACERO A36 | B11: Cal 18 | C11: 0.35
A12: ACERO A36 | B12: Cal 20 | C12: 0.25
A14: INOXIDABLE | B14: 1/4´´ | C14: 2.58
A15: INOXIDABLE | B15: 3/16´´ | C15: 2.48
... A25: ALUMINIO | B25: 3/16´´ | C25: 1.06
A26: ALUMINIO | B26: 1/4´´ | C26: =+C24*2 -> 2.12
A27: ALUMINIO
A28: ALUMINIO | B28: Cal 12 | C28: 1.06
A29: ALUMINIO | B29: Cal 14 | C29: 1.06
A30: ALUMINIO | B30: Cal 16 | C30: 1.06
A31: ALUMINIO | B31: Cal 18 | C31: 1.06
A32: ALUMINIO | B32: Cal 20 | C32: 1.06

Sheet REQ. PINTADO
B1: PARTE | C1: CANTIDAD | D1: MATERIAL | E1: COSTO UNITARIO | K1: COSTO TOTAL | O1: COSTO TOTAL | P1: TOTAL (venta)
E2: MAT | F2: LASER | G2: DOBLEZ | H2: PINTURA | I2: COSTO PIEZA | J2: Venta | K2: MAT | L2: LASER | M2: DOBLEZ | N2: PINTURA
A3: 1 | B3: 12-6010-01 | C3: 48 | D3: =+VLOOKUP(B3,'COT. PITADO'!B:F,5,FALSE) -> 16gacr | E3: =IFERROR(+VLOOKUP(B3,'COT. PITADO'!B:AG,12,0),0) -> 9.7323389 | F3: =IFERROR(+VLOOKUP(B3,'COT. PITADO'!B:AG,21,0)+VLOOKUP(B3,'COT. PITADO'!B:AG,25,0),0) -> 6.7696432 | G3: =IFERROR(+VLOOKUP(B3,'COT. PITADO'!B:AG,27,0)+VLOOKUP(B3,'COT. PITADO'!B:AG,30,0),0) -> 50 | H3: =IFERROR(+VLOOKUP(B3,'COT. PITADO'!B:AG,22,0),0) -> 3 | I3: =SUM(E3:H3) -> 69.501982 | J3: =+I3/(1-Analisis!$E$9) -> 86.877478 | K3: =+E3*$C3 -> 467.15227 | L3: =+F3*$C3 -> 324.94287 | M3: =+G3*$C3 -> 2400 | N3: =+H3*$C3 -> 144 | O3: =SUM(K3:N3) -> 3336.0951 | P3: =+O3/(1-Analisis!$E$9) -> 4170.1189
A4: 2 | B4: 11-D-3402-01 | C4: 48 | D4: =+VLOOKUP(B4,'COT. PITADO'!B:F,5,FALSE) -> 16gacr | E4: =IFERROR(+VLOOKUP(B4,'COT. PITADO'!B:AG,12,0),0) -> 31.134872 | F4: =IFERROR(+VLOOKUP(B4,'COT. PITADO'!B:AG,21,0)+VLOOKUP(B4,'COT. PITADO'!B:AG,25,0),0) -> 13.241127 | G4: =IFERROR(+VLOOKUP(B4,'COT. PITADO'!B:AG,27,0)+VLOOKUP(B4,'COT. PITADO'!B:AG,30,0),0) -> 50 | H4: =IFERROR(+VLOOKUP(B4,'COT. PITADO'!B:AG,22,0),0) -> 13 | I4: =SUM(E4:H4) -> 107.376 | J4: =+I4/(1-Analisis!$E$9) -> 134.22 | K4: =+E4*$C4 -> 1494.4738 | L4: =+F4*$C4 -> 635.57409 | M4: =+G4*$C4 -> 2400 | N4: =+H4*$C4 -> 624 | O4: =SUM(K4:N4) -> 5154.0479 | P4: =+O4/(1-Analisis!$E$9) -> 6442.5599
A5: 3 | B5: 17-D-6043-02 | C5: 96 | D5: =+VLOOKUP(B5,'COT. PITADO'!B:F,5,FALSE) -> 16gacr | E5: =IFERROR(+VLOOKUP(B5,'COT. PITADO'!B:AG,12,0),0) -> 31.177935 | F5: =IFERROR(+VLOOKUP(B5,'COT. PITADO'!B:AG,21,0)+VLOOKUP(B5,'COT. PITADO'!B:AG,25,0),0) -> 10.088975 | G5: =IFERROR(+VLOOKUP(B5,'COT. PITADO'!B:AG,27,0)+VLOOKUP(B5,'COT. PITADO'!B:AG,30,0),0) -> 50 | H5: =IFERROR(+VLOOKUP(B5,'COT. PITADO'!B:AG,22,0),0) -> 7 | I5: =SUM(E5:H5) -> 98.26691 | J5: =+I5/(1-Analisis!$E$9) -> 122.83364 | K5: =+E5*$C5 -> 2993.0818 | L5: =+F5*$C5 -> 968.54161 | M5: =+G5*$C5 -> 4800 | N5: =+H5*$C5 -> 672 | O5: =SUM(K5:N5) -> 9433.6234 | P5: =+O5/(1-Analisis!$E$9) -> 11792.029
A6: 4 | B6: 17-D-6047-01 | C6: 48 | D6: =+VLOOKUP(B6,'COT. PITADO'!B:F,5,FALSE) -> 16gacr | E6: =IFERROR(+VLOOKUP(B6,'COT. PITADO'!B:AG,12,0),0) -> 7.22106 | F6: =IFERROR(+VLOOKUP(B6,'COT. PITADO'!B:AG,21,0)+VLOOKUP(B6,'COT. PITADO'!B:AG,25,0),0) -> 4.3371047 | G6: =IFERROR(+VLOOKUP(B6,'COT. PITADO'!B:AG,27,0)+VLOOKUP(B6,'COT. PITADO'!B:AG,30,0),0) -> 50 | H6: =IFERROR(+VLOOKUP(B6,'COT. PITADO'!B:AG,22,0),0) -> 3 | I6: =SUM(E6:H6) -> 64.558165 | J6: =+I6/(1-Analisis!$E$9) -> 80.697706 | K6: =+E6*$C6 -> 346.61088 | L6: =+F6*$C6 -> 208.18103 | M6: =+G6*$C6 -> 2400 | N6: =+H6*$C6 -> 144 | O6: =SUM(K6:N6) -> 3098.7919 | P6: =+O6/(1-Analisis!$E$9) -> 3873.4899
A7: 5 | B7: 12-6355-03 | C7: 48 | D7: =+VLOOKUP(B7,'COT. PITADO'!B:F,5,FALSE) -> 16gacr | E7: =IFERROR(+VLOOKUP(B7,'COT. PITADO'!B:AG,12,0),0) -> 63.54458 | F7: =IFERROR(+VLOOKUP(B7,'COT. PITADO'!B:AG,21,0)+VLOOKUP(B7,'COT. PITADO'!B:AG,25,0),0) -> 12.392741 | G7: =IFERROR(+VLOOKUP(B7,'COT. PITADO'!B:AG,27,0)+VLOOKUP(B7,'COT. PITADO'!B:AG,30,0),0) -> 75 | H7: =IFERROR(+VLOOKUP(B7,'COT. PITADO'!B:AG,22,0),0) -> 8 | I7: =SUM(E7:H7) -> 158.93732 | J7: =+I7/(1-Analisis!$E$9) -> 198.67165 | K7: =+E7*$C7 -> 3050.1398 | L7: =+F7*$C7 -> 594.85156 | M7: =+G7*$C7 -> 3600 | N7: =+H7*$C7 -> 384 | O7: =SUM(K7:N7) -> 7628.9914 | P7: =+O7/(1-Analisis!$E$9) -> 9536.2392
A8: 6 | B8: PP21340-01 | C8: 48 | D8: =+VLOOKUP(B8,'COT. PITADO'!B:F,5,FALSE) -> 16gacr | E8: =IFERROR(+VLOOKUP(B8,'COT. PITADO'!B:AG,12,0),0) -> 43.711562 | F8: =IFERROR(+VLOOKUP(B8,'COT. PITADO'!B:AG,21,0)+VLOOKUP(B8,'COT. PITADO'!B:AG,25,0),0) -> 11.170366 | G8: =IFERROR(+VLOOKUP(B8,'COT. PITADO'!B:AG,27,0)+VLOOKUP(B8,'COT. PITADO'!B:AG,30,0),0) -> 75 | H8: =IFERROR(+VLOOKUP(B8,'COT. PITADO'!B:AG,22,0),0) -> 8 | I8: =SUM(E8:H8) -> 137.88193 | J8: =+I8/(1-Analisis!$E$9) -> 172.35241 | K8: =+E8*$C8 -> 2098.155 | L8: =+F8*$C8 -> 536.17756 | M8: =+G8*$C8 -> 3600 | N8: =+H8*$C8 -> 384 | O8: =SUM(K8:N8) -> 6618.3326 | P8: =+O8/(1-Analisis!$E$9) -> 8272.9157
A9: 7 | B9: PP22121-01 | C9: 48 | D9: =+VLOOKUP(B9,'COT. PITADO'!B:F,5,FALSE) -> 16gacr | E9: =IFERROR(+VLOOKUP(B9,'COT. PITADO'!B:AG,12,0),0) -> 112.00802 | F9: =IFERROR(+VLOOKUP(B9,'COT. PITADO'!B:AG,21,0)+VLOOKUP(B9,'COT. PITADO'!B:AG,25,0),0) -> 15.724718 | G9: =IFERROR(+VLOOKUP(B9,'COT. PITADO'!B:AG,27,0)+VLOOKUP(B9,'COT. PITADO'!B:AG,30,0),0) -> 50 | H9: =IFERROR(+VLOOKUP(B9,'COT. PITADO'!B:AG,22,0),0) -> 9 | I9: =SUM(E9:H9) -> 186.73274 | J9: =+I9/(1-Analisis!$E$9) -> 233.41593 | K9: =+E9*$C9 -> 5376.3851 | L9: =+F9*$C9 -> 754.78646 | M9: =+G9*$C9 -> 2400 | N9: =+H9*$C9 -> 432 | O9: =SUM(K9:N9) -> 8963.1716 | P9: =+O9/(1-Analisis!$E$9) -> 11203.965
A10: 8 | B10: 11-D-3408-01 | C10: 96 | D10: =+VLOOKUP(B10,'COT. PITADO'!B:F,5,FALSE) -> 16gacr | E10: =IFERROR(+VLOOKUP(B10,'COT. PITADO'!B:AG,12,0),0) -> 1.1196496 | F10: =IFERROR(+VLOOKUP(B10,'COT. PITADO'!B:AG,21,0)+VLOOKUP(B10,'COT. PITADO'!B:AG,25,0),0) -> 2.1432429 | G10: =IFERROR(+VLOOKUP(B10,'COT. PITADO'!B:AG,27,0)+VLOOKUP(B10,'COT. PITADO'!B:AG,30,0),0) -> 50 | H10: =IFERROR(+VLOOKUP(B10,'COT. PITADO'!B:AG,22,0),0) -> 2 | I10: =SUM(E10:H10) -> 55.262892 | J10: =+I10/(1-Analisis!$E$9) -> 69.078616 | K10: =+E10*$C10 -> 107.48636 | L10: =+F10*$C10 -> 205.75132 | M10: =+G10*$C10 -> 4800 | N10: =+H10*$C10 -> 192 | O10: =SUM(K10:N10) -> 5305.2377 | P10: =+O10/(1-Analisis!$E$9) -> 6631.5471
A11: 9 | B11: PP21341-12 | C11: 48 | D11: =+VLOOKUP(B11,'COT. PITADO'!B:F,5,FALSE) -> 16gacr | E11: =IFERROR(+VLOOKUP(B11,'COT. PITADO'!B:AG,12,0),0) -> 74.327508 | F11: =IFERROR(+VLOOKUP(B11,'COT. PITADO'!B:AG,21,0)+VLOOKUP(B11,'COT. PITADO'!B:AG,25,0),0) -> 17.793824 | G11: =IFERROR(+VLOOKUP(B11,'COT. PITADO'!B:AG,27,0)+VLOOKUP(B11,'COT. PITADO'!B:AG,30,0),0) -> 50 | H11: =IFERROR(+VLOOKUP(B11,'COT. PITADO'!B:AG,22,0),0) -> 17 | I11: =SUM(E11:H11) -> 159.12133 | J11: =+I11/(1-Analisis!$E$9) -> 198.90167 | K11: =+E11*$C11 -> 3567.7204 | L11: =+F11*$C11 -> 854.10356 | M11: =+G11*$C11 -> 2400 | N11: =+H11*$C11 -> 816 | O11: =SUM(K11:N11) -> 7637.824 | P11: =+O11/(1-Analisis!$E$9) -> 9547.2799
A12: 10 | B12: 12-6010-09 | C12: 48 | D12: =+VLOOKUP(B12,'COT. PITADO'!B:F,5,FALSE) -> 16gacr | E12: =IFERROR(+VLOOKUP(B12,'COT. PITADO'!B:AG,12,0),0) -> 31.264062 | F12: =IFERROR(+VLOOKUP(B12,'COT. PITADO'!B:AG,21,0)+VLOOKUP(B12,'COT. PITADO'!B:AG,25,0),0) -> 7.990797 | G12: =IFERROR(+VLOOKUP(B12,'COT. PITADO'!B:AG,27,0)+VLOOKUP(B12,'COT. PITADO'!B:AG,30,0),0) -> 50 | H12: =IFERROR(+VLOOKUP(B12,'COT. PITADO'!B:AG,22,0),0) -> 3 | I12: =SUM(E12:H12) -> 92.254859 | J12: =+I12/(1-Analisis!$E$9) -> 115.31857 | K12: =+E12*$C12 -> 1500.675 | L12: =+F12*$C12 -> 383.55826 | M12: =+G12*$C12 -> 2400 | N12: =+H12*$C12 -> 144 | O12: =SUM(K12:N12) -> 4428.2332 | P12: =+O12/(1-Analisis!$E$9) -> 5535.2915
A13: 11 | B13: PP22124-01 | C13: 48 | D13: =+VLOOKUP(B13,'COT. PITADO'!B:F,5,FALSE) -> 16gacr | E13: =IFERROR(+VLOOKUP(B13,'COT. PITADO'!B:AG,12,0),0) -> 93.248691 | F13: =IFERROR(+VLOOKUP(B13,'COT. PITADO'!B:AG,21,0)+VLOOKUP(B13,'COT. PITADO'!B:AG,25,0),0) -> 18.429376 | G13: =IFERROR(+VLOOKUP(B13,'COT. PITADO'!B:AG,27,0)+VLOOKUP(B13,'COT. PITADO'!B:AG,30,0),0) -> 75 | H13: =IFERROR(+VLOOKUP(B13,'COT. PITADO'!B:AG,22,0),0) -> 16 | I13: =SUM(E13:H13) -> 202.67807 | J13: =+I13/(1-Analisis!$E$9) -> 253.34758 | K13: =+E13*$C13 -> 4475.9372 | L13: =+F13*$C13 -> 884.61003 | M13: =+G13*$C13 -> 3600 | N13: =+H13*$C13 -> 768 | O13: =SUM(K13:N13) -> 9728.5472 | P13: =+O13/(1-Analisis!$E$9) -> 12160.684
A14: 12 | B14: 11-D-3409-02 | C14: 144 | D14: =+VLOOKUP(B14,'COT. PITADO'!B:F,5,FALSE) -> 12gacr | E14: =IFERROR(+VLOOKUP(B14,'COT. PITADO'!B:AG,12,0),0) -> 5.3547655 | F14: =IFERROR(+VLOOKUP(B14,'COT. PITADO'!B:AG,21,0)+VLOOKUP(B14,'COT. PITADO'!B:AG,25,0),0) -> 17.910088 | G14: =IFERROR(+VLOOKUP(B14,'COT. PITADO'!B:AG,27,0)+VLOOKUP(B14,'COT. PITADO'!B:AG,30,0),0) -> 75 | H14: =IFERROR(+VLOOKUP(B14,'COT. PITADO'!B:AG,22,0),0) -> 5 | I14: =SUM(E14:H14) -> 103.26485 | J14: =+I14/(1-Analisis!$E$9) -> 129.08107 | K14: =+E14*$C14 -> 771.08624 | L14: =+F14*$C14 -> 2579.0527 | M14: =+G14*$C14 -> 10800 | N14: =+H14*$C14 -> 720 | O14: =SUM(K14:N14) -> 14870.139 | P14: =+O14/(1-Analisis!$E$9) -> 18587.674
C15: =SUM(C3:C14) -> 768 | K15: =SUM(K3:K14) -> 26248.904 | L15: =SUM(L3:L14) -> 8930.131 | M15: =SUM(M3:M14) -> 45600 | N15: =SUM(N3:N14) -> 5424 | O15: =SUM(K15:N15) -> 86203.035 | P15: =SUM(P3:P14) -> 107753.79 | R15: 1021242.7 | S15: =+R15-P15 -> 913488.92 | T15: BAJA MATERIA PRIMA
K16: =+K15/$O$15 -> 0.30450093 | L16: =+L15/$O$15 -> 0.10359416 | M16: =+M15/$O$15 -> 0.5289837 | N16: =+N15/$O$15 -> 0.062921219 | O16: =+O15/$O$15 -> 1
L17: P.U. | M17: HOJAS | N17: Pronest | O17: PPAP | P17: TOTAL
H18: 16gacr | J18: =+Material!K7 -> 981.58073 | K18: =+SUMIF($D$3:$D$14,H18,$K$3:$K$14) -> 25477.818 | L18: =+VLOOKUP(H18,Material!H2:K12,4,FALSE) -> 981.58073 | M18: =+K18/L18 -> 25.955906 | N18: 0 | O18: 1 | P18: =+N18+O18 -> 1
H19: 14gacr | J19: 0 | K19: =+SUMIF($D$3:$D$14,H19,$K$3:$K$14) -> 0 | L19: =+VLOOKUP(H19,Material!H3:K13,4,FALSE) -> 1800 | M19: =+K19/L19 -> 0 | N19: 0 | O19: 0 | P19: =+N19+O19 -> 0
H20: 12gacr | J20: =+Material!K5 -> 1625.6397 | K20: =+SUMIF($D$3:$D$14,H20,$K$3:$K$14) -> 771.08624 | L20: =+VLOOKUP(H20,Material!H4:K14,4,FALSE) -> 1625.6397 | M20: =+K20/L20 -> 0.47432788 | N20: 0 | O20: 2 | P20: =+N20+O20 -> 2
H21: 10gacr | K21: =+SUMIF($D$3:$D$14,H21,$K$3:$K$14) -> 0 | L21: =+VLOOKUP(H21,Material!H5:K15,4,FALSE) -> 3000 | M21: =+K21/L21 -> 0 | O21: 0 | P21: =+N21+O21 -> 0
H22: Material | K22: =SUM(K18:K21) -> 26248.904 | M22: =SUM(M18:M21) -> 26.430234 | N22: =SUM(N18:N21) -> 0 | O22: =SUM(O18:O21) -> 3 | P22: =SUM(P18:P21) -> 3
M30: USD | N30: TC | O30: MXN
M31: 56.39 | N31: =+Material!R1 -> 17.407 | O31: =+N31*M31 -> 981.58073
M32: 93.59 | N32: =+N31 -> 17.407 | O32: =+N32*M32 -> 1629.1211

Sheet COT. PITADO
A1: No. | B1: Numero Parte | C1: Descripción | D1: Cantidad | E1: P.F. | F1: Material | G1: Acabado | H1: Ancho (in) | I1: Longitud (in) | J1: Espesor (in) | K1: Peso (lb) | L1: $ / Kg | M1: $ Material | N1: TARIFA | O1: $/Hr | P1: Material | Q1: Cal. Corte | R1: Velocidad | S1: Tarifa $/mm | T1: Tiempo corte laser | U1: Long corte (mm) | V1: $ Corte | W1: Objetos | X1: Tiempo por Objeto | Y1: Total Tiempo x Objeto | Z1: $ Objetos | AA1: Golpes | AB1: $ Golpes | AC1: Punzonado | AD1: Tiempo (min) | AE1: $ Punz. | AF1: Area a pintar | AG1: Pintura | AH1: COSTO | AI1: P.V. | AJ1: P.F. COMISION VENTA 7% | AK1: VENTA TOTAL
A2: 1 | B2: 11-A-9423-01 | D2: =IFERROR(VLOOKUP(B2,'REQ. PINTADO'!B:C,2,0),0) -> 0 | E2: =+AJ2 -> 451.51868 | F2: 14ga | G2: DECAPADO | H2: 8.43 | I2: 26.14 | J2: 0.105 | K2: 6.72 | L2: =+M2*2.2/K2 -> 37.479884 | M2: =+VLOOKUP(F2,Material!$H$2:$M$17,6,FALSE)*H2*I2*(1+Material!$K$14) -> 114.48401 | N2: =+Analisis!J5 -> T5.0 | O2: =+VLOOKUP(N2,[3]Material!$A$3:$B$58,2,FALSE) -> 5000 | P2: ACERO A36 | Q2: =+VLOOKUP(F2,[3]Material!$C$2:$E$12,2,FALSE) -> Cal 14 | R2: =+IF(P2="ACERO A36",VLOOKUP(Q2,'[3]Velocidades Std 1500 w'!$B$2:$F$15,5,FALSE),IF(P2="INOXIDABLE",VLOOKUP(Q2,'[3]Velocidades Std 1500 w'!$B$17:$F$28,5,FALSE),IF(P2="ALUMINIO",VLOOKUP(Q2,'[3]Velocidades Std 1500 w'!$B$30:$F$38,5,FALSE)))) -> 2.0080321e-06 | S2: =+R2*O2 -> 0.010040161 | T2: =+R2*U2*3600 -> 18.535329 | U2: =(+I2*2+H2*2+W2*1.5)*25.4*1.05 -> 2564.0538 | V2: =+U2*S2 -> 25.743512 | W2: 18 | X2: =+IF(P2="ACERO A36",VLOOKUP(Q2,'[3]Tiempo Objeto'!$B$2:$C$12,2,FALSE),IF(P2="INOXIDABLE",VLOOKUP(Q2,'[3]Tiempo Objeto'!$B$14:$C$22,2,FALSE),IF(P2="ALUMINIO",VLOOKUP(Q2,'[3]Tiempo Objeto'!$B$24:$C$32,2,FALSE)))) -> 0.31333333 | Y2: =+X2*W2 -> 5.64 | Z2: =+Y2*O2/3600 -> 7.8333333 | AA2: 6 | AB2: =+AA2*Analisis!$J$6 -> 150 | AC2: 0 | AD2: =30*AC2+AC2*$D2*1.5 -> 0 | AE2: =+AC2*Analisis!$J$7 -> 0 | AF2: =+H2*0.0254*I2*0.0254*2*(1+[3]Analisis!$G$2) -> 0.35541897 | AG2: =+AF2*Analisis!$J$8 -> 37.869045 | AH2: =+AE2+AB2+Z2+V2+M2+AG2 -> 335.9299 | AI2: =+AH2/(1-Analisis!G9) -> 419.91238 | AJ2: =+AI2/(1-0.07) -> 451.51868 | AK2: =+AJ2*D2 -> 0 | AL2: =+VLOOKUP(B2,#REF!,2,FALSE) -> #REF! | AM2: =+AL2-E2 -> #REF! | AN2: =+AM2/AL2 -> #REF!
A3: 2 | B3: 11-A-9423-02 | D3: =IFERROR(VLOOKUP(B3,'REQ. PINTADO'!B:C,2,0),0) -> 0 | E3: =+AJ3 -> 349.43516 | F3: 12gacr | G3: DECAPADO | H3: 8.43 | I3: 36.14 | J3: 0.105 | K3: 9.29 | L3: =+M3*2.2/K3 -> 27.081714 | M3: =+VLOOKUP(F3,Material!$H$2:$M$17,6,FALSE)*H3*I3*(1+Material!$K$14) -> 114.35869 | N3: =+N2 -> T5.0 | O3: =+VLOOKUP(N3,[3]Material!$A$3:$B$58,2,FALSE) -> 5000 | P3: ACERO A36 | Q3: =+VLOOKUP(F3,[3]Material!$C$2:$E$12,2,FALSE) -> Cal 12 | R3: =+IF(P3="ACERO A36",VLOOKUP(Q3,'[3]Velocidades Std 1500 w'!$B$2:$F$15,5,FALSE),IF(P3="INOXIDABLE",VLOOKUP(Q3,'[3]Velocidades Std 1500 w'!$B$17:$F$28,5,FALSE),IF(P3="ALUMINIO",VLOOKUP(Q3,'[3]Velocidades Std 1500 w'!$B$30:$F$38,5,FALSE)))) -> 4.3859649e-06 | S3: =+R3*O3 -> 0.021929825 | T3: =+R3*U3*3600 -> 48.907165 | U3: =(+I3*2+H3*2+W3*1.5)*25.4*1.05 -> 3097.4538 | V3: =+U3*S3 -> 67.926618 | W3: 18 | X3: =+IF(P3="ACERO A36",VLOOKUP(Q3,'[3]Tiempo Objeto'!$B$2:$C$12,2,FALSE),IF(P3="INOXIDABLE",VLOOKUP(Q3,'[3]Tiempo Objeto'!$B$14:$C$22,2,FALSE),IF(P3="ALUMINIO",VLOOKUP(Q3,'[3]Tiempo Objeto'!$B$24:$C$32,2,FALSE)))) -> 0.61333333 | Y3: =+X3*W3 -> 11.04 | Z3: =+Y3*O3/3600 -> 15.333333 | AA3: 3 | AB3: =+AA3*Analisis!$J$6 -> 75 | AC3: 0 | AD3: =30*AC3+AC3*$D3*1.5 -> 0 | AE3: =+AC3*Analisis!$J$7 -> 0 | AF3: =+H3*0.0254*I3*0.0254*2*(1+[3]Analisis!$G$2) -> 0.49138644 | AG3: =+AF3*Analisis!$J$8 -> 52.356055 | AH3: =+AE3+AB3+Z3+V3+M3+AG3 -> 324.9747 | AI3: =+AH3/(1-Analisis!G10) -> 324.9747 | AJ3: =+AI3/(1-0.07) -> 349.43516 | AK3: =+AJ3*D3 -> 0 | AL3: =+VLOOKUP(B3,#REF!,2,FALSE) -> #REF! | AM3: =+AL3-E3 -> #REF! | AN3: =+AM3/AL3 -> #REF!
A4: 3 | B4: 11-A-9424-01 | D4: =IFERROR(VLOOKUP(B4,'REQ. PINTADO'!B:C,2,0),0) -> 0 | E4: =+AJ4 -> 440.5566 | F4: 12gacr | G4: DECAPADO | H4: 12.9 | I4: 20.5 | J4: 0.105 | K4: 8.07 | L4: =+M4*2.2/K4 -> 27.061146 | M4: =+VLOOKUP(F4,Material!$H$2:$M$17,6,FALSE)*H4*I4*(1+Material!$K$14) -> 99.265203 | N4: =+N3 -> T5.0 | O4: =+VLOOKUP(N4,[3]Material!$A$3:$B$58,2,FALSE) -> 5000 | P4: ACERO A36 | Q4: =+VLOOKUP(F4,[3]Material!$C$2:$E$12,2,FALSE) -> Cal 12 | R4: =+IF(P4="ACERO A36",VLOOKUP(Q4,'[3]Velocidades Std 1500 w'!$B$2:$F$15,5,FALSE),IF(P4="INOXIDABLE",VLOOKUP(Q4,'[3]Velocidades Std 1500 w'!$B$17:$F$28,5,FALSE),IF(P4="ALUMINIO",VLOOKUP(Q4,'[3]Velocidades Std 1500 w'!$B$30:$F$38,5,FALSE)))) -> 4.3859649e-06 | S4: =+R4*O4 -> 0.021929825 | T4: =+R4*U4*3600 -> 37.6047 | U4: =(+I4*2+H4*2+W4*1.5)*25.4*1.05 -> 2381.631 | V4: =+U4*S4 -> 52.22875 | W4: 15 | X4: =+IF(P4="ACERO A36",VLOOKUP(Q4,'[3]Tiempo Objeto'!$B$2:$C$12,2,FALSE),IF(P4="INOXIDABLE",VLOOKUP(Q4,'[3]Tiempo Objeto'!$B$14:$C$22,2,FALSE),IF(P4="ALUMINIO",VLOOKUP(Q4,'[3]Tiempo Objeto'!$B$24:$C$32,2,FALSE)))) -> 0.61333333 | Y4: =+X4*W4 -> 9.2 | Z4: =+Y4*O4/3600 -> 12.777778 | AA4: 8 | AB4: =+AA4*Analisis!$J$6 -> 200 | AC4: 0 | AD4: =30*AC4+AC4*$D4*1.5 -> 0 | AE4: =+AC4*Analisis!$J$7 -> 0 | AF4: =+H4*0.0254*I4*0.0254*2*(1+[3]Analisis!$G$2) -> 0.4265314 | AG4: =+AF4*Analisis!$J$8 -> 45.445906 | AH4: =+AE4+AB4+Z4+V4+M4+AG4 -> 409.71764 | AI4: =+AH4/(1-Analisis!G11) -> 409.71764 | AJ4: =+AI4/(1-0.07) -> 440.5566 | AK4: =+AJ4*D4 -> 0 | AL4: =+VLOOKUP(B4,#REF!,2,FALSE) -> #REF! | AM4: =+AL4-E4 -> #REF! | AN4: =+AM4/AL4 -> #REF!
A5: 4 | B5: 11-A-9424-02 | D5: =IFERROR(VLOOKUP(B5,'REQ. PINTADO'!B:C,2,0),0) -> 0 | E5: =+AJ5 -> 367.74816 | F5: 12gacr | G5: DECAPADO | H5: 12.9 | I5: 30.5 | J5: 0.105 | K5: 12 | L5: =+M5*2.2/K5 -> 27.075996 | M5: =+VLOOKUP(F5,Material!$H$2:$M$17,6,FALSE)*H5*I5*(1+Material!$K$14) -> 147.68725 | N5: =+N4 -> T5.0 | O5: =+VLOOKUP(N5,[3]Material!$A$3:$B$58,2,FALSE) -> 5000 | P5: ACERO A36 | Q5: =+VLOOKUP(F5,[3]Material!$C$2:$E$12,2,FALSE) -> Cal 12 | R5: =+IF(P5="ACERO A36",VLOOKUP(Q5,'[3]Velocidades Std 1500 w'!$B$2:$F$15,5,FALSE),IF(P5="INOXIDABLE",VLOOKUP(Q5,'[3]Velocidades Std 1500 w'!$B$17:$F$28,5,FALSE),IF(P5="ALUMINIO",VLOOKUP(Q5,'[3]Velocidades Std 1500 w'!$B$30:$F$38,5,FALSE)))) -> 4.3859649e-06 | S5: =+R5*O5 -> 0.021929825 | T5: =+R5*U5*3600 -> 46.026805 | U5: =(+I5*2+H5*2+W5*1.5)*25.4*1.05 -> 2915.031 | V5: =+U5*S5 -> 63.926118 | W5: 15 | X5: =+IF(P5="ACERO A36",VLOOKUP(Q5,'[3]Tiempo Objeto'!$B$2:$C$12,2,FALSE),IF(P5="INOXIDABLE",VLOOKUP(Q5,'[3]Tiempo Objeto'!$B$14:$C$22,2,FALSE),IF(P5="ALUMINIO",VLOOKUP(Q5,'[3]Tiempo Objeto'!$B$24:$C$32,2,FALSE)))) -> 0.61333333 | Y5: =+X5*W5 -> 9.2 | Z5: =+Y5*O5/3600 -> 12.777778 | AA5: 2 | AB5: =+AA5*Analisis!$J$6 -> 50 | AC5: 0 | AD5: =30*AC5+AC5*$D5*1.5 -> 0 | AE5: =+AC5*Analisis!$J$7 -> 0 | AF5: =+H5*0.0254*I5*0.0254*2*(1+[3]Analisis!$G$2) -> 0.6345955 | AG5: =+AF5*Analisis!$J$8 -> 67.61464 | AH5: =+AE5+AB5+Z5+V5+M5+AG5 -> 342.00579 | AI5: =+AH5/(1-Analisis!G12) -> 342.00579 | AJ5: =+AI5/(1-0.07) -> 367.74816 | AK5: =+AJ5*D5 -> 0 | AL5: =+VLOOKUP(B5,#REF!,2,FALSE) -> #REF! | AM5: =+AL5-E5 -> #REF! | AN5: =+AM5/AL5 -> #REF!
A6: 5 | B6: 11-A-9499-01 | D6: =IFERROR(VLOOKUP(B6,'REQ. PINTADO'!B:C,2,0),0) -> 0 | E6: =+AJ6 -> #REF! | F6: 14gacr | G6: DECAPADO | H6: 1.75 | I6: 7.56 | J6: 0.075 | K6: 0.29 | L6: =+M6*2.2/K6 -> 41.714418 | M6: =+VLOOKUP(F6,Material!$H$2:$M$17,6,FALSE)*H6*I6*(1+Material!$K$14) -> 5.4987187 | N6: =+N5 -> T5.0 | O6: =+VLOOKUP(N6,[3]Material!$A$3:$B$58,2,FALSE) -> 5000 | P6: ACERO A36 | Q6: =+VLOOKUP(F6,[3]Material!$C$2:$E$12,2,FALSE) -> Cal 14 | R6: =+IF(P6="ACERO A36",VLOOKUP(Q6,'[3]Velocidades Std 1500 w'!$B$2:$F$15,5,FALSE),IF(P6="INOXIDABLE",VLOOKUP(Q6,'[3]Velocidades Std 1500 w'!$B$17:$F$28,5,FALSE),IF(P6="ALUMINIO",VLOOKUP(Q6,'[3]Velocidades Std 1500 w'!$B$30:$F$38,5,FALSE)))) -> 2.0080321e-06 | S6: =+R6*O6 -> 0.010040161 | T6: =+R6*U6*3600 -> 4.4574246 | U6: =(+I6*2+H6*2+W6*1.5)*25.4*1.05 -> 616.6104 | V6: =+U6*S6 -> 6.1908675 | W6: 3 | X6: =+IF(P6="ACERO A36",VLOOKUP(Q6,'[3]Tiempo Objeto'!$B$2:$C$12,2,FALSE),IF(P6="INOXIDABLE",VLOOKUP(Q6,'[3]Tiempo Objeto'!$B$14:$C$22,2,FALSE),IF(P6="ALUMINIO",VLOOKUP(Q6,'[3]Tiempo Objeto'!$B$24:$C$32,2,FALSE)))) -> 0.31333333 | Y6: =+X6*W6 -> 0.94 | Z6: =+Y6*O6/3600 -> 1.3055556 | AA6: 18 | AB6: =+AA6*Analisis!$J$6 -> 450 | AC6: 0 | AD6: =30*AC6+AC6*$D6*1.5 -> 0 | AE6: =+AC6*Analisis!$J$7 -> 0 | AF6: =+H6*0.0254*I6*0.0254*2*(1+[3]Analisis!$G$2) -> 0.021338667 | AG6: =+AF6*Analisis!$J$8 -> 2.2735842 | AH6: =+AE6+AB6+Z6+V6+M6+AG6 -> 465.26873 | AI6: =+AH6/(1-Analisis!#REF!) -> #REF! | AJ6: =+AI6/(1-0.07) -> #REF! | AK6: =+AJ6*D6 -> #REF! | AL6: =+VLOOKUP(B6,#REF!,2,FALSE) -> #REF! | AM6: =+AL6-E6 -> #REF! | AN6: =+AM6/AL6 -> #REF!
A7: 6 | B7: 11-A-9524-01 | D7: =IFERROR(VLOOKUP(B7,'REQ. PINTADO'!B:C,2,0),0) -> 0 | E7: =+AJ7 -> #REF! | F7: 12gacr | G7: DECAPADO | H7: 8.76 | I7: 16.41 | J7: 0.105 | K7: 4 | L7: =+M7*2.2/K7 -> 29.677604 | M7: =+VLOOKUP(F7,Material!$H$2:$M$17,6,FALSE)*H7*I7*(1+Material!$K$14) -> 53.95928 | N7: =+N6 -> T5.0 | O7: =+VLOOKUP(N7,[3]Material!$A$3:$B$58,2,FALSE) -> 5000 | P7: ACERO A36 | Q7: =+VLOOKUP(F7,[3]Material!$C$2:$E$12,2,FALSE) -> Cal 12 | R7: =+IF(P7="ACERO A36",VLOOKUP(Q7,'[3]Velocidades Std 1500 w'!$B$2:$F$15,5,FALSE),IF(P7="INOXIDABLE",VLOOKUP(Q7,'[3]Velocidades Std 1500 w'!$B$17:$F$28,5,FALSE),IF(P7="ALUMINIO",VLOOKUP(Q7,'[3]Velocidades Std 1500 w'!$B$30:$F$38,5,FALSE)))) -> 4.3859649e-06 | S7: =+R7*O7 -> 0.021929825 | T7: =+R7*U7*3600 -> 36.358228 | U7: =(+I7*2+H7*2+W7*1.5)*25.4*1.05 -> 2302.6878 | V7: =+U7*S7 -> 50.497539 | W7: 24 | X7: =+IF(P7="ACERO A36",VLOOKUP(Q7,'[3]Tiempo Objeto'!$B$2:$C$12,2,FALSE),IF(P7="INOXIDABLE",VLOOKUP(Q7,'[3]Tiempo Objeto'!$B$14:$C$22,2,FALSE),IF(P7="ALUMINIO",VLOOKUP(Q7,'[3]Tiempo Objeto'!$B$24:$C$32,2,FALSE)))) -> 0.61333333 | Y7: =+X7*W7 -> 14.72 | Z7: =+Y7*O7/3600 -> 20.444444 | AA7: 3 | AB7: =+AA7*Analisis!$J$6 -> 75 | AC7: 0 | AD7: =30*AC7+AC7*$D7*1.5 -> 0 | AE7: =+AC7*Analisis!$J$7 -> 0 | AF7: =+H7*0.0254*I7*0.0254*2*(1+[3]Analisis!$G$2) -> 0.23185696 | AG7: =+AF7*Analisis!$J$8 -> 24.703807 | AH7: =+AE7+AB7+Z7+V7+M7+AG7 -> 224.60507 | AI7: =+AH7/(1-Analisis!#REF!) -> #REF! | AJ7: =+AI7/(1-0.07) -> #REF! | AK7: =+AJ7*D7 -> #REF! | AL7: =+VLOOKUP(B7,#REF!,2,FALSE) -> #REF! | AM7: =+AL7-E7 -> #REF! | AN7: =+AM7/AL7 -> #REF!
A8: 7 | B8: 11-A-9524-02 | D8: =IFERROR(VLOOKUP(B8,'REQ. PINTADO'!B:C,2,0),0) -> 0 | E8: =+AJ8 -> 224.98764 | F8: 12gacr | G8: DECAPADO | H8: 8.76 | I8: 26.41 | J8: 0.105 | K8: 6 | L8: =+M8*2.2/K8 -> 31.841785 | M8: =+VLOOKUP(F8,Material!$H$2:$M$17,6,FALSE)*H8*I8*(1+Material!$K$14) -> 86.841231 | N8: =+N7 -> T5.0 | O8: =+VLOOKUP(N8,[3]Material!$A$3:$B$58,2,FALSE) -> 5000 | P8: ACERO A36 | Q8: =+VLOOKUP(F8,[3]Material!$C$2:$E$12,2,FALSE) -> Cal 12 | R8: =+IF(P8="ACERO A36",VLOOKUP(Q8,'[3]Velocidades Std 1500 w'!$B$2:$F$15,5,FALSE),IF(P8="INOXIDABLE",VLOOKUP(Q8,'[3]Velocidades Std 1500 w'!$B$17:$F$28,5,FALSE),IF(P8="ALUMINIO",VLOOKUP(Q8,'[3]Velocidades Std 1500 w'!$B$30:$F$38,5,FALSE)))) -> 4.3859649e-06 | S8: =+R8*O8 -> 0.021929825 | T8: =+R8*U8*3600 -> 44.780334 | U8: =(+I8*2+H8*2+W8*1.5)*25.4*1.05 -> 2836.0878 | V8: =+U8*S8 -> 62.194908 | W8: 24 | X8: =+IF(P8="ACERO A36",VLOOKUP(Q8,'[3]Tiempo Objeto'!$B$2:$C$12,2,FALSE),IF(P8="INOXIDABLE",VLOOKUP(Q8,'[3]Tiempo Objeto'!$B$14:$C$22,2,FALSE),IF(P8="ALUMINIO",VLOOKUP(Q8,'[3]Tiempo Objeto'!$B$24:$C$32,2,FALSE)))) -> 0.61333333 | Y8: =+X8*W8 -> 14.72 | Z8: =+Y8*O8/3600 -> 20.444444 | AA8: 0 | AB8: =+AA8*Analisis!$J$6 -> 0 | AC8: 0 | AD8: =30*AC8+AC8*$D8*1.5 -> 0 | AE8: =+AC8*Analisis!$J$7 -> 0 | AF8: =+H8*0.0254*I8*0.0254*2*(1+[3]Analisis!$G$2) -> 0.373147 | AG8: =+AF8*Analisis!$J$8 -> 39.757924 | AH8: =+AE8+AB8+Z8+V8+M8+AG8 -> 209.23851 | AI8: =+AH8/(1-Analisis!G13) -> 209.23851 | AJ8: =+AI8/(1-0.07) -> 224.98764 | AK8: =+AJ8*D8 -> 0 | AL8: =+VLOOKUP(B8,#REF!,2,FALSE) -> #REF! | AM8: =+AL8-E8 -> #REF! | AN8: =+AM8/AL8 -> #REF!
A9: 8 | B9: 11-A-9556-01 | D9: =IFERROR(VLOOKUP(B9,'REQ. PINTADO'!B:C,2,0),0) -> 0 | E9: =+AJ9 -> 134.29851 | F9: 12gacr | G9: DECAPADO | H9: 1.75 | I9: 7.49 | J9: 0.105 | K9: 0.4 | L9: =+M9*2.2/K9 -> 27.060513 | M9: =+VLOOKUP(F9,Material!$H$2:$M$17,6,FALSE)*H9*I9*(1+Material!$K$14) -> 4.9200932 | N9: =+N8 -> T5.0 | O9: =+VLOOKUP(N9,[3]Material!$A$3:$B$58,2,FALSE) -> 5000 | P9: ACERO A36 | Q9: =+VLOOKUP(F9,[3]Material!$C$2:$E$12,2,FALSE) -> Cal 12 | R9: =+IF(P9="ACERO A36",VLOOKUP(Q9,'[3]Velocidades Std 1500 w'!$B$2:$F$15,5,FALSE),IF(P9="INOXIDABLE",VLOOKUP(Q9,'[3]Velocidades Std 1500 w'!$B$17:$F$28,5,FALSE),IF(P9="ALUMINIO",VLOOKUP(Q9,'[3]Velocidades Std 1500 w'!$B$30:$F$38,5,FALSE)))) -> 4.3859649e-06 | S9: =+R9*O9 -> 0.021929825 | T9: =+R9*U9*3600 -> 10.308657 | U9: =(+I9*2+H9*2+W9*1.5)*25.4*1.05 -> 652.8816 | V9: =+U9*S9 -> 14.317579 | W9: 4 | X9: =+IF(P9="ACERO A36",VLOOKUP(Q9,'[3]Tiempo Objeto'!$B$2:$C$12,2,FALSE),IF(P9="INOXIDABLE",VLOOKUP(Q9,'[3]Tiempo Objeto'!$B$14:$C$22,2,FALSE),IF(P9="ALUMINIO",VLOOKUP(Q9,'[3]Tiempo Objeto'!$B$24:$C$32,2,FALSE)))) -> 0.61333333 | Y9: =+X9*W9 -> 2.4533333 | Z9: =+Y9*O9/3600 -> 3.4074074 | AA9: 4 | AB9: =+AA9*Analisis!$J$6 -> 100 | AC9: 0 | AD9: =30*AC9+AC9*$D9*1.5 -> 0 | AE9: =+AC9*Analisis!$J$7 -> 0 | AF9: =+H9*0.0254*I9*0.0254*2*(1+[3]Analisis!$G$2) -> 0.021141087 | AG9: =+AF9*Analisis!$J$8 -> 2.2525325 | AH9: =+AE9+AB9+Z9+V9+M9+AG9 -> 124.89761 | AI9: =+AH9/(1-Analisis!G14) -> 124.89761 | AJ9: =+AI9/(1-0.07) -> 134.29851 | AK9: =+AJ9*D9 -> 0 | AL9: =+VLOOKUP(B9,#REF!,2,FALSE) -> #REF! | AM9: =+AL9-E9 -> #REF! | AN9: =+AM9/AL9 -> #REF!
A10: 9 | B10: 11-A-9559-01 | D10: =IFERROR(VLOOKUP(B10,'REQ. PINTADO'!B:C,2,0),0) -> 0 | E10: =+AJ10 -> 1202.954 | F10: 14gacr | G10: DECAPADO | H10: 108.95 | I10: 12.31 | J10: 0.105 | K10: 45.123 | L10: =+M10*2.2/K10 -> 27.177635 | M10: =+VLOOKUP(F10,Material!$H$2:$M$17,6,FALSE)*H10*I10*(1+Material!$K$14) -> 557.42565 | N10: =+N9 -> T5.0 | O10: =+VLOOKUP(N10,[3]Material!$A$3:$B$58,2,FALSE) -> 5000 | P10: ACERO A36 | Q10: =+VLOOKUP(F10,[3]Material!$C$2:$E$12,2,FALSE) -> Cal 14 | R10: =+IF(P10="ACERO A36",VLOOKUP(Q10,'[3]Velocidades Std 1500 w'!$B$2:$F$15,5,FALSE),IF(P10="INOXIDABLE",VLOOKUP(Q10,'[3]Velocidades Std 1500 w'!$B$17:$F$28,5,FALSE),IF(P10="ALUMINIO",VLOOKUP(Q10,'[3]Velocidades Std 1500 w'!$B$30:$F$38,5,FALSE)))) -> 2.0080321e-06 | S10: =+R10*O10 -> 0.010040161 | T10: =+R10*U10*3600 -> 52.25135 | U10: =(+I10*2+H10*2+W10*1.5)*25.4*1.05 -> 7228.1034 | V10: =+U10*S10 -> 72.571319 | W10: 19 | X10: =+IF(P10="ACERO A36",VLOOKUP(Q10,'[3]Tiempo Objeto'!$B$2:$C$12,2,FALSE),IF(P10="INOXIDABLE",VLOOKUP(Q10,'[3]Tiempo Objeto'!$B$14:$C$22,2,FALSE),IF(P10="ALUMINIO",VLOOKUP(Q10,'[3]Tiempo Objeto'!$B$24:$C$32,2,FALSE)))) -> 0.31333333 | Y10: =+X10*W10 -> 5.9533333 | Z10: =+Y10*O10/3600 -> 8.2685185 | AA10: 10 | AB10: =+AA10*Analisis!$J$6 -> 250 | AC10: 0 | AD10: =30*AC10+AC10*$D10*1.5 -> 0 | AE10: =+AC10*Analisis!$J$7 -> 0 | AF10: =+H10*0.0254*I10*0.0254*2*(1+[3]Analisis!$G$2) -> 2.1631804 | AG10: =+AF10*Analisis!$J$8 -> 230.48172 | AH10: =+AE10+AB10+Z10+V10+M10+AG10 -> 1118.7472 | AI10: =+AH10/(1-Analisis!G15) -> 1118.7472 | AJ10: =+AI10/(1-0.07) -> 1202.954 | AK10: =+AJ10*D10 -> 0 | AL10: =+VLOOKUP(B10,#REF!,2,FALSE) -> #REF! | AM10: =+AL10-E10 -> #REF! | AN10: =+AM10/AL10 -> #REF!
A11: 10 | B11: 11-A-9890-01 | D11: =IFERROR(VLOOKUP(B11,'REQ. PINTADO'!B:C,2,0),0) -> 0 | E11: =+AJ11 -> 112.96297 | F11: 12gacr | G11: DECAPADO | H11: 2.94 | I11: 7.09 | J11: 0.105 | K11: 45.123 | L11: =+M11*2.2/K11 -> 0.38147997 | M11: =+VLOOKUP(F11,Material!$H$2:$M$17,6,FALSE)*H11*I11*(1+Material!$K$14) -> 7.8243276 | N11: =+N10 -> T5.0 | O11: =+VLOOKUP(N11,[3]Material!$A$3:$B$58,2,FALSE) -> 5000 | P11: ACERO A36 | Q11: =+VLOOKUP(F11,[3]Material!$C$2:$E$12,2,FALSE) -> Cal 12 | R11: =+IF(P11="ACERO A36",VLOOKUP(Q11,'[3]Velocidades Std 1500 w'!$B$2:$F$15,5,FALSE),IF(P11="INOXIDABLE",VLOOKUP(Q11,'[3]Velocidades Std 1500 w'!$B$17:$F$28,5,FALSE),IF(P11="ALUMINIO",VLOOKUP(Q11,'[3]Velocidades Std 1500 w'!$B$30:$F$38,5,FALSE)))) -> 4.3859649e-06 | S11: =+R11*O11 -> 0.021929825 | T11: =+R11*U11*3600 -> 10.974003 | U11: =(+I11*2+H11*2+W11*1.5)*25.4*1.05 -> 695.0202 | V11: =+U11*S11 -> 15.241671 | W11: 4 | X11: =+IF(P11="ACERO A36",VLOOKUP(Q11,'[3]Tiempo Objeto'!$B$2:$C$12,2,FALSE),IF(P11="INOXIDABLE",VLOOKUP(Q11,'[3]Tiempo Objeto'!$B$14:$C$22,2,FALSE),IF(P11="ALUMINIO",VLOOKUP(Q11,'[3]Tiempo Objeto'!$B$24:$C$32,2,FALSE)))) -> 0.61333333 | Y11: =+X11*W11 -> 2.4533333 | Z11: =+Y11*O11/3600 -> 3.4074074 | AA11: 3 | AB11: =+AA11*Analisis!$J$6 -> 75 | AC11: 0 | AD11: =30*AC11+AC11*$D11*1.5 -> 0 | AE11: =+AC11*Analisis!$J$7 -> 0 | AF11: =+H11*0.0254*I11*0.0254*2*(1+[3]Analisis!$G$2) -> 0.033620255 | AG11: =+AF11*Analisis!$J$8 -> 3.5821582 | AH11: =+AE11+AB11+Z11+V11+M11+AG11 -> 105.05556 | AI11: =+AH11/(1-Analisis!G16) -> 105.05556 | AJ11: =+AI11/(1-0.07) -> 112.96297 | AK11: =+AJ11*D11 -> 0 | AL11: =+VLOOKUP(B11,#REF!,2,FALSE) -> #REF! | AM11: =+AL11-E11 -> #REF! | AN11: =+AM11/AL11 -> #REF!
A12: 11 | B12: 11-A-9934-01 | D12: =IFERROR(VLOOKUP(B12,'REQ. PINTADO'!B:C,2,0),0) -> 0 | E12: =+AJ12 -> 213.77401 | F12: 14gacr | G12: DECAPADO | H12: 21.94 | I12: 5.55 | J12: 0.105 | K12: 3.72 | L12: =+M12*2.2/K12 -> 29.930296 | M12: =+VLOOKUP(F12,Material!$H$2:$M$17,6,FALSE)*H12*I12*(1+Material!$K$14) -> 50.609409 | N12: =+N11 -> T5.0 | O12: =+VLOOKUP(N12,[3]Material!$A$3:$B$58,2,FALSE) -> 5000 | P12: ACERO A36 | Q12: =+VLOOKUP(F12,[3]Material!$C$2:$E$12,2,FALSE) -> Cal 14 | R12: =+IF(P12="ACERO A36",VLOOKUP(Q12,'[3]Velocidades Std 1500 w'!$B$2:$F$15,5,FALSE),IF(P12="INOXIDABLE",VLOOKUP(Q12,'[3]Velocidades Std 1500 w'!$B$17:$F$28,5,FALSE),IF(P12="ALUMINIO",VLOOKUP(Q12,'[3]Velocidades Std 1500 w'!$B$30:$F$38,5,FALSE)))) -> 2.0080321e-06 | S12: =+R12*O12 -> 0.010040161 | T12: =+R12*U12*3600 -> 14.937771 | U12: =(+I12*2+H12*2+W12*1.5)*25.4*1.05 -> 2066.3916 | V12: =+U12*S12 -> 20.746904 | W12: 15 | X12: =+IF(P12="ACERO A36",VLOOKUP(Q12,'[3]Tiempo Objeto'!$B$2:$C$12,2,FALSE),IF(P12="INOXIDABLE",VLOOKUP(Q12,'[3]Tiempo Objeto'!$B$14:$C$22,2,FALSE),IF(P12="ALUMINIO",VLOOKUP(Q12,'[3]Tiempo Objeto'!$B$24:$C$32,2,FALSE)))) -> 0.31333333 | Y12: =+X12*W12 -> 4.7 | Z12: =+Y12*O12/3600 -> 6.5277778 | AA12: 4 | AB12: =+AA12*Analisis!$J$6 -> 100 | AC12: 0 | AD12: =30*AC12+AC12*$D12*1.5 -> 0 | AE12: =+AC12*Analisis!$J$7 -> 0 | AF12: =+H12*0.0254*I12*0.0254*2*(1+[3]Analisis!$G$2) -> 0.19639799 | AG12: =+AF12*Analisis!$J$8 -> 20.925739 | AH12: =+AE12+AB12+Z12+V12+M12+AG12 -> 198.80983 | AI12: =+AH12/(1-Analisis!G17) -> 198.80983 | AJ12: =+AI12/(1-0.07) -> 213.77401 | AK12: =+AJ12*D12 -> 0 | AL12: =+VLOOKUP(B12,#REF!,2,FALSE) -> #REF! | AM12: =+AL12-E12 -> #REF! | AN12: =+AM12/AL12 -> #REF!
A13: 12 | B13: 11-A-9934-02 | D13: =IFERROR(VLOOKUP(B13,'REQ. PINTADO'!B:C,2,0),0) -> 0 | E13: =+AJ13 -> 308.355 | F13: 14gacr | G13: DECAPADO | H13: 31.94 | I13: 5.55 | J13: 0.105 | K13: 5.41 | L13: =+M13*2.2/K13 -> 29.960908 | M13: =+VLOOKUP(F13,Material!$H$2:$M$17,6,FALSE)*H13*I13*(1+Material!$K$14) -> 73.676597 | N13: =+N12 -> T5.0 | O13: =+VLOOKUP(N13,[3]Material!$A$3:$B$58,2,FALSE) -> 5000 | P13: ACERO A36 | Q13: =+VLOOKUP(F13,[3]Material!$C$2:$E$12,2,FALSE) -> Cal 14 | R13: =+IF(P13="ACERO A36",VLOOKUP(Q13,'[3]Velocidades Std 1500 w'!$B$2:$F$15,5,FALSE),IF(P13="INOXIDABLE",VLOOKUP(Q13,'[3]Velocidades Std 1500 w'!$B$17:$F$28,5,FALSE),IF(P13="ALUMINIO",VLOOKUP(Q13,'[3]Velocidades Std 1500 w'!$B$30:$F$38,5,FALSE)))) -> 2.0080321e-06 | S13: =+R13*O13 -> 0.010040161 | T13: =+R13*U13*3600 -> 18.793674 | U13: =(+I13*2+H13*2+W13*1.5)*25.4*1.05 -> 2599.7916 | V13: =+U13*S13 -> 26.102325 | W13: 15 | X13: =+IF(P13="ACERO A36",VLOOKUP(Q13,'[3]Tiempo Objeto'!$B$2:$C$12,2,FALSE),IF(P13="INOXIDABLE",VLOOKUP(Q13,'[3]Tiempo Objeto'!$B$14:$C$22,2,FALSE),IF(P13="ALUMINIO",VLOOKUP(Q13,'[3]Tiempo Objeto'!$B$24:$C$32,2,FALSE)))) -> 0.31333333 | Y13: =+X13*W13 -> 4.7 | Z13: =+Y13*O13/3600 -> 6.5277778 | AA13: 6 | AB13: =+AA13*Analisis!$J$6 -> 150 | AC13: 0 | AD13: =30*AC13+AC13*$D13*1.5 -> 0 | AE13: =+AC13*Analisis!$J$7 -> 0 | AF13: =+H13*0.0254*I13*0.0254*2*(1+[3]Analisis!$G$2) -> 0.28591394 | AG13: =+AF13*Analisis!$J$8 -> 30.46345 | AH13: =+AE13+AB13+Z13+V13+M13+AG13 -> 286.77015 | AI13: =+AH13/(1-Analisis!G18) -> 286.77015 | AJ13: =+AI13/(1-0.07) -> 308.355 | AK13: =+AJ13*D13 -> 0 | AL13: =+VLOOKUP(B13,#REF!,2,FALSE) -> #REF! | AM13: =+AL13-E13 -> #REF! | AN13: =+AM13/AL13 -> #REF!
A14: 12 | B14: 11-A-9934-03 | D14: =IFERROR(VLOOKUP(B14,'REQ. PINTADO'!B:C,2,0),0) -> 0 | E14: =+AJ14 -> 349.17255 | F14: 14gacr | G14: DECAPADO | H14: 41.94 | I14: 5.55 | J14: 0.105 | K14: 7.1 | L14: =+M14*2.2/K14 -> 29.976947 | M14: =+VLOOKUP(F14,Material!$H$2:$M$17,6,FALSE)*H14*I14*(1+Material!$K$14) -> 96.743784 | N14: =+N13 -> T5.0 | O14: =+VLOOKUP(N14,[3]Material!$A$3:$B$58,2,FALSE) -> 5000 | P14: ACERO A36 | Q14: =+VLOOKUP(F14,[3]Material!$C$2:$E$12,2,FALSE) -> Cal 14 | R14: =+IF(P14="ACERO A36",VLOOKUP(Q14,'[3]Velocidades Std 1500 w'!$B$2:$F$15,5,FALSE),IF(P14="INOXIDABLE",VLOOKUP(Q14,'[3]Velocidades Std 1500 w'!$B$17:$F$28,5,FALSE),IF(P14="ALUMINIO",VLOOKUP(Q14,'[3]Velocidades Std 1500 w'!$B$30:$F$38,5,FALSE)))) -> 2.0080321e-06 | S14: =+R14*O14 -> 0.010040161 | T14: =+R14*U14*3600 -> 22.649578 | U14: =(+I14*2+H14*2+W14*1.5)*25.4*1.05 -> 3133.1916 | V14: =+U14*S14 -> 31.457747 | W14: 15 | X14: =+IF(P14="ACERO A36",VLOOKUP(Q14,'[3]Tiempo Objeto'!$B$2:$C$12,2,FALSE),IF(P14="INOXIDABLE",VLOOKUP(Q14,'[3]Tiempo Objeto'!$B$14:$C$22,2,FALSE),IF(P14="ALUMINIO",VLOOKUP(Q14,'[3]Tiempo Objeto'!$B$24:$C$32,2,FALSE)))) -> 0.31333333 | Y14: =+X14*W14 -> 4.7 | Z14: =+Y14*O14/3600 -> 6.5277778 | AA14: 6 | AB14: =+AA14*Analisis!$J$6 -> 150 | AC14: 0 | AD14: =30*AC14+AC14*$D14*1.5 -> 0 | AE14: =+AC14*Analisis!$J$7 -> 0 | AF14: =+H14*0.0254*I14*0.0254*2*(1+[3]Analisis!$G$2) -> 0.37542989 | AG14: =+AF14*Analisis!$J$8 -> 40.001161 | AH14: =+AE14+AB14+Z14+V14+M14+AG14 -> 324.73047 | AI14: =+AH14/(1-Analisis!G19) -> 324.73047 | AJ14: =+AI14/(1-0.07) -> 349.17255 | AK14: =+AJ14*D14 -> 0 | AL14: =+VLOOKUP(B14,#REF!,2,FALSE) -> #REF! | AM14: =+AL14-E14 -> #REF! | AN14: =+AM14/AL14 -> #REF!
A15: 12 | B15: 11-A-9934-04 | D15: =IFERROR(VLOOKUP(B15,'REQ. PINTADO'!B:C,2,0),0) -> 0 | E15: =+AJ15 -> 332.96798 | F15: 14gacr | G15: DECAPADO | H15: 37.97 | I15: 5.55 | J15: 0.105 | K15: 6.43 | L15: =+M15*2.2/K15 -> 29.967254 | M15: =+VLOOKUP(F15,Material!$H$2:$M$17,6,FALSE)*H15*I15*(1+Material!$K$14) -> 87.586111 | N15: =+N14 -> T5.0 | O15: =+VLOOKUP(N15,[3]Material!$A$3:$B$58,2,FALSE) -> 5000 | P15: ACERO A36 | Q15: =+VLOOKUP(F15,[3]Material!$C$2:$E$12,2,FALSE) -> Cal 14 | R15: =+IF(P15="ACERO A36",VLOOKUP(Q15,'[3]Velocidades Std 1500 w'!$B$2:$F$15,5,FALSE),IF(P15="INOXIDABLE",VLOOKUP(Q15,'[3]Velocidades Std 1500 w'!$B$17:$F$28,5,FALSE),IF(P15="ALUMINIO",VLOOKUP(Q15,'[3]Velocidades Std 1500 w'!$B$30:$F$38,5,FALSE)))) -> 2.0080321e-06 | S15: =+R15*O15 -> 0.010040161 | T15: =+R15*U15*3600 -> 21.118784 | U15: =(+I15*2+H15*2+W15*1.5)*25.4*1.05 -> 2921.4318 | V15: =+U15*S15 -> 29.331645 | W15: 15 | X15: =+IF(P15="ACERO A36",VLOOKUP(Q15,'[3]Tiempo Objeto'!$B$2:$C$12,2,FALSE),IF(P15="INOXIDABLE",VLOOKUP(Q15,'[3]Tiempo Objeto'!$B$14:$C$22,2,FALSE),IF(P15="ALUMINIO",VLOOKUP(Q15,'[3]Tiempo Objeto'!$B$24:$C$32,2,FALSE)))) -> 0.31333333 | Y15: =+X15*W15 -> 4.7 | Z15: =+Y15*O15/3600 -> 6.5277778 | AA15: 6 | AB15: =+AA15*Analisis!$J$6 -> 150 | AC15: 0 | AD15: =30*AC15+AC15*$D15*1.5 -> 0 | AE15: =+AC15*Analisis!$J$7 -> 0 | AF15: =+H15*0.0254*I15*0.0254*2*(1+[3]Analisis!$G$2) -> 0.33989206 | AG15: =+AF15*Analisis!$J$8 -> 36.21469 | AH15: =+AE15+AB15+Z15+V15+M15+AG15 -> 309.66022 | AI15: =+AH15/(1-Analisis!G20) -> 309.66022 | AJ15: =+AI15/(1-0.07) -> 332.96798 | AK15: =+AJ15*D15 -> 0 | AL15: =+VLOOKUP(B15,#REF!,2,FALSE) -> #REF! | AM15: =+AL15-E15 -> #REF! | AN15: =+AM15/AL15 -> #REF!
A16: 12 | B16: 11-A-9934-05 | D16: =IFERROR(VLOOKUP(B16,'REQ. PINTADO'!B:C,2,0),0) -> 0 | E16: =+AJ16 -> 341.00904 | F16: 14gacr | G16: DECAPADO | H16: 39.94 | I16: 5.55 | J16: 0.105 | K16: 6.76 | L16: =+M16*2.2/K16 -> 29.983249 | M16: =+VLOOKUP(F16,Material!$H$2:$M$17,6,FALSE)*H16*I16*(1+Material!$K$14) -> 92.130347 | N16: =+N15 -> T5.0 | O16: =+VLOOKUP(N16,[3]Material!$A$3:$B$58,2,FALSE) -> 5000 | P16: ACERO A36 | Q16: =+VLOOKUP(F16,[3]Material!$C$2:$E$12,2,FALSE) -> Cal 14 | R16: =+IF(P16="ACERO A36",VLOOKUP(Q16,'[3]Velocidades Std 1500 w'!$B$2:$F$15,5,FALSE),IF(P16="INOXIDABLE",VLOOKUP(Q16,'[3]Velocidades Std 1500 w'!$B$17:$F$28,5,FALSE),IF(P16="ALUMINIO",VLOOKUP(Q16,'[3]Velocidades Std 1500 w'!$B$30:$F$38,5,FALSE)))) -> 2.0080321e-06 | S16: =+R16*O16 -> 0.010040161 | T16: =+R16*U16*3600 -> 21.878397 | U16: =(+I16*2+H16*2+W16*1.5)*25.4*1.05 -> 3026.5116 | V16: =+U16*S16 -> 30.386663 | W16: 15 | X16: =+IF(P16="ACERO A36",VLOOKUP(Q16,'[3]Tiempo Objeto'!$B$2:$C$12,2,FALSE),IF(P16="INOXIDABLE",VLOOKUP(Q16,'[3]Tiempo Objeto'!$B$14:$C$22,2,FALSE),IF(P16="ALUMINIO",VLOOKUP(Q16,'[3]Tiempo Objeto'!$B$24:$C$32,2,FALSE)))) -> 0.31333333 | Y16: =+X16*W16 -> 4.7 | Z16: =+Y16*O16/3600 -> 6.5277778 | AA16: 6 | AB16: =+AA16*Analisis!$J$6 -> 150 | AC16: 0 | AD16: =30*AC16+AC16*$D16*1.5 -> 0 | AE16: =+AC16*Analisis!$J$7 -> 0 | AF16: =+H16*0.0254*I16*0.0254*2*(1+[3]Analisis!$G$2) -> 0.3575267 | AG16: =+AF16*Analisis!$J$8 -> 38.093619 | AH16: =+AE16+AB16+Z16+V16+M16+AG16 -> 317.13841 | AI16: =+AH16/(1-Analisis!G21) -> 317.13841 | AJ16: =+AI16/(1-0.07) -> 341.00904 | AK16: =+AJ16*D16 -> 0 | AL16: =+VLOOKUP(B16,#REF!,2,FALSE) -> #REF! | AM16: =+AL16-E16 -> #REF! | AN16: =+AM16/AL16 -> #REF!
A17: 12 | B17: 11-A-9934-06 | D17: =IFERROR(VLOOKUP(B17,'REQ. PINTADO'!B:C,2,0),0) -> 0 | E17: =+AJ17 -> 365.49957 | F17: 14gacr | G17: DECAPADO | H17: 45.94 | I17: 5.55 | J17: 0.105 | K17: 7.78 | L17: =+M17*2.2/K17 -> 29.965996 | M17: =+VLOOKUP(F17,Material!$H$2:$M$17,6,FALSE)*H17*I17*(1+Material!$K$14) -> 105.97066 | N17: =+N16 -> T5.0 | O17: =+VLOOKUP(N17,[3]Material!$A$3:$B$58,2,FALSE) -> 5000 | P17: ACERO A36 | Q17: =+VLOOKUP(F17,[3]Material!$C$2:$E$12,2,FALSE) -> Cal 14 | R17: =+IF(P17="ACERO A36",VLOOKUP(Q17,'[3]Velocidades Std 1500 w'!$B$2:$F$15,5,FALSE),IF(P17="INOXIDABLE",VLOOKUP(Q17,'[3]Velocidades Std 1500 w'!$B$17:$F$28,5,FALSE),IF(P17="ALUMINIO",VLOOKUP(Q17,'[3]Velocidades Std 1500 w'!$B$30:$F$38,5,FALSE)))) -> 2.0080321e-06 | S17: =+R17*O17 -> 0.010040161 | T17: =+R17*U17*3600 -> 24.191939 | U17: =(+I17*2+H17*2+W17*1.5)*25.4*1.05 -> 3346.5516 | V17: =+U17*S17 -> 33.599916 | W17: 15 | X17: =+IF(P17="ACERO A36",VLOOKUP(Q17,'[3]Tiempo Objeto'!$B$2:$C$12,2,FALSE),IF(P17="INOXIDABLE",VLOOKUP(Q17,'[3]Tiempo Objeto'!$B$14:$C$22,2,FALSE),IF(P17="ALUMINIO",VLOOKUP(Q17,'[3]Tiempo Objeto'!$B$24:$C$32,2,FALSE)))) -> 0.31333333 | Y17: =+X17*W17 -> 4.7 | Z17: =+Y17*O17/3600 -> 6.5277778 | AA17: 6 | AB17: =+AA17*Analisis!$J$6 -> 150 | AC17: 0 | AD17: =30*AC17+AC17*$D17*1.5 -> 0 | AE17: =+AC17*Analisis!$J$7 -> 0 | AF17: =+H17*0.0254*I17*0.0254*2*(1+[3]Analisis!$G$2) -> 0.41123627 | AG17: =+AF17*Analisis!$J$8 -> 43.816246 | AH17: =+AE17+AB17+Z17+V17+M17+AG17 -> 339.9146 | AI17: =+AH17/(1-Analisis!G22) -> 339.9146 | AJ17: =+AI17/(1-0.07) -> 365.49957 | AK17: =+AJ17*D17 -> 0 | AL17: =+VLOOKUP(B17,#REF!,2,FALSE) -> #REF! | AM17: =+AL17-E17 -> #REF! | AN17: =+AM17/AL17 -> #REF!
A18: 13 | B18: 11-A-9951-01 | D18: =IFERROR(VLOOKUP(B18,'REQ. PINTADO'!B:C,2,0),0) -> 0 | E18: =+AJ18 -> 174.19953 | F18: 12gacr | G18: DECAPADO | H18: 20.25 | I18: 6.08 | J18: 0.105 | K18: 4 | L18: =+M18*2.2/K18 -> 25.418198 | M18: =+VLOOKUP(F18,Material!$H$2:$M$17,6,FALSE)*H18*I18*(1+Material!$K$14) -> 46.214905 | N18: =+N17 -> T5.0 | O18: =+VLOOKUP(N18,[3]Material!$A$3:$B$58,2,FALSE) -> 5000 | P18: ACERO A36 | Q18: =+VLOOKUP(F18,[3]Material!$C$2:$E$12,2,FALSE) -> Cal 12 | R18: =+IF(P18="ACERO A36",VLOOKUP(Q18,'[3]Velocidades Std 1500 w'!$B$2:$F$15,5,FALSE),IF(P18="INOXIDABLE",VLOOKUP(Q18,'[3]Velocidades Std 1500 w'!$B$17:$F$28,5,FALSE),IF(P18="ALUMINIO",VLOOKUP(Q18,'[3]Velocidades Std 1500 w'!$B$30:$F$38,5,FALSE)))) -> 4.3859649e-06 | S18: =+R18*O18 -> 0.021929825 | T18: =+R18*U18*3600 -> 27.228666 | U18: =(+I18*2+H18*2+W18*1.5)*25.4*1.05 -> 1724.4822 | V18: =+U18*S18 -> 37.817592 | W18: 8 | X18: =+IF(P18="ACERO A36",VLOOKUP(Q18,'[3]Tiempo Objeto'!$B$2:$C$12,2,FALSE),IF(P18="INOXIDABLE",VLOOKUP(Q18,'[3]Tiempo Objeto'!$B$14:$C$22,2,FALSE),IF(P18="ALUMINIO",VLOOKUP(Q18,'[3]Tiempo Objeto'!$B$24:$C$32,2,FALSE)))) -> 0.61333333 | Y18: =+X18*W18 -> 4.9066667 | Z18: =+Y18*O18/3600 -> 6.8148148 | AA18: 2 | AB18: =+AA18*Analisis!$J$6 -> 50 | AC18: 0 | AD18: =30*AC18+AC18*$D18*1.5 -> 0 | AE18: =+AC18*Analisis!$J$7 -> 0 | AF18: =+H18*0.0254*I18*0.0254*2*(1+[3]Analisis!$G$2) -> 0.19858025 | AG18: =+AF18*Analisis!$J$8 -> 21.158253 | AH18: =+AE18+AB18+Z18+V18+M18+AG18 -> 162.00557 | AI18: =+AH18/(1-Analisis!G23) -> 162.00557 | AJ18: =+AI18/(1-0.07) -> 174.19953 | AK18: =+AJ18*D18 -> 0 | AL18: =+VLOOKUP(B18,#REF!,2,FALSE) -> #REF! | AM18: =+AL18-E18 -> #REF! | AN18: =+AM18/AL18 -> #REF!
A19: 14 | B19: 11-A-9960-01 | D19: =IFERROR(VLOOKUP(B19,'REQ. PINTADO'!B:C,2,0),0) -> 0 | E19: =+AJ19 -> 337.26844 | F19: 12gacr | G19: DECAPADO | H19: 2.7 | I19: 85.94 | J19: 0.105 | K19: 7.07 | L19: =+M19*2.2/K19 -> 27.102905 | M19: =+VLOOKUP(F19,Material!$H$2:$M$17,6,FALSE)*H19*I19*(1+Material!$K$14) -> 87.098881 | N19: =+N18 -> T5.0 | O19: =+VLOOKUP(N19,[3]Material!$A$3:$B$58,2,FALSE) -> 5000 | P19: ACERO A36 | Q19: =+VLOOKUP(F19,[3]Material!$C$2:$E$12,2,FALSE) -> Cal 12 | R19: =+IF(P19="ACERO A36",VLOOKUP(Q19,'[3]Velocidades Std 1500 w'!$B$2:$F$15,5,FALSE),IF(P19="INOXIDABLE",VLOOKUP(Q19,'[3]Velocidades Std 1500 w'!$B$17:$F$28,5,FALSE),IF(P19="ALUMINIO",VLOOKUP(Q19,'[3]Velocidades Std 1500 w'!$B$30:$F$38,5,FALSE)))) -> 4.3859649e-06 | S19: =+R19*O19 -> 0.021929825 | T19: =+R19*U19*3600 -> 104.97312 | U19: =(+I19*2+H19*2+W19*1.5)*25.4*1.05 -> 6648.2976 | V19: =+U19*S19 -> 145.796 | W19: 48 | X19: =+IF(P19="ACERO A36",VLOOKUP(Q19,'[3]Tiempo Objeto'!$B$2:$C$12,2,FALSE),IF(P19="INOXIDABLE",VLOOKUP(Q19,'[3]Tiempo Objeto'!$B$14:$C$22,2,FALSE),IF(P19="ALUMINIO",VLOOKUP(Q19,'[3]Tiempo Objeto'!$B$24:$C$32,2,FALSE)))) -> 0.61333333 | Y19: =+X19*W19 -> 29.44 | Z19: =+Y19*O19/3600 -> 40.888889 | AA19: 0 | AB19: =+AA19*Analisis!$J$6 -> 0 | AC19: 0 | AD19: =30*AC19+AC19*$D19*1.5 -> 0 | AE19: =+AC19*Analisis!$J$7 -> 0 | AF19: =+H19*0.0254*I19*0.0254*2*(1+[3]Analisis!$G$2) -> 0.37425409 | AG19: =+AF19*Analisis!$J$8 -> 39.875882 | AH19: =+AE19+AB19+Z19+V19+M19+AG19 -> 313.65965 | AI19: =+AH19/(1-Analisis!G24) -> 313.65965 | AJ19: =+AI19/(1-0.07) -> 337.26844 | AK19: =+AJ19*D19 -> 0 | AL19: =+VLOOKUP(B19,#REF!,2,FALSE) -> #REF! | AM19: =+AL19-E19 -> #REF! | AN19: =+AM19/AL19 -> #REF!
... A24: 19 | B24: 11-B-9034-01 | D24: =IFERROR(VLOOKUP(B24,'REQ. PINTADO'!B:C,2,0),0) -> 0 | E24: =+AJ24 -> 541.53134 | F24: 12gacr | G24: DECAPADO | H24: 19.04 | I24: 31.39 | J24: 0.105 | K24: 18.23 | L24: =+M24*2.2/K24 -> 27.073708 | M24: =+VLOOKUP(F24,Material!$H$2:$M$17,6,FALSE)*H24*I24*(1+Material!$K$14) -> 224.34259 | N24: =+N23 -> T5.0 | O24: =+VLOOKUP(N24,[3]Material!$A$3:$B$58,2,FALSE) -> 5000 | P24: ACERO A36 | Q24: =+VLOOKUP(F24,[3]Material!$C$2:$E$12,2,FALSE) -> Cal 12 | R24: =+IF(P24="ACERO A36",VLOOKUP(Q24,'[3]Velocidades Std 1500 w'!$B$2:$F$15,5,FALSE),IF(P24="INOXIDABLE",VLOOKUP(Q24,'[3]Velocidades Std 1500 w'!$B$17:$F$28,5,FALSE),IF(P24="ALUMINIO",VLOOKUP(Q24,'[3]Velocidades Std 1500 w'!$B$30:$F$38,5,FALSE)))) -> 4.3859649e-06 | S24: =+R24*O24 -> 0.021929825 | T24: =+R24*U24*3600 -> 85.425414 | U24: =(+I24*2+H24*2+W24*1.5)*25.4*1.05 -> 5410.2762 | V24: =+U24*S24 -> 118.64641 | W24: 68 | X24: =+IF(P24="ACERO A36",VLOOKUP(Q24,'[3]Tiempo Objeto'!$B$2:$C$12,2,FALSE),IF(P24="INOXIDABLE",VLOOKUP(Q24,'[3]Tiempo Objeto'!$B$14:$C$22,2,FALSE),IF(P24="ALUMINIO",VLOOKUP(Q24,'[3]Tiempo Objeto'!$B$24:$C$32,2,FALSE)))) -> 0.61333333 | Y24: =+X24*W24 -> 41.706667 | Z24: =+Y24*O24/3600 -> 57.925926 | AA24: 0 | AB24: =+AA24*Analisis!$J$6 -> 0 | AC24: 0 | AD24: =30*AC24+AC24*$D24*1.5 -> 0 | AE24: =+AC24*Analisis!$J$7 -> 0 | AF24: =+H24*0.0254*I24*0.0254*2*(1+[3]Analisis!$G$2) -> 0.96397485 | AG24: =+AF24*Analisis!$J$8 -> 102.70922 | AH24: =+AE24+AB24+Z24+V24+M24+AG24 -> 503.62414 | AI24: =+AH24/(1-Analisis!G29) -> 503.62414 | AJ24: =+AI24/(1-0.07) -> 541.53134 | AK24: =+AJ24*D24 -> 0 | AL24: =+VLOOKUP(B24,#REF!,2,FALSE) -> #REF! | AM24: =+AL24-E24 -> #REF! | AN24: =+AM24/AL24 -> #REF!
B25: 11-B-9034-02 | D25: =IFERROR(VLOOKUP(B25,'REQ. PINTADO'!B:C,2,0),0) -> 0 | E25: =+AJ25 -> 643.88881 | F25: 12gacr | G25: DECAPADO | H25: 24.04 | I25: 31.39 | J25: 0.105 | K25: 23.02 | L25: =+M25*2.2/K25 -> 27.07052 | M25: =+VLOOKUP(F25,Material!$H$2:$M$17,6,FALSE)*H25*I25*(1+Material!$K$14) -> 283.25608 | N25: =+N24 -> T5.0 | O25: =+VLOOKUP(N25,[3]Material!$A$3:$B$58,2,FALSE) -> 5000 | P25: ACERO A36 | Q25: =+VLOOKUP(F25,[3]Material!$C$2:$E$12,2,FALSE) -> Cal 12 | R25: =+IF(P25="ACERO A36",VLOOKUP(Q25,'[3]Velocidades Std 1500 w'!$B$2:$F$15,5,FALSE),IF(P25="INOXIDABLE",VLOOKUP(Q25,'[3]Velocidades Std 1500 w'!$B$17:$F$28,5,FALSE),IF(P25="ALUMINIO",VLOOKUP(Q25,'[3]Velocidades Std 1500 w'!$B$30:$F$38,5,FALSE)))) -> 4.3859649e-06 | S25: =+R25*O25 -> 0.021929825 | T25: =+R25*U25*3600 -> 90.899782 | U25: =(+I25*2+H25*2+W25*1.5)*25.4*1.05 -> 5756.9862 | V25: =+U25*S25 -> 126.2497 | W25: 70 | X25: =+IF(P25="ACERO A36",VLOOKUP(Q25,'[3]Tiempo Objeto'!$B$2:$C$12,2,FALSE),IF(P25="INOXIDABLE",VLOOKUP(Q25,'[3]Tiempo Objeto'!$B$14:$C$22,2,FALSE),IF(P25="ALUMINIO",VLOOKUP(Q25,'[3]Tiempo Objeto'!$B$24:$C$32,2,FALSE)))) -> 0.61333333 | Y25: =+X25*W25 -> 42.933333 | Z25: =+Y25*O25/3600 -> 59.62963 | AA25: 0 | AB25: =+AA25*Analisis!$J$6 -> 0 | AC25: 0 | AD25: =30*AC25+AC25*$D25*1.5 -> 0 | AE25: =+AC25*Analisis!$J$7 -> 0 | AF25: =+H25*0.0254*I25*0.0254*2*(1+[3]Analisis!$G$2) -> 1.2171195 | AG25: =+AF25*Analisis!$J$8 -> 129.68118 | AH25: =+AE25+AB25+Z25+V25+M25+AG25 -> 598.81659 | AI25: =+AH25/(1-Analisis!G30) -> 598.81659 | AJ25: =+AI25/(1-0.07) -> 643.88881 | AK25: =+AJ25*D25 -> 0 | AL25: =+VLOOKUP(B25,#REF!,2,FALSE) -> #REF! | AM25: =+AL25-E25 -> #REF! | AN25: =+AM25/AL25 -> #REF!
